Workbook

Sheet 1_Dashboard
A1: TABLERO INSTITUCIONAL BTC / ETH — DASHBOARD OPERATIVO v3
A2: v3: motor de liquidaciones ampliado. Valores de respaldo del 28-ago-2026: se sustituyen al refrescar (Datos > Actualizar todo).
A4: A. ESTADO EN VIVO
A5: Metrica | B5: Valor en vivo | C5: Fuente | D5: Manual (respaldo) | E5: EN USO | F5: Unidad | G5: Lectura | H5: Comentario
A6: Precio BTC (spot) | B6: =IF(ISNUMBER('2_Live_Precios'!G5),'2_Live_Precios'!G5,IF(COUNT('12_Datos_5m'!$F$5:$F$504)>0,INDEX('12_Datos_5m'!$F$5:$F$504,COUNT('12_Datos_5m'!$F$5:$F$504)),"n/d")) -> n/d | C6: Binance / 5m | D6: 77477 | E6: =IF(ISNUMBER(B6),B6,D6) -> 77477 | F6: USD | G6: =IF(NOT(ISNUMBER(E6)),"—",IF(E6>=$B$33,"ALCISTA",IF(E6>=$B$34,"NEUTRO-ALCISTA",IF(E6>=$B$35,"BISAGRA",IF(E6>=$B$36,"NEUTRO-BAJISTA",IF(E6>=$B$37,"ZONA SPRING","QUIEBRE")))))) -> BISAGRA | H6: Ultimo dato citado 28-ago: 77,477
A7: Precio ETH (spot) | B7: =IFERROR(IF(ISNUMBER('2_Live_Precios'!G6),'2_Live_Precios'!G6,"n/d"),"n/d") -> n/d | C7: Binance | D7: 2501 | E7: =IF(ISNUMBER(B7),B7,D7) -> 2501 | F7: USD | G7: =IF(NOT(ISNUMBER(E7)),"—",IF(E7>=2534,"SOBRE EMA200-3D",IF(E7>=2503,"SOBRE PIVOTE",IF(E7>=2471,"PIVOTE PERDIDO",IF(E7>=2426,"ZONA SPRING","VACIO <2400"))))) -> PIVOTE PERDIDO | H7: EMA200(3D) ~2,534 / pivote 2,503
A8: Funding BTC perp (8h) | B8: =IFERROR(IF(ISNUMBER('3_Live_Derivados'!G5),'3_Live_Derivados'!G5,"n/d"),"n/d") -> n/d | C8: Binance F. | D8: 4.8e-05 | E8: =IF(ISNUMBER(B8),B8,D8) -> 4.8e-05 | F8: frac | G8: =IF(NOT(ISNUMBER(E8)),"—",IF(E8>0.0003,"SOBRECALENTADO",IF(E8>0.0001,"POSITIVO",IF(E8>=-0.0001,"NEUTRO","NEGATIVO")))) -> NEUTRO | H8: Neutro = combustible alcista limpio
A9: Open Interest BTC (USD) | B9: =IFERROR(IF(ISNUMBER('3_Live_Derivados'!G7),'3_Live_Derivados'!G7*E6,"n/d"),"n/d") -> n/d | C9: Binance F. | D9: 56480000000 | E9: =IF(ISNUMBER(B9),B9,D9) -> 56480000000 | F9: USD | G9: =IF(NOT(ISNUMBER(E9)),"—",IF(E9>60000000000,"APALANCAMIENTO ALTO",IF(E9>45000000000,"NORMAL","DESAPALANCADO"))) -> NORMAL | H9: Solo Binance en vivo; manual = agregado 56.48B
A10: Long/Short cuentas BTC | B10: =IFERROR(IF(ISNUMBER('3_Live_Derivados'!G9),'3_Live_Derivados'!G9,"n/d"),"n/d") -> n/d | C10: Binance F. | D10: 1.98 | E10: =IF(ISNUMBER(B10),B10,D10) -> 1.98 | F10: ratio | G10: =IF(NOT(ISNUMBER(E10)),"—",IF(E10>2.2,"RETAIL MUY LARGO",IF(E10>1.6,"RETAIL LARGO",IF(E10>1.1,"EQUILIBRIO","RETAIL CORTO")))) -> RETAIL LARGO | H10: Retail. >2 = combustible bajista
A11: Long/Short top traders | B11: =IFERROR(IF(ISNUMBER('3_Live_Derivados'!G10),'3_Live_Derivados'!G10,"n/d"),"n/d") -> n/d | C11: Binance F. | D11: 1.35 | E11: =IF(ISNUMBER(B11),B11,D11) -> 1.35 | F11: ratio | G11: =IF(OR(NOT(ISNUMBER(E11)),NOT(ISNUMBER(E10))),"—",IF(E10-E11>0.5,"DIVERGENCIA FUERTE",IF(E10-E11>0.2,"DIVERGENCIA","ALINEADOS"))) -> DIVERGENCIA FUERTE | H11: Divergencia retail vs pro = seccion 2.5
A12: Fear & Greed | B12: =IFERROR(IF(ISNUMBER('4_Live_Macro'!G5),'4_Live_Macro'!G5,"n/d"),"n/d") -> n/d | C12: alternative.me | D12: 62 | E12: =IF(ISNUMBER(B12),B12,D12) -> 62 | F12: 0-100 | G12: =IF(NOT(ISNUMBER(E12)),"—",IF(E12>=75,"CODICIA EXTREMA",IF(E12>=55,"CODICIA",IF(E12>=45,"NEUTRO",IF(E12>=25,"MIEDO","MIEDO EXTREMO"))))) -> CODICIA | H12: Sentimiento agregado
A13: Rend. Tesoro 2A (%) | B13: =IFERROR(IF(ISNUMBER('4_Live_Macro'!G11),'4_Live_Macro'!G11,"n/d"),"n/d") -> n/d | C13: Tesoro EEUU | D13: 4.35 | E13: =IF(ISNUMBER(B13),B13,D13) -> 4.35 | F13: % | G13: =IF(NOT(ISNUMBER(E13)),"—",IF(E13>4.5,"RESTRICTIVO",IF(E13>4.2,"TENSION","ALIVIO"))) -> TENSION | H13: 28-ago: +12pb a 4.35%
A15: B. VEREDICTO — PROBABILIDADES (motor en hoja 6)
A16: Escenario | B16: Prob. base | C16: Ajuste en vivo | D16: PROB. FINAL | E16: Disparador | F16: Objetivo BTC | G16: Objetivo ETH | H16: Accion
A17: FALSA CAIDA (barrida y vuelta) | B17: 0.45 | C17: =IF(AND(ISNUMBER($E$10),$E$10>2),0.05,0) -> 0 | D17: =MAX(0,B17+C17)/(MAX(0,B17+C17)+MAX(0,B18+C18)+MAX(0,B19+C19)) -> 0.44117647 | E17: Perder 76,900 con volumen | F17: 74,000–76,500 | G17: 2,400–2,463 | H17: Esperar cascada >800M/h y comprar
A18: ABURRIMIENTO (rango) | B18: 0.28 | C18: =IF(AND(ISNUMBER($E$6),$E$6>=77250,$E$6<=79000),0.05,-0.02) -> 0.05 | D18: =MAX(0,B18+C18)/(MAX(0,B17+C17)+MAX(0,B18+C18)+MAX(0,B19+C19)) -> 0.32352941 | E18: Cierre semanal 77.25K–79K | F18: 76,900–80,000 | G18: 2,463–2,528 | H18: No operar; esperar ETF del lunes
A19: SUBIDA VIOLENTA (squeeze) | B19: 0.27 | C19: =IF(AND(ISNUMBER($E$6),$E$6>79000),0.08,-0.03) -> -0.03 | D19: =MAX(0,B19+C19)/(MAX(0,B17+C17)+MAX(0,B18+C18)+MAX(0,B19+C19)) -> 0.23529412 | E19: Cierre 4H >79,000 con OI al alza | F19: 81,033 → 82,400 | G19: 2,528 → 2,600 | H19: Perseguir largo con stop bajo 79,000
A20: ESCENARIO DOMINANTE | B20: =INDEX(A17:A19,MATCH(MAX(D17:D19),D17:D19,0)) -> FALSA CAIDA (barrida y vuelta) | F20: =MAX(D17:D19) -> 0.44117647 | G20: confianza
A22: C. SEMAFORO DE ENTRADA — 5 FILTROS DE ARBITRAJE POST-LIQUIDACION
A23: Filtro | B23: Umbral | C23: Valor actual | D23: Cumple | E23: Peso | F23: Puntos | G23: Fuente del dato | H23: Nota
A24: 1. Liquidaciones 1h | B24: >= 800 M USD | C24: =IF(N('5_Liquidaciones'!C7)>0,'5_Liquidaciones'!C7,'15_Liq_Reales'!D12+'15_Liq_Reales'!D13) -> 0 | D24: =IF(NOT(ISNUMBER(C24)),0,IF(C24>=800000000,1,0)) -> 0 | E24: 1 | F24: =D24*E24 -> 0 | G24: Coinglass manual > reales | H24: El tamano del rebote escala con esto
A25: 2. % del OI purgado | B25: >= 2.5% | C25: =IF(ISNUMBER('16_Fase_Cascada'!B14),'16_Fase_Cascada'!B14,'5_Liquidaciones'!C17) -> 0.0086345609 | D25: =IF(NOT(ISNUMBER(C25)),0,IF(C25>=0.025,1,0)) -> 0 | E25: 1.5 | F25: =D25*E25 -> 0 | G25: Hoja 16 > manual | H25: 0.86% hoy = purga incompleta
A26: 3. Dominancia de longs | B26: >= 75% | C26: =IF(ISNUMBER('15_Liq_Reales'!D18),'15_Liq_Reales'!D18,'5_Liquidaciones'!C16) -> 0.73818898 | D26: =IF(NOT(ISNUMBER(C26)),0,IF(C26>=0.75,1,0)) -> 0 | E26: 1 | F26: =D26*E26 -> 0 | G26: Hoja 15 > manual | H26: 74% hoy
A27: 4. Funding pre-caida | B27: <= 0.0100% | C27: =$E$8 -> 4.8e-05 | D27: =IF(NOT(ISNUMBER(C27)),0,IF(C27<=0.0001,1,0)) -> 1 | E27: 1 | F27: =D27*E27 -> 1 | G27: Binance API | H27: Neutro o negativo
A28: 5. Bid spot (ETF) | B28: Flujos positivos | C28: ='5_Liquidaciones'!C12 -> 1 | D28: =IF(NOT(ISNUMBER(C28)),0,IF(C28>=0.5,1,0)) -> 1 | E28: 0.5 | F28: =D28*E28 -> 0.5 | G28: Farside / manual | H28: 1 = si, 0 = no
A29: PUNTUACION TOTAL | B29: =SUM(F24:F28) -> 1.5 | C29: de 5.0 | D29: =IF(B29>=4,"ENTRAR",IF(B29>=3,"PREPARAR ORDEN","NO OPERAR")) -> NO OPERAR | G29: Regla: 4 de 5 filtros minimo
A31: D. MAPA DE NIVELES — DISTANCIA AL PRECIO EN VIVO
A32: Nivel BTC | B32: Precio | C32: Distancia % | D32: Tipo | E32: Significado | F32: Nivel ETH | G32: Precio | H32: Distancia % | I32: Tipo
A33: MA 50 semanas | B33: 81033 | C33: =IF(ISNUMBER($E$6),($E$6-B33)/B33,"n/d") -> -0.043883356 | D33: Resistencia mayor | E33: Sobre esto muere la tesis bajista | F33: EMA 200 (3D) | G33: 2534 | H33: =IF(ISNUMBER($E$7),($E$7-G33)/G33,"n/d") -> -0.013022889 | I33: Techo del rally
A34: Gatillo squeeze | B34: 79000 | C34: =IF(ISNUMBER($E$6),($E$6-B34)/B34,"n/d") -> -0.019278481 | D34: Disparador alcista | E34: Cierre 4H encima = plan B | F34: Pivote diario | G34: 2503 | H34: =IF(ISNUMBER($E$7),($E$7-G34)/G34,"n/d") -> -0.00079904115 | I34: El arbitro
A35: EMA 50 semanas | B35: 77250 | C35: =IF(ISNUMBER($E$6),($E$6-B35)/B35,"n/d") -> 0.0029385113 | D35: BISAGRA DEL CICLO | E35: Define tendencia mayor | F35: Soporte diario | G35: 2471 | H35: =IF(ISNUMBER($E$7),($E$7-G35)/G35,"n/d") -> 0.012140834 | I35: Perderlo gira bajista
A36: Minimo 28-ago | B36: 76909 | C36: =IF(ISNUMBER($E$6),($E$6-B36)/B36,"n/d") -> 0.0073853515 | D36: Soporte probado | E36: Separa falsa caida de caida real | F36: Zona Spring | G36: 2426 | H36: =IF(ISNUMBER($E$7),($E$7-G36)/G36,"n/d") -> 0.030915087 | I36: Soporte 5-10 dias
A37: Bolsa de liquidez | B37: 74000 | C37: =IF(ISNUMBER($E$6),($E$6-B37)/B37,"n/d") -> 0.046986486 | D37: Zona Spring | E37: Objetivo de barrida | F37: Ultima red | G37: 2400 | H37: =IF(ISNUMBER($E$7),($E$7-G37)/G37,"n/d") -> 0.042083333 | I37: Debajo: vacio a 2,250
A38: Quiebre estructural | B38: 73800 | C38: =IF(ISNUMBER($E$6),($E$6-B38)/B38,"n/d") -> 0.049823848 | D38: Invalidacion | E38: Debajo = distribucion confirmada | F38: Cluster mayor | G38: 2250 | H38: =IF(ISNUMBER($E$7),($E$7-G38)/G38,"n/d") -> 0.11155556 | I38: Siguiente liquidez
A40: F. LIQUIDACIONES EN VIVO — mapa estimado, prints reales y fase del ciclo
A41: Indicador | B41: Valor | E41: Lectura / contexto | H41: Hoja
A42: FASE DEL CICLO DE LIQUIDACION | B42: ='16_Fase_Cascada'!B28 -> SIN DATOS SUFICIENTES | E42: ='16_Fase_Cascada'!B29 -> Instala y refresca qBase5m (hoja 9). | H42: 16
A43: Cuadrante precio/OI 1h | B43: ='16_Fase_Cascada'!C12 -> n/d | E43: ="4h: "&'16_Fase_Cascada'!D12 -> 4h: n/d | H43: 16
A44: Purga de OI desde maximo 24h | B44: ='16_Fase_Cascada'!B14 -> n/d | E44: ="Umbral de limpieza: 2.5%" -> Umbral de limpieza: 2.5% | H44: 16
A45: Primer cluster LONG (precio) | B45: ='13_Mapa_Liq'!B32 -> n/d | E45: =IF(ISNUMBER('13_Mapa_Liq'!B33),"a "&ROUND('13_Mapa_Liq'!B33*100,1)&"% del precio","sin datos") -> sin datos | H45: 13
A46: Primer cluster SHORT (precio) | B46: ='13_Mapa_Liq'!B35 -> n/d | E46: =IF(ISNUMBER('13_Mapa_Liq'!B36),"a +"&ROUND('13_Mapa_Liq'!B36*100,1)&"% del precio","sin datos") -> sin datos | H46: 13
A47: Asimetria de combustible | B47: ='13_Mapa_Liq'!B25 -> n/d | E47: ='13_Mapa_Liq'!B26 -> SIN DATOS | H47: 13
A48: Combustible / volumen 5m | B48: ='13_Mapa_Liq'!B38 -> n/d | E48: =">3x = cascada autoalimentable" -> >3x = cascada autoalimentable | H48: 13
A49: Liquidaciones reales 1h (mercado est.) | B49: ='15_Liq_Reales'!D12+'15_Liq_Reales'!D13 -> 0 | E49: =IF(ISNUMBER('15_Liq_Reales'!D18),"Longs: "&ROUND('15_Liq_Reales'!D18*100,0)&"%","sin prints") -> sin prints | H49: 15
A50: Detector de cascada 5m | B50: ='15_Liq_Reales'!B55 -> SIN LIQUIDACIONES REGISTRADAS | E50: ="Pico/mediana: "&ROUND('15_Liq_Reales'!B54,1)&"x" -> Pico/mediana: 0x | H50: 15
A51: Donde se disparo la cascada (VWAP longs 1h) | B51: ='15_Liq_Reales'!D21 -> n/d | E51: ="Suele convertirse en soporte" -> Suele convertirse en soporte | H51: 15
A53: G. GUIA RAPIDA
A54: Amarillo | B54: Entrada manual o supuesto editable.
A55: Verde | B55: Valor calculado o traido en vivo desde una API publica.
A56: Refresh | B56: Datos > Actualizar todo (consultas Power Query de la hoja 9). En Excel Windows, F9 recalcula tambien WEBSERVICE.
A57: Arranque minimo | B57: Instala 3 consultas: qBase5m (mapa y fase), qLiqOKX (liquidaciones reales) y qDerivados. Con eso el tablero funciona.
A58: Regla de oro | B58: Solo se compra la caida con fase AGOTAMIENTO POST-CASCADA y 4 de 5 filtros. Cualquier otra combinacion es esperar.

Sheet 2_Live_Precios
A1: PRECIOS EN VIVO — APIs PUBLICAS SIN CLAVE
A2: Redundancia deliberada: cuatro fuentes independientes para el mismo precio. Si divergen mas de 0.3%, hay estres de liquidez.
A3: La columna E llama a la API. La F aisla el fragmento. La G convierte a numero. Si ves SIN CONEXION, habilita el acceso a datos externos o usa Power Query (hoja 9).
A4: Indicador | B4: Fuente | C4: URL del endpoint (publico, sin clave) | D4: Clave JSON | E4: Respuesta cruda (WEBSERVICE) | F4: Fragmento aislado | G4: VALOR | H4: Unidad | I4: Como se usa en el modelo
A5: BTC spot (Binance) | B5: Binance | C5: https://api.binance.com/api/v3/ticker/price?symbol=BTCUSDT | D5: price | E5: =IFERROR(webservice(C5),"SIN CONEXION") -> SIN CONEXION | F5: =IFERROR(MID(E5,SEARCH(""""&D5&""":",E5)+LEN(D5)+3,32),"n/d") -> n/d | G5: =IFERROR(VALUE(SUBSTITUTE(LEFT(SUBSTITUTE(SUBSTITUTE(F5,"""",""),"[",""),MIN(IFERROR(SEARCH(",",SUBSTITUTE(SUBSTITUTE(F5,"""",""),"[","")),99),IFERROR(SEARCH("}",SUBSTITUTE(SUBSTITUTE(F5,"""",""),"[","")),99),IFERROR(SEARCH("]",SUBSTITUTE(SUBSTITUTE(F5,"""",""),"[","")),99))-1),".",MID(1/2,2,1))),"n/d") -> n/d | H5: USD | I5: Precio principal del modelo. Alimenta E6 del dashboard.
A6: ETH spot (Binance) | B6: Binance | C6: https://api.binance.com/api/v3/ticker/price?symbol=ETHUSDT | D6: price | E6: =IFERROR(webservice(C6),"SIN CONEXION") -> SIN CONEXION | F6: =IFERROR(MID(E6,SEARCH(""""&D6&""":",E6)+LEN(D6)+3,32),"n/d") -> n/d | G6: =IFERROR(VALUE(SUBSTITUTE(LEFT(SUBSTITUTE(SUBSTITUTE(F6,"""",""),"[",""),MIN(IFERROR(SEARCH(",",SUBSTITUTE(SUBSTITUTE(F6,"""",""),"[","")),99),IFERROR(SEARCH("}",SUBSTITUTE(SUBSTITUTE(F6,"""",""),"[","")),99),IFERROR(SEARCH("]",SUBSTITUTE(SUBSTITUTE(F6,"""",""),"[","")),99))-1),".",MID(1/2,2,1))),"n/d") -> n/d | H6: USD | I6: Precio ETH. Alimenta E7 del dashboard.
A7: BTC var. 24h | B7: Binance | C7: https://api.binance.com/api/v3/ticker/24hr?symbol=BTCUSDT | D7: priceChangePercent | E7: =IFERROR(webservice(C7),"SIN CONEXION") -> SIN CONEXION | F7: =IFERROR(MID(E7,SEARCH(""""&D7&""":",E7)+LEN(D7)+3,32),"n/d") -> n/d | G7: =IFERROR(VALUE(SUBSTITUTE(LEFT(SUBSTITUTE(SUBSTITUTE(F7,"""",""),"[",""),MIN(IFERROR(SEARCH(",",SUBSTITUTE(SUBSTITUTE(F7,"""",""),"[","")),99),IFERROR(SEARCH("}",SUBSTITUTE(SUBSTITUTE(F7,"""",""),"[","")),99),IFERROR(SEARCH("]",SUBSTITUTE(SUBSTITUTE(F7,"""",""),"[","")),99))-1),".",MID(1/2,2,1))),"n/d") -> n/d | H7: % | I7: Magnitud del movimiento diario. -4% hoy.
A8: BTC minimo 24h | B8: Binance | C8: https://api.binance.com/api/v3/ticker/24hr?symbol=BTCUSDT | D8: lowPrice | E8: =IFERROR(webservice(C8),"SIN CONEXION") -> SIN CONEXION | F8: =IFERROR(MID(E8,SEARCH(""""&D8&""":",E8)+LEN(D8)+3,32),"n/d") -> n/d | G8: =IFERROR(VALUE(SUBSTITUTE(LEFT(SUBSTITUTE(SUBSTITUTE(F8,"""",""),"[",""),MIN(IFERROR(SEARCH(",",SUBSTITUTE(SUBSTITUTE(F8,"""",""),"[","")),99),IFERROR(SEARCH("}",SUBSTITUTE(SUBSTITUTE(F8,"""",""),"[","")),99),IFERROR(SEARCH("]",SUBSTITUTE(SUBSTITUTE(F8,"""",""),"[","")),99))-1),".",MID(1/2,2,1))),"n/d") -> n/d | H8: USD | I8: Cola de la mecha. Compara con la zona de captura.
A9: BTC maximo 24h | B9: Binance | C9: https://api.binance.com/api/v3/ticker/24hr?symbol=BTCUSDT | D9: highPrice | E9: =IFERROR(webservice(C9),"SIN CONEXION") -> SIN CONEXION | F9: =IFERROR(MID(E9,SEARCH(""""&D9&""":",E9)+LEN(D9)+3,32),"n/d") -> n/d | G9: =IFERROR(VALUE(SUBSTITUTE(LEFT(SUBSTITUTE(SUBSTITUTE(F9,"""",""),"[",""),MIN(IFERROR(SEARCH(",",SUBSTITUTE(SUBSTITUTE(F9,"""",""),"[","")),99),IFERROR(SEARCH("}",SUBSTITUTE(SUBSTITUTE(F9,"""",""),"[","")),99),IFERROR(SEARCH("]",SUBSTITUTE(SUBSTITUTE(F9,"""",""),"[","")),99))-1),".",MID(1/2,2,1))),"n/d") -> n/d | H9: USD | I9: Rango del dia = ATR intradia aproximado.
A10: BTC volumen 24h (quote) | B10: Binance | C10: https://api.binance.com/api/v3/ticker/24hr?symbol=BTCUSDT | D10: quoteVolume | E10: =IFERROR(webservice(C10),"SIN CONEXION") -> SIN CONEXION | F10: =IFERROR(MID(E10,SEARCH(""""&D10&""":",E10)+LEN(D10)+3,32),"n/d") -> n/d | G10: =IFERROR(VALUE(SUBSTITUTE(LEFT(SUBSTITUTE(SUBSTITUTE(F10,"""",""),"[",""),MIN(IFERROR(SEARCH(",",SUBSTITUTE(SUBSTITUTE(F10,"""",""),"[","")),99),IFERROR(SEARCH("}",SUBSTITUTE(SUBSTITUTE(F10,"""",""),"[","")),99),IFERROR(SEARCH("]",SUBSTITUTE(SUBSTITUTE(F10,"""",""),"[","")),99))-1),".",MID(1/2,2,1))),"n/d") -> n/d | H10: USD | I10: Volumen spot. Si sube en la caida, la venta es real.
A11: ETH var. 24h | B11: Binance | C11: https://api.binance.com/api/v3/ticker/24hr?symbol=ETHUSDT | D11: priceChangePercent | E11: =IFERROR(webservice(C11),"SIN CONEXION") -> SIN CONEXION | F11: =IFERROR(MID(E11,SEARCH(""""&D11&""":",E11)+LEN(D11)+3,32),"n/d") -> n/d | G11: =IFERROR(VALUE(SUBSTITUTE(LEFT(SUBSTITUTE(SUBSTITUTE(F11,"""",""),"[",""),MIN(IFERROR(SEARCH(",",SUBSTITUTE(SUBSTITUTE(F11,"""",""),"[","")),99),IFERROR(SEARCH("}",SUBSTITUTE(SUBSTITUTE(F11,"""",""),"[","")),99),IFERROR(SEARCH("]",SUBSTITUTE(SUBSTITUTE(F11,"""",""),"[","")),99))-1),".",MID(1/2,2,1))),"n/d") -> n/d | H11: % | I11: Beta de ETH vs BTC = fila 3 dividida por esta.
A12: ETH minimo 24h | B12: Binance | C12: https://api.binance.com/api/v3/ticker/24hr?symbol=ETHUSDT | D12: lowPrice | E12: =IFERROR(webservice(C12),"SIN CONEXION") -> SIN CONEXION | F12: =IFERROR(MID(E12,SEARCH(""""&D12&""":",E12)+LEN(D12)+3,32),"n/d") -> n/d | G12: =IFERROR(VALUE(SUBSTITUTE(LEFT(SUBSTITUTE(SUBSTITUTE(F12,"""",""),"[",""),MIN(IFERROR(SEARCH(",",SUBSTITUTE(SUBSTITUTE(F12,"""",""),"[","")),99),IFERROR(SEARCH("}",SUBSTITUTE(SUBSTITUTE(F12,"""",""),"[","")),99),IFERROR(SEARCH("]",SUBSTITUTE(SUBSTITUTE(F12,"""",""),"[","")),99))-1),".",MID(1/2,2,1))),"n/d") -> n/d | H12: USD | I12: Compara con 2,426 y 2,400.
A13: BTC spot (Coinbase) | B13: Coinbase | C13: https://api.coinbase.com/v2/prices/BTC-USD/spot | D13: amount | E13: =IFERROR(webservice(C13),"SIN CONEXION") -> SIN CONEXION | F13: =IFERROR(MID(E13,SEARCH(""""&D13&""":",E13)+LEN(D13)+3,32),"n/d") -> n/d | G13: =IFERROR(VALUE(SUBSTITUTE(LEFT(SUBSTITUTE(SUBSTITUTE(F13,"""",""),"[",""),MIN(IFERROR(SEARCH(",",SUBSTITUTE(SUBSTITUTE(F13,"""",""),"[","")),99),IFERROR(SEARCH("}",SUBSTITUTE(SUBSTITUTE(F13,"""",""),"[","")),99),IFERROR(SEARCH("]",SUBSTITUTE(SUBSTITUTE(F13,"""",""),"[","")),99))-1),".",MID(1/2,2,1))),"n/d") -> n/d | H13: USD | I13: Referencia institucional EEUU. Prima vs Binance = flujo local.
A14: ETH spot (Coinbase) | B14: Coinbase | C14: https://api.coinbase.com/v2/prices/ETH-USD/spot | D14: amount | E14: =IFERROR(webservice(C14),"SIN CONEXION") -> SIN CONEXION | F14: =IFERROR(MID(E14,SEARCH(""""&D14&""":",E14)+LEN(D14)+3,32),"n/d") -> n/d | G14: =IFERROR(VALUE(SUBSTITUTE(LEFT(SUBSTITUTE(SUBSTITUTE(F14,"""",""),"[",""),MIN(IFERROR(SEARCH(",",SUBSTITUTE(SUBSTITUTE(F14,"""",""),"[","")),99),IFERROR(SEARCH("}",SUBSTITUTE(SUBSTITUTE(F14,"""",""),"[","")),99),IFERROR(SEARCH("]",SUBSTITUTE(SUBSTITUTE(F14,"""",""),"[","")),99))-1),".",MID(1/2,2,1))),"n/d") -> n/d | H14: USD | I14: Idem para ETH.
A15: BTC spot (Kraken) | B15: Kraken | C15: https://api.kraken.com/0/public/Ticker?pair=XBTUSD | D15: c | E15: =IFERROR(webservice(C15),"SIN CONEXION") -> SIN CONEXION | F15: =IFERROR(MID(E15,SEARCH(""""&D15&""":",E15)+LEN(D15)+3,32),"n/d") -> n/d | G15: =IFERROR(VALUE(SUBSTITUTE(LEFT(SUBSTITUTE(SUBSTITUTE(F15,"""",""),"[",""),MIN(IFERROR(SEARCH(",",SUBSTITUTE(SUBSTITUTE(F15,"""",""),"[","")),99),IFERROR(SEARCH("}",SUBSTITUTE(SUBSTITUTE(F15,"""",""),"[","")),99),IFERROR(SEARCH("]",SUBSTITUTE(SUBSTITUTE(F15,"""",""),"[","")),99))-1),".",MID(1/2,2,1))),"n/d") -> n/d | H15: USD | I15: Tercera referencia. Clave 'c' = ultimo cierre.
A16: BTC indice (Deribit) | B16: Deribit | C16: https://www.deribit.com/api/v2/public/get_index_price?index_name=btc_usd | D16: index_price | E16: =IFERROR(webservice(C16),"SIN CONEXION") -> SIN CONEXION | F16: =IFERROR(MID(E16,SEARCH(""""&D16&""":",E16)+LEN(D16)+3,32),"n/d") -> n/d | G16: =IFERROR(VALUE(SUBSTITUTE(LEFT(SUBSTITUTE(SUBSTITUTE(F16,"""",""),"[",""),MIN(IFERROR(SEARCH(",",SUBSTITUTE(SUBSTITUTE(F16,"""",""),"[","")),99),IFERROR(SEARCH("}",SUBSTITUTE(SUBSTITUTE(F16,"""",""),"[","")),99),IFERROR(SEARCH("]",SUBSTITUTE(SUBSTITUTE(F16,"""",""),"[","")),99))-1),".",MID(1/2,2,1))),"n/d") -> n/d | H16: USD | I16: Indice de liquidacion de opciones. El que decide el max pain.
... A20: BTC spot (Bitstamp) | B20: Bitstamp | C20: https://www.bitstamp.net/api/v2/ticker/btcusd/ | D20: last | E20: =IFERROR(webservice(C20),"SIN CONEXION") -> SIN CONEXION | F20: =IFERROR(MID(E20,SEARCH(""""&D20&""":",E20)+LEN(D20)+3,32),"n/d") -> n/d | G20: =IFERROR(VALUE(SUBSTITUTE(LEFT(SUBSTITUTE(SUBSTITUTE(F20,"""",""),"[",""),MIN(IFERROR(SEARCH(",",SUBSTITUTE(SUBSTITUTE(F20,"""",""),"[","")),99),IFERROR(SEARCH("}",SUBSTITUTE(SUBSTITUTE(F20,"""",""),"[","")),99),IFERROR(SEARCH("]",SUBSTITUTE(SUBSTITUTE(F20,"""",""),"[","")),99))-1),".",MID(1/2,2,1))),"n/d") -> n/d | H20: USD | I20: Referencia citada en el analisis del 28-ago (minimo 78,442).

Sheet 3_Live_Derivados
A1: DERIVADOS EN VIVO — FUNDING, OPEN INTEREST, POSICIONAMIENTO
A2: El corazon del modelo. Aqui se ve el combustible de liquidacion antes de que se queme.
A3: La columna E llama a la API. La F aisla el fragmento. La G convierte a numero. Si ves SIN CONEXION, habilita el acceso a datos externos o usa Power Query (hoja 9).
A4: Indicador | B4: Fuente | C4: URL del endpoint (publico, sin clave) | D4: Clave JSON | E4: Respuesta cruda (WEBSERVICE) | F4: Fragmento aislado | G4: VALOR | H4: Unidad | I4: Como se usa en el modelo
A5: Funding BTC (actual) | B5: Binance F. | C5: https://fapi.binance.com/fapi/v1/premiumIndex?symbol=BTCUSDT | D5: lastFundingRate | E5: =IFERROR(webservice(C5),"SIN CONEXION") -> SIN CONEXION | F5: =IFERROR(MID(E5,SEARCH(""""&D5&""":",E5)+LEN(D5)+3,32),"n/d") -> n/d | G5: =IFERROR(VALUE(SUBSTITUTE(LEFT(SUBSTITUTE(SUBSTITUTE(F5,"""",""),"[",""),MIN(IFERROR(SEARCH(",",SUBSTITUTE(SUBSTITUTE(F5,"""",""),"[","")),99),IFERROR(SEARCH("}",SUBSTITUTE(SUBSTITUTE(F5,"""",""),"[","")),99),IFERROR(SEARCH("]",SUBSTITUTE(SUBSTITUTE(F5,"""",""),"[","")),99))-1),".",MID(1/2,2,1))),"n/d") -> n/d | H5: frac/8h | I5: FILTRO 4. Neutro o negativo = setup limpio. >0.0003 = sobrecalentado.
A6: Funding ETH (actual) | B6: Binance F. | C6: https://fapi.binance.com/fapi/v1/premiumIndex?symbol=ETHUSDT | D6: lastFundingRate | E6: =IFERROR(webservice(C6),"SIN CONEXION") -> SIN CONEXION | F6: =IFERROR(MID(E6,SEARCH(""""&D6&""":",E6)+LEN(D6)+3,32),"n/d") -> n/d | G6: =IFERROR(VALUE(SUBSTITUTE(LEFT(SUBSTITUTE(SUBSTITUTE(F6,"""",""),"[",""),MIN(IFERROR(SEARCH(",",SUBSTITUTE(SUBSTITUTE(F6,"""",""),"[","")),99),IFERROR(SEARCH("}",SUBSTITUTE(SUBSTITUTE(F6,"""",""),"[","")),99),IFERROR(SEARCH("]",SUBSTITUTE(SUBSTITUTE(F6,"""",""),"[","")),99))-1),".",MID(1/2,2,1))),"n/d") -> n/d | H6: frac/8h | I6: Divergencia con BTC senala rotacion.
A7: Open Interest BTC (contratos) | B7: Binance F. | C7: https://fapi.binance.com/fapi/v1/openInterest?symbol=BTCUSDT | D7: openInterest | E7: =IFERROR(webservice(C7),"SIN CONEXION") -> SIN CONEXION | F7: =IFERROR(MID(E7,SEARCH(""""&D7&""":",E7)+LEN(D7)+3,32),"n/d") -> n/d | G7: =IFERROR(VALUE(SUBSTITUTE(LEFT(SUBSTITUTE(SUBSTITUTE(F7,"""",""),"[",""),MIN(IFERROR(SEARCH(",",SUBSTITUTE(SUBSTITUTE(F7,"""",""),"[","")),99),IFERROR(SEARCH("}",SUBSTITUTE(SUBSTITUTE(F7,"""",""),"[","")),99),IFERROR(SEARCH("]",SUBSTITUTE(SUBSTITUTE(F7,"""",""),"[","")),99))-1),".",MID(1/2,2,1))),"n/d") -> n/d | H7: BTC | I7: Multiplicar por precio = OI en USD. Base del % purgado.
A8: Open Interest ETH (contratos) | B8: Binance F. | C8: https://fapi.binance.com/fapi/v1/openInterest?symbol=ETHUSDT | D8: openInterest | E8: =IFERROR(webservice(C8),"SIN CONEXION") -> SIN CONEXION | F8: =IFERROR(MID(E8,SEARCH(""""&D8&""":",E8)+LEN(D8)+3,32),"n/d") -> n/d | G8: =IFERROR(VALUE(SUBSTITUTE(LEFT(SUBSTITUTE(SUBSTITUTE(F8,"""",""),"[",""),MIN(IFERROR(SEARCH(",",SUBSTITUTE(SUBSTITUTE(F8,"""",""),"[","")),99),IFERROR(SEARCH("}",SUBSTITUTE(SUBSTITUTE(F8,"""",""),"[","")),99),IFERROR(SEARCH("]",SUBSTITUTE(SUBSTITUTE(F8,"""",""),"[","")),99))-1),".",MID(1/2,2,1))),"n/d") -> n/d | H8: ETH | I8: Idem ETH.
A9: L/S cuentas BTC (retail) | B9: Binance F. | C9: https://fapi.binance.com/futures/data/globalLongShortAccountRatio?symbol=BTCUSDT&period=1h&limit=1 | D9: longShortRatio | E9: =IFERROR(webservice(C9),"SIN CONEXION") -> SIN CONEXION | F9: =IFERROR(MID(E9,SEARCH(""""&D9&""":",E9)+LEN(D9)+3,32),"n/d") -> n/d | G9: =IFERROR(VALUE(SUBSTITUTE(LEFT(SUBSTITUTE(SUBSTITUTE(F9,"""",""),"[",""),MIN(IFERROR(SEARCH(",",SUBSTITUTE(SUBSTITUTE(F9,"""",""),"[","")),99),IFERROR(SEARCH("}",SUBSTITUTE(SUBSTITUTE(F9,"""",""),"[","")),99),IFERROR(SEARCH("]",SUBSTITUTE(SUBSTITUTE(F9,"""",""),"[","")),99))-1),".",MID(1/2,2,1))),"n/d") -> n/d | H9: ratio | I9: La multitud. 70.3% largo el 28-ago. >2 = combustible bajista.
A10: L/S posiciones top BTC (pro) | B10: Binance F. | C10: https://fapi.binance.com/futures/data/topLongShortPositionRatio?symbol=BTCUSDT&period=1h&limit=1 | D10: longShortRatio | E10: =IFERROR(webservice(C10),"SIN CONEXION") -> SIN CONEXION | F10: =IFERROR(MID(E10,SEARCH(""""&D10&""":",E10)+LEN(D10)+3,32),"n/d") -> n/d | G10: =IFERROR(VALUE(SUBSTITUTE(LEFT(SUBSTITUTE(SUBSTITUTE(F10,"""",""),"[",""),MIN(IFERROR(SEARCH(",",SUBSTITUTE(SUBSTITUTE(F10,"""",""),"[","")),99),IFERROR(SEARCH("}",SUBSTITUTE(SUBSTITUTE(F10,"""",""),"[","")),99),IFERROR(SEARCH("]",SUBSTITUTE(SUBSTITUTE(F10,"""",""),"[","")),99))-1),".",MID(1/2,2,1))),"n/d") -> n/d | H10: ratio | I10: El dinero inteligente. 57.4% largo. La BRECHA es la senal.
A11: L/S cuentas ETH | B11: Binance F. | C11: https://fapi.binance.com/futures/data/globalLongShortAccountRatio?symbol=ETHUSDT&period=1h&limit=1 | D11: longShortRatio | E11: =IFERROR(webservice(C11),"SIN CONEXION") -> SIN CONEXION | F11: =IFERROR(MID(E11,SEARCH(""""&D11&""":",E11)+LEN(D11)+3,32),"n/d") -> n/d | G11: =IFERROR(VALUE(SUBSTITUTE(LEFT(SUBSTITUTE(SUBSTITUTE(F11,"""",""),"[",""),MIN(IFERROR(SEARCH(",",SUBSTITUTE(SUBSTITUTE(F11,"""",""),"[","")),99),IFERROR(SEARCH("}",SUBSTITUTE(SUBSTITUTE(F11,"""",""),"[","")),99),IFERROR(SEARCH("]",SUBSTITUTE(SUBSTITUTE(F11,"""",""),"[","")),99))-1),".",MID(1/2,2,1))),"n/d") -> n/d | H11: ratio | I11: ETH tiene beta de liquidacion >2x.
A12: L/S posiciones top ETH | B12: Binance F. | C12: https://fapi.binance.com/futures/data/topLongShortPositionRatio?symbol=ETHUSDT&period=1h&limit=1 | D12: longShortRatio | E12: =IFERROR(webservice(C12),"SIN CONEXION") -> SIN CONEXION | F12: =IFERROR(MID(E12,SEARCH(""""&D12&""":",E12)+LEN(D12)+3,32),"n/d") -> n/d | G12: =IFERROR(VALUE(SUBSTITUTE(LEFT(SUBSTITUTE(SUBSTITUTE(F12,"""",""),"[",""),MIN(IFERROR(SEARCH(",",SUBSTITUTE(SUBSTITUTE(F12,"""",""),"[","")),99),IFERROR(SEARCH("}",SUBSTITUTE(SUBSTITUTE(F12,"""",""),"[","")),99),IFERROR(SEARCH("]",SUBSTITUTE(SUBSTITUTE(F12,"""",""),"[","")),99))-1),".",MID(1/2,2,1))),"n/d") -> n/d | H12: ratio | I12: Idem ETH.
A13: Taker buy/sell BTC | B13: Binance F. | C13: https://fapi.binance.com/futures/data/takerlongshortRatio?symbol=BTCUSDT&period=1h&limit=1 | D13: buySellRatio | E13: =IFERROR(webservice(C13),"SIN CONEXION") -> SIN CONEXION | F13: =IFERROR(MID(E13,SEARCH(""""&D13&""":",E13)+LEN(D13)+3,32),"n/d") -> n/d | G13: =IFERROR(VALUE(SUBSTITUTE(LEFT(SUBSTITUTE(SUBSTITUTE(F13,"""",""),"[",""),MIN(IFERROR(SEARCH(",",SUBSTITUTE(SUBSTITUTE(F13,"""",""),"[","")),99),IFERROR(SEARCH("}",SUBSTITUTE(SUBSTITUTE(F13,"""",""),"[","")),99),IFERROR(SEARCH("]",SUBSTITUTE(SUBSTITUTE(F13,"""",""),"[","")),99))-1),".",MID(1/2,2,1))),"n/d") -> n/d | H13: ratio | I13: Agresion real. <0.9 sostenido en la caida = venta informada, NO comprar.
A14: OI historico BTC (5m) | B14: Binance F. | C14: https://fapi.binance.com/futures/data/openInterestHist?symbol=BTCUSDT&period=5m&limit=1 | D14: sumOpenInterestValue | E14: =IFERROR(webservice(C14),"SIN CONEXION") -> SIN CONEXION | F14: =IFERROR(MID(E14,SEARCH(""""&D14&""":",E14)+LEN(D14)+3,32),"n/d") -> n/d | G14: =IFERROR(VALUE(SUBSTITUTE(LEFT(SUBSTITUTE(SUBSTITUTE(F14,"""",""),"[",""),MIN(IFERROR(SEARCH(",",SUBSTITUTE(SUBSTITUTE(F14,"""",""),"[","")),99),IFERROR(SEARCH("}",SUBSTITUTE(SUBSTITUTE(F14,"""",""),"[","")),99),IFERROR(SEARCH("]",SUBSTITUTE(SUBSTITUTE(F14,"""",""),"[","")),99))-1),".",MID(1/2,2,1))),"n/d") -> n/d | H14: USD | I14: OI en USD directo. Compara contra el valor de hace 1h para medir la purga.
A15: Funding BTC (OKX) | B15: OKX | C15: https://www.okx.com/api/v5/public/funding-rate?instId=BTC-USDT-SWAP | D15: fundingRate | E15: =IFERROR(webservice(C15),"SIN CONEXION") -> SIN CONEXION | F15: =IFERROR(MID(E15,SEARCH(""""&D15&""":",E15)+LEN(D15)+3,32),"n/d") -> n/d | G15: =IFERROR(VALUE(SUBSTITUTE(LEFT(SUBSTITUTE(SUBSTITUTE(F15,"""",""),"[",""),MIN(IFERROR(SEARCH(",",SUBSTITUTE(SUBSTITUTE(F15,"""",""),"[","")),99),IFERROR(SEARCH("}",SUBSTITUTE(SUBSTITUTE(F15,"""",""),"[","")),99),IFERROR(SEARCH("]",SUBSTITUTE(SUBSTITUTE(F15,"""",""),"[","")),99))-1),".",MID(1/2,2,1))),"n/d") -> n/d | H15: frac/8h | I15: Segunda venue. Divergencia entre venues = arbitraje de base.
A16: Ticker BTC perp (Bybit) | B16: Bybit | C16: https://api.bybit.com/v5/market/tickers?category=linear&symbol=BTCUSDT | D16: fundingRate | E16: =IFERROR(webservice(C16),"SIN CONEXION") -> SIN CONEXION | F16: =IFERROR(MID(E16,SEARCH(""""&D16&""":",E16)+LEN(D16)+3,32),"n/d") -> n/d | G16: =IFERROR(VALUE(SUBSTITUTE(LEFT(SUBSTITUTE(SUBSTITUTE(F16,"""",""),"[",""),MIN(IFERROR(SEARCH(",",SUBSTITUTE(SUBSTITUTE(F16,"""",""),"[","")),99),IFERROR(SEARCH("}",SUBSTITUTE(SUBSTITUTE(F16,"""",""),"[","")),99),IFERROR(SEARCH("]",SUBSTITUTE(SUBSTITUTE(F16,"""",""),"[","")),99))-1),".",MID(1/2,2,1))),"n/d") -> n/d | H16: frac/8h | I16: Tercera venue.
... A21: Interes abierto futuros Deribit | B21: Deribit | C21: https://www.deribit.com/api/v2/public/get_book_summary_by_currency?currency=BTC&kind=future | D21: open_interest | E21: =IFERROR(webservice(C21),"SIN CONEXION") -> SIN CONEXION | F21: =IFERROR(MID(E21,SEARCH(""""&D21&""":",E21)+LEN(D21)+3,32),"n/d") -> n/d | G21: =IFERROR(VALUE(SUBSTITUTE(LEFT(SUBSTITUTE(SUBSTITUTE(F21,"""",""),"[",""),MIN(IFERROR(SEARCH(",",SUBSTITUTE(SUBSTITUTE(F21,"""",""),"[","")),99),IFERROR(SEARCH("}",SUBSTITUTE(SUBSTITUTE(F21,"""",""),"[","")),99),IFERROR(SEARCH("]",SUBSTITUTE(SUBSTITUTE(F21,"""",""),"[","")),99))-1),".",MID(1/2,2,1))),"n/d") -> n/d | H21: USD | I21: OI de futuros Deribit.

Sheet 4_Live_Macro
A1: MACRO, SENTIMIENTO Y FLUJOS — APIs PUBLICAS
A2: El bloque que decide si la venta es FORZADA (rebota) o INFORMADA (no rebota). Warsh cambio este bloque el 28-ago.
A3: La columna E llama a la API. La F aisla el fragmento. La G convierte a numero. Si ves SIN CONEXION, habilita el acceso a datos externos o usa Power Query (hoja 9).
A4: Indicador | B4: Fuente | C4: URL del endpoint (publico, sin clave) | D4: Clave JSON | E4: Respuesta cruda (WEBSERVICE) | F4: Fragmento aislado | G4: VALOR | H4: Unidad | I4: Como se usa en el modelo
A5: Fear & Greed cripto | B5: alternative.me | C5: https://api.alternative.me/fng/?limit=1 | D5: value | E5: =IFERROR(webservice(C5),"SIN CONEXION") -> SIN CONEXION | F5: =IFERROR(MID(E5,SEARCH(""""&D5&""":",E5)+LEN(D5)+3,32),"n/d") -> n/d | G5: =IFERROR(VALUE(SUBSTITUTE(LEFT(SUBSTITUTE(SUBSTITUTE(F5,"""",""),"[",""),MIN(IFERROR(SEARCH(",",SUBSTITUTE(SUBSTITUTE(F5,"""",""),"[","")),99),IFERROR(SEARCH("}",SUBSTITUTE(SUBSTITUTE(F5,"""",""),"[","")),99),IFERROR(SEARCH("]",SUBSTITUTE(SUBSTITUTE(F5,"""",""),"[","")),99))-1),".",MID(1/2,2,1))),"n/d") -> n/d | H5: 0-100 | I5: Sentimiento. En el squeeze del 20-ago estuvo en 54 neutro: rally forzado, no euforico.
A6: Fear & Greed (ayer) | B6: alternative.me | C6: https://api.alternative.me/fng/?limit=2 | D6: value | E6: =IFERROR(webservice(C6),"SIN CONEXION") -> SIN CONEXION | F6: =IFERROR(MID(E6,SEARCH(""""&D6&""":",E6)+LEN(D6)+3,32),"n/d") -> n/d | G6: =IFERROR(VALUE(SUBSTITUTE(LEFT(SUBSTITUTE(SUBSTITUTE(F6,"""",""),"[",""),MIN(IFERROR(SEARCH(",",SUBSTITUTE(SUBSTITUTE(F6,"""",""),"[","")),99),IFERROR(SEARCH("}",SUBSTITUTE(SUBSTITUTE(F6,"""",""),"[","")),99),IFERROR(SEARCH("]",SUBSTITUTE(SUBSTITUTE(F6,"""",""),"[","")),99))-1),".",MID(1/2,2,1))),"n/d") -> n/d | H6: 0-100 | I6: Comparar contra hoy para ver la velocidad del cambio de sentimiento.
A7: Cap. total mercado cripto | B7: CoinGecko | C7: https://api.coingecko.com/api/v3/global | D7: active_cryptocurrencies | E7: =IFERROR(webservice(C7),"SIN CONEXION") -> SIN CONEXION | F7: =IFERROR(MID(E7,SEARCH(""""&D7&""":",E7)+LEN(D7)+3,32),"n/d") -> n/d | G7: =IFERROR(VALUE(SUBSTITUTE(LEFT(SUBSTITUTE(SUBSTITUTE(F7,"""",""),"[",""),MIN(IFERROR(SEARCH(",",SUBSTITUTE(SUBSTITUTE(F7,"""",""),"[","")),99),IFERROR(SEARCH("}",SUBSTITUTE(SUBSTITUTE(F7,"""",""),"[","")),99),IFERROR(SEARCH("]",SUBSTITUTE(SUBSTITUTE(F7,"""",""),"[","")),99))-1),".",MID(1/2,2,1))),"n/d") -> n/d | H7: n | I7: Sustituye la clave por 'total_market_cap' con Power Query para el valor real (~2.7T).
A8: BTC vs oro (proxy) | B8: CoinGecko | C8: https://api.coingecko.com/api/v3/simple/price?ids=bitcoin&vs_currencies=xau | D8: xau | E8: =IFERROR(webservice(C8),"SIN CONEXION") -> SIN CONEXION | F8: =IFERROR(MID(E8,SEARCH(""""&D8&""":",E8)+LEN(D8)+3,32),"n/d") -> n/d | G8: =IFERROR(VALUE(SUBSTITUTE(LEFT(SUBSTITUTE(SUBSTITUTE(F8,"""",""),"[",""),MIN(IFERROR(SEARCH(",",SUBSTITUTE(SUBSTITUTE(F8,"""",""),"[","")),99),IFERROR(SEARCH("}",SUBSTITUTE(SUBSTITUTE(F8,"""",""),"[","")),99),IFERROR(SEARCH("]",SUBSTITUTE(SUBSTITUTE(F8,"""",""),"[","")),99))-1),".",MID(1/2,2,1))),"n/d") -> n/d | H8: oz | I8: El 28-ago oro y plata perdieron valor tras Warsh. Ratio BTC/oro = apetito de riesgo real.
A9: DXY proxy (EUR/USD) | B9: Frankfurter/BCE | C9: https://api.frankfurter.app/latest?from=USD&to=EUR | D9: EUR | E9: =IFERROR(webservice(C9),"SIN CONEXION") -> SIN CONEXION | F9: =IFERROR(MID(E9,SEARCH(""""&D9&""":",E9)+LEN(D9)+3,32),"n/d") -> n/d | G9: =IFERROR(VALUE(SUBSTITUTE(LEFT(SUBSTITUTE(SUBSTITUTE(F9,"""",""),"[",""),MIN(IFERROR(SEARCH(",",SUBSTITUTE(SUBSTITUTE(F9,"""",""),"[","")),99),IFERROR(SEARCH("}",SUBSTITUTE(SUBSTITUTE(F9,"""",""),"[","")),99),IFERROR(SEARCH("]",SUBSTITUTE(SUBSTITUTE(F9,"""",""),"[","")),99))-1),".",MID(1/2,2,1))),"n/d") -> n/d | H9: ratio | I9: Sube = dolar fuerte = presion sobre cripto. DXY estaba en 99.5 el 28-ago.
A10: USD/JPY | B10: Frankfurter/BCE | C10: https://api.frankfurter.app/latest?from=USD&to=JPY | D10: JPY | E10: =IFERROR(webservice(C10),"SIN CONEXION") -> SIN CONEXION | F10: =IFERROR(MID(E10,SEARCH(""""&D10&""":",E10)+LEN(D10)+3,32),"n/d") -> n/d | G10: =IFERROR(VALUE(SUBSTITUTE(LEFT(SUBSTITUTE(SUBSTITUTE(F10,"""",""),"[",""),MIN(IFERROR(SEARCH(",",SUBSTITUTE(SUBSTITUTE(F10,"""",""),"[","")),99),IFERROR(SEARCH("}",SUBSTITUTE(SUBSTITUTE(F10,"""",""),"[","")),99),IFERROR(SEARCH("]",SUBSTITUTE(SUBSTITUTE(F10,"""",""),"[","")),99))-1),".",MID(1/2,2,1))),"n/d") -> n/d | H10: ratio | I10: Proxy de carry trade. Rupturas aqui preceden liquidaciones cripto.
A11: Rend. Tesoro 2A | B11: Tesoro EEUU | C11: https://home.treasury.gov/resource-center/data-chart-center/interest-rates/daily-treasury-rates.csv/2026/all?type=daily_treasury_yield_curve&field_tdr_date_value=2026 | D11: 2 Yr | E11: =IFERROR(webservice(C11),"SIN CONEXION") -> SIN CONEXION | F11: =IFERROR(MID(E11,SEARCH(""""&D11&""":",E11)+LEN(D11)+3,32),"n/d") -> n/d | G11: =IFERROR(VALUE(SUBSTITUTE(LEFT(SUBSTITUTE(SUBSTITUTE(F11,"""",""),"[",""),MIN(IFERROR(SEARCH(",",SUBSTITUTE(SUBSTITUTE(F11,"""",""),"[","")),99),IFERROR(SEARCH("}",SUBSTITUTE(SUBSTITUTE(F11,"""",""),"[","")),99),IFERROR(SEARCH("]",SUBSTITUTE(SUBSTITUTE(F11,"""",""),"[","")),99))-1),".",MID(1/2,2,1))),"n/d") -> n/d | H11: % | I11: CSV: usar Power Query (hoja 9). 28-ago: +12pb a 4.35%, maximo de un mes.
A12: Rend. Tesoro 30A | B12: Tesoro EEUU | C12: https://home.treasury.gov/resource-center/data-chart-center/interest-rates/daily-treasury-rates.csv/2026/all?type=daily_treasury_yield_curve&field_tdr_date_value=2026 | D12: 30 Yr | E12: =IFERROR(webservice(C12),"SIN CONEXION") -> SIN CONEXION | F12: =IFERROR(MID(E12,SEARCH(""""&D12&""":",E12)+LEN(D12)+3,32),"n/d") -> n/d | G12: =IFERROR(VALUE(SUBSTITUTE(LEFT(SUBSTITUTE(SUBSTITUTE(F12,"""",""),"[",""),MIN(IFERROR(SEARCH(",",SUBSTITUTE(SUBSTITUTE(F12,"""",""),"[","")),99),IFERROR(SEARCH("}",SUBSTITUTE(SUBSTITUTE(F12,"""",""),"[","")),99),IFERROR(SEARCH("]",SUBSTITUTE(SUBSTITUTE(F12,"""",""),"[","")),99))-1),".",MID(1/2,2,1))),"n/d") -> n/d | H12: % | I12: 28-ago: 5.15%. La parte larga BAJO mientras la corta SUBIO: aplanamiento hawkish.
A13: Fed Funds efectiva (FRED) | B13: FRED | C13: https://fred.stlouisfed.org/graph/fredgraph.csv?id=DFF | D13: DFF | E13: =IFERROR(webservice(C13),"SIN CONEXION") -> SIN CONEXION | F13: =IFERROR(MID(E13,SEARCH(""""&D13&""":",E13)+LEN(D13)+3,32),"n/d") -> n/d | G13: =IFERROR(VALUE(SUBSTITUTE(LEFT(SUBSTITUTE(SUBSTITUTE(F13,"""",""),"[",""),MIN(IFERROR(SEARCH(",",SUBSTITUTE(SUBSTITUTE(F13,"""",""),"[","")),99),IFERROR(SEARCH("}",SUBSTITUTE(SUBSTITUTE(F13,"""",""),"[","")),99),IFERROR(SEARCH("]",SUBSTITUTE(SUBSTITUTE(F13,"""",""),"[","")),99))-1),".",MID(1/2,2,1))),"n/d") -> n/d | H13: % | I13: CSV sin clave. Rango objetivo 3.50-3.75% desde julio.
A14: PCE subyacente (FRED) | B14: FRED | C14: https://fred.stlouisfed.org/graph/fredgraph.csv?id=PCEPILFE | D14: PCEPILFE | E14: =IFERROR(webservice(C14),"SIN CONEXION") -> SIN CONEXION | F14: =IFERROR(MID(E14,SEARCH(""""&D14&""":",E14)+LEN(D14)+3,32),"n/d") -> n/d | G14: =IFERROR(VALUE(SUBSTITUTE(LEFT(SUBSTITUTE(SUBSTITUTE(F14,"""",""),"[",""),MIN(IFERROR(SEARCH(",",SUBSTITUTE(SUBSTITUTE(F14,"""",""),"[","")),99),IFERROR(SEARCH("}",SUBSTITUTE(SUBSTITUTE(F14,"""",""),"[","")),99),IFERROR(SEARCH("]",SUBSTITUTE(SUBSTITUTE(F14,"""",""),"[","")),99))-1),".",MID(1/2,2,1))),"n/d") -> n/d | H14: indice | I14: Warsh cito PCE 12m en 3.7% y 6m en 4.1%. Objetivo firme del 2%.
A15: Flujos ETF BTC spot | B15: Farside | C15: https://farside.co.uk/bitcoin-etf-flow-all-data/ | D15: flow | E15: =IFERROR(webservice(C15),"SIN CONEXION") -> SIN CONEXION | F15: =IFERROR(MID(E15,SEARCH(""""&D15&""":",E15)+LEN(D15)+3,32),"n/d") -> n/d | G15: =IFERROR(VALUE(SUBSTITUTE(LEFT(SUBSTITUTE(SUBSTITUTE(F15,"""",""),"[",""),MIN(IFERROR(SEARCH(",",SUBSTITUTE(SUBSTITUTE(F15,"""",""),"[","")),99),IFERROR(SEARCH("}",SUBSTITUTE(SUBSTITUTE(F15,"""",""),"[","")),99),IFERROR(SEARCH("]",SUBSTITUTE(SUBSTITUTE(F15,"""",""),"[","")),99))-1),".",MID(1/2,2,1))),"n/d") -> n/d | H15: M USD | I15: FILTRO 5. Tabla HTML: usar Power Query. 8 sesiones positivas al 28-ago; 1.92B semanal.
A16: Flujos ETF ETH spot | B16: Farside | C16: https://farside.co.uk/ethereum-etf-flow-all-data/ | D16: flow | E16: =IFERROR(webservice(C16),"SIN CONEXION") -> SIN CONEXION | F16: =IFERROR(MID(E16,SEARCH(""""&D16&""":",E16)+LEN(D16)+3,32),"n/d") -> n/d | G16: =IFERROR(VALUE(SUBSTITUTE(LEFT(SUBSTITUTE(SUBSTITUTE(F16,"""",""),"[",""),MIN(IFERROR(SEARCH(",",SUBSTITUTE(SUBSTITUTE(F16,"""",""),"[","")),99),IFERROR(SEARCH("}",SUBSTITUTE(SUBSTITUTE(F16,"""",""),"[","")),99),IFERROR(SEARCH("]",SUBSTITUTE(SUBSTITUTE(F16,"""",""),"[","")),99))-1),".",MID(1/2,2,1))),"n/d") -> n/d | H16: M USD | I16: 697M semanales en la semana del squeeze.
... A21: Precio BTC fin de mes | B21: Polymarket | C21: https://gamma-api.polymarket.com/markets?closed=false&limit=5 | D21: bestBid | E21: =IFERROR(webservice(C21),"SIN CONEXION") -> SIN CONEXION | F21: =IFERROR(MID(E21,SEARCH(""""&D21&""":",E21)+LEN(D21)+3,32),"n/d") -> n/d | G21: =IFERROR(VALUE(SUBSTITUTE(LEFT(SUBSTITUTE(SUBSTITUTE(F21,"""",""),"[",""),MIN(IFERROR(SEARCH(",",SUBSTITUTE(SUBSTITUTE(F21,"""",""),"[","")),99),IFERROR(SEARCH("}",SUBSTITUTE(SUBSTITUTE(F21,"""",""),"[","")),99),IFERROR(SEARCH("]",SUBSTITUTE(SUBSTITUTE(F21,"""",""),"[","")),99))-1),".",MID(1/2,2,1))),"n/d") -> n/d | H21: prob | I21: Distribucion implicita del mercado de prediccion.

Sheet 5_Liquidaciones
A1: MOTOR FORENSE DE LIQUIDACIONES
A2: Coinglass no ofrece endpoint gratuito sin clave: las celdas amarillas se llenan a mano desde coinglass.com/liquidations (30 segundos). Todo lo demas se calcula solo.
A4: A. ENTRADAS (amarillo = escribir a mano) / VERDE = calculado
A5: Variable | C5: Valor | D5: Unidad | E5: Umbral | F5: Estado | G5: Referencia 28-ago-2026 | H5: Nota
A6: Liquidaciones totales 24h | C6: 487680000 | D6: USD | E6: — | F6: — | G6: 487.68 M | H6: Coinglass / CryptoSlate 28-ago-2026
A7: Liquidaciones ultima 1 hora | C7: 0 | D7: USD | E7: 800000000 | F7: =IF(C7>=E7,"OK","BAJO") -> BAJO | G7: — | H7: FILTRO 1 del dashboard. Es el gatillo real de entrada.
A8: Traders liquidados 24h | C8: 97691 | D8: n | E8: — | F8: — | G8: 97,691 | H8: Para calcular perdida media por cuenta.
A9: Longs liquidados 24h | C9: 360000000 | D9: USD | E9: — | F9: — | G9: 360 M | H9: FILTRO 3 usa la dominancia derivada de aqui.
A10: Shorts liquidados 24h | C10: 127680000 | D10: USD | E10: — | F10: — | G10: 127.68 M | H10: Complemento.
A11: Open Interest agregado (USD) | C11: 56480000000 | D11: USD | E11: — | F11: — | G11: 56.48 B | H11: Denominador del % purgado.
A12: Flujos ETF positivos hoy (1/0) | C12: 1 | D12: 0/1 | E12: 1 | F12: =IF(C12>=E12,"OK","BAJO") -> OK | G12: 1 (8 sesiones) | H12: FILTRO 5. Escribe 1 si los flujos ETF del dia son positivos, 0 si no.
A13: B. METRICAS DERIVADAS — EL ANALISIS QUE NADIE HACE
A14: Metrica derivada | C14: Valor | D14: Formato | E14: Umbral critico | F14: Diagnostico | G14: Valor del 28-ago | H14: Interpretacion
A15: Perdida media por trader | C15: =IFERROR(C6/C8,0) -> 4992.0668 | D15: #,##0 | E15: — | F15: — | G15: ≈ 4,992 USD | H15: Perfil retail apalancado medio-alto, no ballenas.
A16: Dominancia de longs | C16: =IFERROR(C9/C6,0) -> 0.73818898 | D16: 0.0% | E16: 0.75 | F16: =IF(C16>=E16,"CUMPLE","NO CUMPLE") -> NO CUMPLE | G16: 74% | H16: FILTRO 3. >75% confirma purga unilateral.
A17: % del OI purgado (24h) | C17: =IFERROR(C6/C11,0) -> 0.0086345609 | D17: 0.00% | E17: 0.025 | F17: =IF(C17>=E17,"CUMPLE","NO CUMPLE") -> NO CUMPLE | G17: 0.86% | H17: FILTRO 2. HALLAZGO CLAVE: <1% = purga incompleta, queda combustible.
A18: Ratio purga vs capitulacion | C18: =IFERROR((C6/C11)/0.04,0) -> 0.21586402 | D18: 0.00x | E18: 1 | F18: =IF(C18>=E18,"CUMPLE","NO CUMPLE") -> NO CUMPLE | G18: 0.22x | H18: 1.00x = purga de capitulacion (4% del OI). Hoy solo el 22% del camino.
A19: Rebote esperado (ley de escala) | C19: =IFERROR(IF(C6<500000000,0.014,IF(C6<1500000000,0.0275,IF(C6<3000000000,0.0475,0.09))),0) -> 0.014 | D19: 0.00% | E19: — | F19: — | G19: 1.4% | H19: Media del tramo. El rebote escala con la LIQUIDACION, no con la caida.
A20: Rebote real observado hoy (ola 3) | C20: =IFERROR((77712-76909)/76909,0) -> 0.010440911 | D20: 0.00% | E20: — | F20: — | G20: 1.04% | H20: 76,909 -> 77,712. Coincide con la prediccion del modelo.
A21: Error del modelo | C21: =IFERROR(C20-C19,0) -> -0.0035590893 | D21: +0.00%;-0.00% | E21: — | F21: — | G21: -0.36pp | H21: Calibracion. Si el error crece, recalibra los tramos.
A22: Grado de la cascada (0-6) | C22: =(IF(C7>=800000000,1,0))+(IF(C6/C11>=0.025,1.5,0))+(IF(C9/C6>=0.8,1,0))+(IF('1_Dashboard'!E8<=0.0001,1,0))+(IF(C12>0,0.5,0))+(IF(C6>=1000000000,1,0)) -> 1.5 | D22: 0.0 | E22: 4 | F22: =IF(C22>=E22,"CUMPLE","NO CUMPLE") -> NO CUMPLE | G22: 1.5 de 6 | H22: CALIDAD BAJA. Rubrica ponderada (el informe usaba una sin pesos: 2.5/6). Debajo de 4 no se opera.
A24: C. LEY DE ESCALA DEL REBOTE (calibrada con datos observados)
A25: Tramo de liquidacion 24h | C25: Rebote esperado | D25: Con 3x | E25: Con 5x | F25: Con 10x | G25: Evento de referencia | H25: Comentario
A26: < 500 M USD | C26: 0.014 | D26: =C26*3 -> 0.042 | E26: =C26*5 -> 0.07 | F26: =C26*10 -> 0.14 | G26: 28-ago-2026: 487.68 M -> rebote real 1.04% | H26: El apalancamiento multiplica el rebote Y la ruina. Ver hoja 7.
A27: 500 M – 1.5 B | C27: 0.0275 | D27: =C27*3 -> 0.0825 | E27: =C27*5 -> 0.1375 | F27: =C27*10 -> 0.275 | G27: 19-ago-2026: 691.06 M (mayor liq. de cortos desde 2019 en Glassnode) | H27: El apalancamiento multiplica el rebote Y la ruina. Ver hoja 7.
A28: 1.5 B – 3.0 B | C28: 0.0475 | D28: =C28*3 -> 0.1425 | E28: =C28*5 -> 0.2375 | F28: =C28*10 -> 0.475 | G28: Flash crash XRP: 1.35 B en 24h | H28: El apalancamiento multiplica el rebote Y la ruina. Ver hoja 7.
A29: > 3.0 B | C29: 0.09 | D29: =C29*3 -> 0.27 | E29: =C29*5 -> 0.45 | F29: =C29*10 -> 0.9 | G29: Semana del 20-ago: 7.2 B en cortos | H29: El apalancamiento multiplica el rebote Y la ruina. Ver hoja 7.
A31: D. CAMBIO DE POLARIDAD — EL DATO QUE DECIDE EL REGIMEN
A32: Ventana | C32: Liquidaciones | D32: Split dominante | E32: % dominante | F32: Regimen | G32: Fuente | H32: Lectura
A33: 19-ago-2026 | C33: 691060000 | D33: CORTOS | E33: 0.85 | F33: Short squeeze historico | G33: Glassnode / CoinStats | H33: =IF(D33="LONGS","Bajista: el lado concurrido se esta rompiendo","Alcista: cobertura forzada") -> Alcista: cobertura forzada
A34: Semana del 20-ago | C34: 7200000000 | D34: CORTOS | E34: 0.9 | F34: Squeeze en cadena | G34: Trading Economics | H34: =IF(D34="LONGS","Bajista: el lado concurrido se esta rompiendo","Alcista: cobertura forzada") -> Alcista: cobertura forzada
A35: Desde el miercoles 26-ago | C35: 6400000000 | D35: CORTOS | E35: 0.9 | F35: Continuacion | G35: Charles Schwab | H35: =IF(D35="LONGS","Bajista: el lado concurrido se esta rompiendo","Alcista: cobertura forzada") -> Alcista: cobertura forzada
A36: 24h PREVIAS a Warsh | C36: 160470000 | D36: CORTOS | E36: 1 | F36: Ultimo aliento alcista | G36: CoinStats 27-ago | H36: =IF(D36="LONGS","Bajista: el lado concurrido se esta rompiendo","Alcista: cobertura forzada") -> Alcista: cobertura forzada
A37: 24h POSTERIORES a Warsh | C37: 487680000 | D37: LONGS | E37: 0.74 | F37: INVERSION DE REGIMEN | G37: CryptoSlate 28-ago | H37: =IF(D37="LONGS","Bajista: el lado concurrido se esta rompiendo","Alcista: cobertura forzada") -> Bajista: el lado concurrido se esta rompiendo
A38: CONCLUSION DEL MOTOR | C38: =IF(C17<0.025,"PURGA INCOMPLETA - queda combustible de longs abajo - NO comprar la primera cascada","PURGA COMPLETA - el suelo es defendible") -> PURGA INCOMPLETA - queda combustible de longs abajo - NO comprar la primera cascada

Sheet 13_Mapa_Liq
A1: MAPA DE LIQUIDACIONES ESTIMADO — construido desde OI, flujo agresor y apalancamiento
A2: Metodo tipo heatmap: cada aumento de OI se reparte en niveles de apalancamiento y se proyecta su precio de liquidacion. Los niveles ya tocados por el precio se eliminan. Es una ESTIMACION, no el libro real de posiciones.
A4: A. PARAMETROS (amarillo = editable)
A5: Precio de referencia (ultimo cierre) | B5: =IF(COUNT('12_Datos_5m'!$F$5:$F$504)=0,'1_Dashboard'!E6,INDEX('12_Datos_5m'!$F$5:$F$504,COUNT('12_Datos_5m'!$F$5:$F$504))) -> 77477 | D5: Automatico. Si no hay datos 5m usa el precio EN USO del dashboard.
A6: Margen de mantenimiento (MMR) | B6: 0.004 | D6: Binance BTCUSDT tramo base: 0.40%. Acerca el precio de liquidacion.
A7: Vida media de las posiciones (horas) | B7: 24 | D7: Decaimiento: una posicion abierta hace 24h pesa 37% (e^-1). Supuesto.
A8: Ancho de cada franja de precio | B8: 0.005 | D8: 0.5% por fila. 61 filas = +/-15% alrededor del precio.
A9: Ventana para la asimetria | B9: 0.05 | D9: Compara combustible dentro de +/-5%.
A10: Umbral de cluster relevante | B10: 0.25 | D10: Una franja cuenta como cluster si tiene >=25% del maximo.
A11: Ventana de combustible inmediato | B11: 0.02 | D11: Longs a liquidar en el primer 2% de caida.
A13: B. DISTRIBUCION DE APALANCAMIENTO (supuesto editable)
A14: Tramo | B14: Apalanc. | C14: Peso | D14: Liq. long a | E14: Liq. short a | J14: Comentario
A15: Tramo 1 | B15: 5 | C15: 0.15 | D15: =-(1/B15-$B$6) -> -0.196 | E15: =1/B15-$B$6 -> 0.196 | J15: Swing / fondos. Liquidacion lejana.
A16: Tramo 2 | B16: 10 | C16: 0.3 | D16: =-(1/B16-$B$6) -> -0.096 | E16: =1/B16-$B$6 -> 0.096 | J16: El grueso del retail prudente.
A17: Tramo 3 | B17: 25 | C17: 0.3 | D17: =-(1/B17-$B$6) -> -0.036 | E17: =1/B17-$B$6 -> 0.036 | J17: Retail agresivo. Aqui nacen las cascadas.
A18: Tramo 4 | B18: 50 | C18: 0.15 | D18: =-(1/B18-$B$6) -> -0.016 | E18: =1/B18-$B$6 -> 0.016 | J18: Scalpers. Liquidacion a ~1.6%.
A19: Tramo 5 | B19: 100 | C19: 0.1 | D19: =-(1/B19-$B$6) -> -0.006 | E19: =1/B19-$B$6 -> 0.006 | J19: Apuesta pura. Se barre con cualquier mecha.
A20: Suma de pesos (debe ser 100%) | C20: =SUM(C15:C19) -> 1 | D20: =IF(ABS(C20-1)<0.001,"OK","CORRIGE LOS PESOS") -> OK
A22: C. RESUMEN DEL MAPA
A23: Longs vivos a liquidar dentro de -ventana | B23: =SUMIFS($G$44:$G$104,$F$44:$F$104,">="&-$B$9,$F$44:$F$104,"<=0") -> 0 | D23: Combustible bajista: ventas forzadas si el precio cae.
A24: Shorts vivos a liquidar dentro de +ventana | B24: =SUMIFS($H$44:$H$104,$F$44:$F$104,"<="&$B$9,$F$44:$F$104,">=0") -> 0 | D24: Combustible alcista: compras forzadas si el precio sube.
A25: Asimetria (longs / shorts) | B25: =IF(B24=0,IF(B23=0,"n/d",99),B23/B24) -> n/d | D25: El 28-ago en ETH era 7.8x hacia abajo.
A26: Iman de liquidez | B26: =IF(NOT(ISNUMBER(B25)),"SIN DATOS",IF(B25>1.5,"IMAN BAJISTA",IF(B25<0.67,"IMAN ALCISTA","EQUILIBRADO"))) -> SIN DATOS | D26: Hacia donde tiene mas razones mecanicas para ir el precio.
A27: Cluster LONG mayor: precio | B27: =IF(MAX($G$44:$G$104)=0,"n/d",INDEX($C$44:$C$104,MATCH(MAX($G$44:$G$104),$G$44:$G$104,0))) -> n/d | D27: La bolsa de longs mas grande del mapa.
A28: Cluster LONG mayor: tamano | B28: =MAX($G$44:$G$104) -> 0
A29: Cluster SHORT mayor: precio | B29: =IF(MAX($H$44:$H$104)=0,"n/d",INDEX($C$44:$C$104,MATCH(MAX($H$44:$H$104),$H$44:$H$104,0))) -> n/d | D29: La bolsa de shorts mas grande del mapa.
A30: Cluster SHORT mayor: tamano | B30: =MAX($H$44:$H$104) -> 0
A31: Primer cluster LONG relevante: franja | B31: =IF(MAX($G$44:$G$104)=0,"n/d",_xlfn.MAXIFS($B$44:$B$104,$B$44:$B$104,"<=0",$G$44:$G$104,">="&$B$10*MAX($G$44:$G$104))) -> n/d | D31: Indice de franja (auxiliar).
A32: Primer cluster LONG relevante: precio | B32: =IF(ISNUMBER(B31),$B$5*(1+B31*$B$8),"n/d") -> n/d | D32: EL NIVEL A VIGILAR: la primera parada de una cascada.
A33: Primer cluster LONG relevante: distancia | B33: =IF(ISNUMBER(B32),B32/$B$5-1,"n/d") -> n/d
A34: Primer cluster SHORT relevante: franja | B34: =IF(MAX($H$44:$H$104)=0,"n/d",_xlfn.MINIFS($B$44:$B$104,$B$44:$B$104,">=0",$H$44:$H$104,">="&$B$10*MAX($H$44:$H$104))) -> n/d | D34: Indice de franja (auxiliar).
A35: Primer cluster SHORT relevante: precio | B35: =IF(ISNUMBER(B34),$B$5*(1+B34*$B$8),"n/d") -> n/d | D35: La primera parada de un squeeze.
A36: Primer cluster SHORT relevante: distancia | B36: =IF(ISNUMBER(B35),B35/$B$5-1,"n/d") -> n/d
A37: Combustible inmediato (longs en -2%) | B37: =SUMIFS($G$44:$G$104,$F$44:$F$104,">="&-$B$11,$F$44:$F$104,"<=0") -> 0 | D37: Lo que se venderia a mercado en el primer tramo de caida.
A38: Ratio combustible / volumen medio 5m | B38: =IF(COUNT('12_Datos_5m'!$G$5:$G$504)=0,"n/d",B37/AVERAGE('12_Datos_5m'!$G$5:$G$504)) -> n/d | D38: >3x: la cascada se autoalimenta. <1x: el mercado la absorbe.
A39: Liquidaciones YA ejecutadas (estimadas): longs | B39: =SUM('14_Motor_Liq'!$AH$5:$AH$504) -> 0 | D39: Cota superior. Contrasta con la hoja 15 (liquidaciones reales).
A40: Liquidaciones YA ejecutadas (estimadas): shorts | B40: =SUM('14_Motor_Liq'!$AI$5:$AI$504) -> 0
A41: LECTURA DEL MAPA | B41: =IF(B26="SIN DATOS","Instala qBase5m para activar el mapa",B26&" | primer cluster long en "&IF(ISNUMBER(B32),ROUND(B32,0)&" ("&ROUND(B33*100,1)&"%)","n/d")&" | primer cluster short en "&IF(ISNUMBER(B35),ROUND(B35,0)&" (+"&ROUND(B36*100,1)&"%)","n/d")&IF(AND(ISNUMBER(B38),N(B38)>3)," | CASCADA AUTOALIMENTABLE","")) -> Instala qBase5m para activar el mapa
A42: D. MAPA — franjas de 0.5% (arriba = shorts por liquidar / abajo = longs por liquidar)
A43: Etiqueta | B43: Franja | C43: Precio centro | D43: Desde | E43: Hasta | F43: Distancia | G43: LONGS a liquidar | H43: SHORTS a liquidar | I43: Total | J43: Intensidad | K43: Acumulado
A44: =IF(B44=0,"<< PRECIO ACTUAL",IF(AND(G44>0,G44=MAX($G$44:$G$104)),"CLUSTER LONG MAYOR",IF(AND(H44>0,H44=MAX($H$44:$H$104)),"CLUSTER SHORT MAYOR",IF(AND(ISNUMBER($B$31),B44=$B$31),"primer cluster long",IF(AND(ISNUMBER($B$34),B44=$B$34),"primer cluster short",""))))) | B44: 30 | C44: =$B$5*(1+B44*$B$8) -> 89098.55 | D44: =$B$5*(1+(B44-0.5)*$B$8) -> 88904.857 | E44: =$B$5*(1+(B44+0.5)*$B$8) -> 89292.242 | F44: =B44*$B$8 -> 0.15 | G44: =SUMIFS('14_Motor_Liq'!$N$5:$N$504,'14_Motor_Liq'!$M$5:$M$504,">="&D44,'14_Motor_Liq'!$M$5:$M$504,"<"&E44)+SUMIFS('14_Motor_Liq'!$R$5:$R$504,'14_Motor_Liq'!$Q$5:$Q$504,">="&D44,'14_Motor_Liq'!$Q$5:$Q$504,"<"&E44)+SUMIFS('14_Motor_Liq'!$V$5:$V$504,'14_Motor_Liq'!$U$5:$U$504,">="&D44,'14_Motor_Liq'!$U$5:$U$504,"<"&E44)+SUMIFS('14_Motor_Liq'!$Z$5:$Z$504,'14_Motor_Liq'!$Y$5:$Y$504,">="&D44,'14_Motor_Liq'!$Y$5:$Y$504,"<"&E44)+SUMIFS('14_Motor_Liq'!$AD$5:$AD$504,'14_Motor_Liq'!$AC$5:$AC$504,">="&D44,'14_Motor_Liq'!$AC$5:$AC$504,"<"&E44) -> 0 | H44: =SUMIFS('14_Motor_Liq'!$P$5:$P$504,'14_Motor_Liq'!$O$5:$O$504,">="&D44,'14_Motor_Liq'!$O$5:$O$504,"<"&E44)+SUMIFS('14_Motor_Liq'!$T$5:$T$504,'14_Motor_Liq'!$S$5:$S$504,">="&D44,'14_Motor_Liq'!$S$5:$S$504,"<"&E44)+SUMIFS('14_Motor_Liq'!$X$5:$X$504,'14_Motor_Liq'!$W$5:$W$504,">="&D44,'14_Motor_Liq'!$W$5:$W$504,"<"&E44)+SUMIFS('14_Motor_Liq'!$AB$5:$AB$504,'14_Motor_Liq'!$AA$5:$AA$504,">="&D44,'14_Motor_Liq'!$AA$5:$AA$504,"<"&E44)+SUMIFS('14_Motor_Liq'!$AF$5:$AF$504,'14_Motor_Liq'!$AE$5:$AE$504,">="&D44,'14_Motor_Liq'!$AE$5:$AE$504,"<"&E44) -> 0 | I44: =G44+H44 -> 0 | J44: =IF(MAX($I$44:$I$104)=0,"",REPT("|",ROUND(I44/MAX($I$44:$I$104)*45,0))) | K44: =IF(B44>0,SUMIFS($H$44:$H$104,$B$44:$B$104,">=0",$B$44:$B$104,"<="&B44),IF(B44<0,SUMIFS($G$44:$G$104,$B$44:$B$104,"<=0",$B$44:$B$104,">="&B44),G44+H44)) -> 0
A45: =IF(B45=0,"<< PRECIO ACTUAL",IF(AND(G45>0,G45=MAX($G$44:$G$104)),"CLUSTER LONG MAYOR",IF(AND(H45>0,H45=MAX($H$44:$H$104)),"CLUSTER SHORT MAYOR",IF(AND(ISNUMBER($B$31),B45=$B$31),"primer cluster long",IF(AND(ISNUMBER($B$34),B45=$B$34),"primer cluster short",""))))) | B45: 29 | C45: =$B$5*(1+B45*$B$8) -> 88711.165 | D45: =$B$5*(1+(B45-0.5)*$B$8) -> 88517.473 | E45: =$B$5*(1+(B45+0.5)*$B$8) -> 88904.857 | F45: =B45*$B$8 -> 0.145 | G45: =SUMIFS('14_Motor_Liq'!$N$5:$N$504,'14_Motor_Liq'!$M$5:$M$504,">="&D45,'14_Motor_Liq'!$M$5:$M$504,"<"&E45)+SUMIFS('14_Motor_Liq'!$R$5:$R$504,'14_Motor_Liq'!$Q$5:$Q$504,">="&D45,'14_Motor_Liq'!$Q$5:$Q$504,"<"&E45)+SUMIFS('14_Motor_Liq'!$V$5:$V$504,'14_Motor_Liq'!$U$5:$U$504,">="&D45,'14_Motor_Liq'!$U$5:$U$504,"<"&E45)+SUMIFS('14_Motor_Liq'!$Z$5:$Z$504,'14_Motor_Liq'!$Y$5:$Y$504,">="&D45,'14_Motor_Liq'!$Y$5:$Y$504,"<"&E45)+SUMIFS('14_Motor_Liq'!$AD$5:$AD$504,'14_Motor_Liq'!$AC$5:$AC$504,">="&D45,'14_Motor_Liq'!$AC$5:$AC$504,"<"&E45) -> 0 | H45: =SUMIFS('14_Motor_Liq'!$P$5:$P$504,'14_Motor_Liq'!$O$5:$O$504,">="&D45,'14_Motor_Liq'!$O$5:$O$504,"<"&E45)+SUMIFS('14_Motor_Liq'!$T$5:$T$504,'14_Motor_Liq'!$S$5:$S$504,">="&D45,'14_Motor_Liq'!$S$5:$S$504,"<"&E45)+SUMIFS('14_Motor_Liq'!$X$5:$X$504,'14_Motor_Liq'!$W$5:$W$504,">="&D45,'14_Motor_Liq'!$W$5:$W$504,"<"&E45)+SUMIFS('14_Motor_Liq'!$AB$5:$AB$504,'14_Motor_Liq'!$AA$5:$AA$504,">="&D45,'14_Motor_Liq'!$AA$5:$AA$504,"<"&E45)+SUMIFS('14_Motor_Liq'!$AF$5:$AF$504,'14_Motor_Liq'!$AE$5:$AE$504,">="&D45,'14_Motor_Liq'!$AE$5:$AE$504,"<"&E45) -> 0 | I45: =G45+H45 -> 0 | J45: =IF(MAX($I$44:$I$104)=0,"",REPT("|",ROUND(I45/MAX($I$44:$I$104)*45,0))) | K45: =IF(B45>0,SUMIFS($H$44:$H$104,$B$44:$B$104,">=0",$B$44:$B$104,"<="&B45),IF(B45<0,SUMIFS($G$44:$G$104,$B$44:$B$104,"<=0",$B$44:$B$104,">="&B45),G45+H45)) -> 0
A46: =IF(B46=0,"<< PRECIO ACTUAL",IF(AND(G46>0,G46=MAX($G$44:$G$104)),"CLUSTER LONG MAYOR",IF(AND(H46>0,H46=MAX($H$44:$H$104)),"CLUSTER SHORT MAYOR",IF(AND(ISNUMBER($B$31),B46=$B$31),"primer cluster long",IF(AND(ISNUMBER($B$34),B46=$B$34),"primer cluster short",""))))) | B46: 28 | C46: =$B$5*(1+B46*$B$8) -> 88323.78 | D46: =$B$5*(1+(B46-0.5)*$B$8) -> 88130.087 | E46: =$B$5*(1+(B46+0.5)*$B$8) -> 88517.473 | F46: =B46*$B$8 -> 0.14 | G46: =SUMIFS('14_Motor_Liq'!$N$5:$N$504,'14_Motor_Liq'!$M$5:$M$504,">="&D46,'14_Motor_Liq'!$M$5:$M$504,"<"&E46)+SUMIFS('14_Motor_Liq'!$R$5:$R$504,'14_Motor_Liq'!$Q$5:$Q$504,">="&D46,'14_Motor_Liq'!$Q$5:$Q$504,"<"&E46)+SUMIFS('14_Motor_Liq'!$V$5:$V$504,'14_Motor_Liq'!$U$5:$U$504,">="&D46,'14_Motor_Liq'!$U$5:$U$504,"<"&E46)+SUMIFS('14_Motor_Liq'!$Z$5:$Z$504,'14_Motor_Liq'!$Y$5:$Y$504,">="&D46,'14_Motor_Liq'!$Y$5:$Y$504,"<"&E46)+SUMIFS('14_Motor_Liq'!$AD$5:$AD$504,'14_Motor_Liq'!$AC$5:$AC$504,">="&D46,'14_Motor_Liq'!$AC$5:$AC$504,"<"&E46) -> 0 | H46: =SUMIFS('14_Motor_Liq'!$P$5:$P$504,'14_Motor_Liq'!$O$5:$O$504,">="&D46,'14_Motor_Liq'!$O$5:$O$504,"<"&E46)+SUMIFS('14_Motor_Liq'!$T$5:$T$504,'14_Motor_Liq'!$S$5:$S$504,">="&D46,'14_Motor_Liq'!$S$5:$S$504,"<"&E46)+SUMIFS('14_Motor_Liq'!$X$5:$X$504,'14_Motor_Liq'!$W$5:$W$504,">="&D46,'14_Motor_Liq'!$W$5:$W$504,"<"&E46)+SUMIFS('14_Motor_Liq'!$AB$5:$AB$504,'14_Motor_Liq'!$AA$5:$AA$504,">="&D46,'14_Motor_Liq'!$AA$5:$AA$504,"<"&E46)+SUMIFS('14_Motor_Liq'!$AF$5:$AF$504,'14_Motor_Liq'!$AE$5:$AE$504,">="&D46,'14_Motor_Liq'!$AE$5:$AE$504,"<"&E46) -> 0 | I46: =G46+H46 -> 0 | J46: =IF(MAX($I$44:$I$104)=0,"",REPT("|",ROUND(I46/MAX($I$44:$I$104)*45,0))) | K46: =IF(B46>0,SUMIFS($H$44:$H$104,$B$44:$B$104,">=0",$B$44:$B$104,"<="&B46),IF(B46<0,SUMIFS($G$44:$G$104,$B$44:$B$104,"<=0",$B$44:$B$104,">="&B46),G46+H46)) -> 0
A47: =IF(B47=0,"<< PRECIO ACTUAL",IF(AND(G47>0,G47=MAX($G$44:$G$104)),"CLUSTER LONG MAYOR",IF(AND(H47>0,H47=MAX($H$44:$H$104)),"CLUSTER SHORT MAYOR",IF(AND(ISNUMBER($B$31),B47=$B$31),"primer cluster long",IF(AND(ISNUMBER($B$34),B47=$B$34),"primer cluster short",""))))) | B47: 27 | C47: =$B$5*(1+B47*$B$8) -> 87936.395 | D47: =$B$5*(1+(B47-0.5)*$B$8) -> 87742.702 | E47: =$B$5*(1+(B47+0.5)*$B$8) -> 88130.087 | F47: =B47*$B$8 -> 0.135 | G47: =SUMIFS('14_Motor_Liq'!$N$5:$N$504,'14_Motor_Liq'!$M$5:$M$504,">="&D47,'14_Motor_Liq'!$M$5:$M$504,"<"&E47)+SUMIFS('14_Motor_Liq'!$R$5:$R$504,'14_Motor_Liq'!$Q$5:$Q$504,">="&D47,'14_Motor_Liq'!$Q$5:$Q$504,"<"&E47)+SUMIFS('14_Motor_Liq'!$V$5:$V$504,'14_Motor_Liq'!$U$5:$U$504,">="&D47,'14_Motor_Liq'!$U$5:$U$504,"<"&E47)+SUMIFS('14_Motor_Liq'!$Z$5:$Z$504,'14_Motor_Liq'!$Y$5:$Y$504,">="&D47,'14_Motor_Liq'!$Y$5:$Y$504,"<"&E47)+SUMIFS('14_Motor_Liq'!$AD$5:$AD$504,'14_Motor_Liq'!$AC$5:$AC$504,">="&D47,'14_Motor_Liq'!$AC$5:$AC$504,"<"&E47) -> 0 | H47: =SUMIFS('14_Motor_Liq'!$P$5:$P$504,'14_Motor_Liq'!$O$5:$O$504,">="&D47,'14_Motor_Liq'!$O$5:$O$504,"<"&E47)+SUMIFS('14_Motor_Liq'!$T$5:$T$504,'14_Motor_Liq'!$S$5:$S$504,">="&D47,'14_Motor_Liq'!$S$5:$S$504,"<"&E47)+SUMIFS('14_Motor_Liq'!$X$5:$X$504,'14_Motor_Liq'!$W$5:$W$504,">="&D47,'14_Motor_Liq'!$W$5:$W$504,"<"&E47)+SUMIFS('14_Motor_Liq'!$AB$5:$AB$504,'14_Motor_Liq'!$AA$5:$AA$504,">="&D47,'14_Motor_Liq'!$AA$5:$AA$504,"<"&E47)+SUMIFS('14_Motor_Liq'!$AF$5:$AF$504,'14_Motor_Liq'!$AE$5:$AE$504,">="&D47,'14_Motor_Liq'!$AE$5:$AE$504,"<"&E47) -> 0 | I47: =G47+H47 -> 0 | J47: =IF(MAX($I$44:$I$104)=0,"",REPT("|",ROUND(I47/MAX($I$44:$I$104)*45,0))) | K47: =IF(B47>0,SUMIFS($H$44:$H$104,$B$44:$B$104,">=0",$B$44:$B$104,"<="&B47),IF(B47<0,SUMIFS($G$44:$G$104,$B$44:$B$104,"<=0",$B$44:$B$104,">="&B47),G47+H47)) -> 0
A48: =IF(B48=0,"<< PRECIO ACTUAL",IF(AND(G48>0,G48=MAX($G$44:$G$104)),"CLUSTER LONG MAYOR",IF(AND(H48>0,H48=MAX($H$44:$H$104)),"CLUSTER SHORT MAYOR",IF(AND(ISNUMBER($B$31),B48=$B$31),"primer cluster long",IF(AND(ISNUMBER($B$34),B48=$B$34),"primer cluster short",""))))) | B48: 26 | C48: =$B$5*(1+B48*$B$8) -> 87549.01 | D48: =$B$5*(1+(B48-0.5)*$B$8) -> 87355.318 | E48: =$B$5*(1+(B48+0.5)*$B$8) -> 87742.702 | F48: =B48*$B$8 -> 0.13 | G48: =SUMIFS('14_Motor_Liq'!$N$5:$N$504,'14_Motor_Liq'!$M$5:$M$504,">="&D48,'14_Motor_Liq'!$M$5:$M$504,"<"&E48)+SUMIFS('14_Motor_Liq'!$R$5:$R$504,'14_Motor_Liq'!$Q$5:$Q$504,">="&D48,'14_Motor_Liq'!$Q$5:$Q$504,"<"&E48)+SUMIFS('14_Motor_Liq'!$V$5:$V$504,'14_Motor_Liq'!$U$5:$U$504,">="&D48,'14_Motor_Liq'!$U$5:$U$504,"<"&E48)+SUMIFS('14_Motor_Liq'!$Z$5:$Z$504,'14_Motor_Liq'!$Y$5:$Y$504,">="&D48,'14_Motor_Liq'!$Y$5:$Y$504,"<"&E48)+SUMIFS('14_Motor_Liq'!$AD$5:$AD$504,'14_Motor_Liq'!$AC$5:$AC$504,">="&D48,'14_Motor_Liq'!$AC$5:$AC$504,"<"&E48) -> 0 | H48: =SUMIFS('14_Motor_Liq'!$P$5:$P$504,'14_Motor_Liq'!$O$5:$O$504,">="&D48,'14_Motor_Liq'!$O$5:$O$504,"<"&E48)+SUMIFS('14_Motor_Liq'!$T$5:$T$504,'14_Motor_Liq'!$S$5:$S$504,">="&D48,'14_Motor_Liq'!$S$5:$S$504,"<"&E48)+SUMIFS('14_Motor_Liq'!$X$5:$X$504,'14_Motor_Liq'!$W$5:$W$504,">="&D48,'14_Motor_Liq'!$W$5:$W$504,"<"&E48)+SUMIFS('14_Motor_Liq'!$AB$5:$AB$504,'14_Motor_Liq'!$AA$5:$AA$504,">="&D48,'14_Motor_Liq'!$AA$5:$AA$504,"<"&E48)+SUMIFS('14_Motor_Liq'!$AF$5:$AF$504,'14_Motor_Liq'!$AE$5:$AE$504,">="&D48,'14_Motor_Liq'!$AE$5:$AE$504,"<"&E48) -> 0 | I48: =G48+H48 -> 0 | J48: =IF(MAX($I$44:$I$104)=0,"",REPT("|",ROUND(I48/MAX($I$44:$I$104)*45,0))) | K48: =IF(B48>0,SUMIFS($H$44:$H$104,$B$44:$B$104,">=0",$B$44:$B$104,"<="&B48),IF(B48<0,SUMIFS($G$44:$G$104,$B$44:$B$104,"<=0",$B$44:$B$104,">="&B48),G48+H48)) -> 0
A49: =IF(B49=0,"<< PRECIO ACTUAL",IF(AND(G49>0,G49=MAX($G$44:$G$104)),"CLUSTER LONG MAYOR",IF(AND(H49>0,H49=MAX($H$44:$H$104)),"CLUSTER SHORT MAYOR",IF(AND(ISNUMBER($B$31),B49=$B$31),"primer cluster long",IF(AND(ISNUMBER($B$34),B49=$B$34),"primer cluster short",""))))) | B49: 25 | C49: =$B$5*(1+B49*$B$8) -> 87161.625 | D49: =$B$5*(1+(B49-0.5)*$B$8) -> 86967.932 | E49: =$B$5*(1+(B49+0.5)*$B$8) -> 87355.318 | F49: =B49*$B$8 -> 0.125 | G49: =SUMIFS('14_Motor_Liq'!$N$5:$N$504,'14_Motor_Liq'!$M$5:$M$504,">="&D49,'14_Motor_Liq'!$M$5:$M$504,"<"&E49)+SUMIFS('14_Motor_Liq'!$R$5:$R$504,'14_Motor_Liq'!$Q$5:$Q$504,">="&D49,'14_Motor_Liq'!$Q$5:$Q$504,"<"&E49)+SUMIFS('14_Motor_Liq'!$V$5:$V$504,'14_Motor_Liq'!$U$5:$U$504,">="&D49,'14_Motor_Liq'!$U$5:$U$504,"<"&E49)+SUMIFS('14_Motor_Liq'!$Z$5:$Z$504,'14_Motor_Liq'!$Y$5:$Y$504,">="&D49,'14_Motor_Liq'!$Y$5:$Y$504,"<"&E49)+SUMIFS('14_Motor_Liq'!$AD$5:$AD$504,'14_Motor_Liq'!$AC$5:$AC$504,">="&D49,'14_Motor_Liq'!$AC$5:$AC$504,"<"&E49) -> 0 | H49: =SUMIFS('14_Motor_Liq'!$P$5:$P$504,'14_Motor_Liq'!$O$5:$O$504,">="&D49,'14_Motor_Liq'!$O$5:$O$504,"<"&E49)+SUMIFS('14_Motor_Liq'!$T$5:$T$504,'14_Motor_Liq'!$S$5:$S$504,">="&D49,'14_Motor_Liq'!$S$5:$S$504,"<"&E49)+SUMIFS('14_Motor_Liq'!$X$5:$X$504,'14_Motor_Liq'!$W$5:$W$504,">="&D49,'14_Motor_Liq'!$W$5:$W$504,"<"&E49)+SUMIFS('14_Motor_Liq'!$AB$5:$AB$504,'14_Motor_Liq'!$AA$5:$AA$504,">="&D49,'14_Motor_Liq'!$AA$5:$AA$504,"<"&E49)+SUMIFS('14_Motor_Liq'!$AF$5:$AF$504,'14_Motor_Liq'!$AE$5:$AE$504,">="&D49,'14_Motor_Liq'!$AE$5:$AE$504,"<"&E49) -> 0 | I49: =G49+H49 -> 0 | J49: =IF(MAX($I$44:$I$104)=0,"",REPT("|",ROUND(I49/MAX($I$44:$I$104)*45,0))) | K49: =IF(B49>0,SUMIFS($H$44:$H$104,$B$44:$B$104,">=0",$B$44:$B$104,"<="&B49),IF(B49<0,SUMIFS($G$44:$G$104,$B$44:$B$104,"<=0",$B$44:$B$104,">="&B49),G49+H49)) -> 0
A50: =IF(B50=0,"<< PRECIO ACTUAL",IF(AND(G50>0,G50=MAX($G$44:$G$104)),"CLUSTER LONG MAYOR",IF(AND(H50>0,H50=MAX($H$44:$H$104)),"CLUSTER SHORT MAYOR",IF(AND(ISNUMBER($B$31),B50=$B$31),"primer cluster long",IF(AND(ISNUMBER($B$34),B50=$B$34),"primer cluster short",""))))) | B50: 24 | C50: =$B$5*(1+B50*$B$8) -> 86774.24 | D50: =$B$5*(1+(B50-0.5)*$B$8) -> 86580.548 | E50: =$B$5*(1+(B50+0.5)*$B$8) -> 86967.932 | F50: =B50*$B$8 -> 0.12 | G50: =SUMIFS('14_Motor_Liq'!$N$5:$N$504,'14_Motor_Liq'!$M$5:$M$504,">="&D50,'14_Motor_Liq'!$M$5:$M$504,"<"&E50)+SUMIFS('14_Motor_Liq'!$R$5:$R$504,'14_Motor_Liq'!$Q$5:$Q$504,">="&D50,'14_Motor_Liq'!$Q$5:$Q$504,"<"&E50)+SUMIFS('14_Motor_Liq'!$V$5:$V$504,'14_Motor_Liq'!$U$5:$U$504,">="&D50,'14_Motor_Liq'!$U$5:$U$504,"<"&E50)+SUMIFS('14_Motor_Liq'!$Z$5:$Z$504,'14_Motor_Liq'!$Y$5:$Y$504,">="&D50,'14_Motor_Liq'!$Y$5:$Y$504,"<"&E50)+SUMIFS('14_Motor_Liq'!$AD$5:$AD$504,'14_Motor_Liq'!$AC$5:$AC$504,">="&D50,'14_Motor_Liq'!$AC$5:$AC$504,"<"&E50) -> 0 | H50: =SUMIFS('14_Motor_Liq'!$P$5:$P$504,'14_Motor_Liq'!$O$5:$O$504,">="&D50,'14_Motor_Liq'!$O$5:$O$504,"<"&E50)+SUMIFS('14_Motor_Liq'!$T$5:$T$504,'14_Motor_Liq'!$S$5:$S$504,">="&D50,'14_Motor_Liq'!$S$5:$S$504,"<"&E50)+SUMIFS('14_Motor_Liq'!$X$5:$X$504,'14_Motor_Liq'!$W$5:$W$504,">="&D50,'14_Motor_Liq'!$W$5:$W$504,"<"&E50)+SUMIFS('14_Motor_Liq'!$AB$5:$AB$504,'14_Motor_Liq'!$AA$5:$AA$504,">="&D50,'14_Motor_Liq'!$AA$5:$AA$504,"<"&E50)+SUMIFS('14_Motor_Liq'!$AF$5:$AF$504,'14_Motor_Liq'!$AE$5:$AE$504,">="&D50,'14_Motor_Liq'!$AE$5:$AE$504,"<"&E50) -> 0 | I50: =G50+H50 -> 0 | J50: =IF(MAX($I$44:$I$104)=0,"",REPT("|",ROUND(I50/MAX($I$44:$I$104)*45,0))) | K50: =IF(B50>0,SUMIFS($H$44:$H$104,$B$44:$B$104,">=0",$B$44:$B$104,"<="&B50),IF(B50<0,SUMIFS($G$44:$G$104,$B$44:$B$104,"<=0",$B$44:$B$104,">="&B50),G50+H50)) -> 0
A51: =IF(B51=0,"<< PRECIO ACTUAL",IF(AND(G51>0,G51=MAX($G$44:$G$104)),"CLUSTER LONG MAYOR",IF(AND(H51>0,H51=MAX($H$44:$H$104)),"CLUSTER SHORT MAYOR",IF(AND(ISNUMBER($B$31),B51=$B$31),"primer cluster long",IF(AND(ISNUMBER($B$34),B51=$B$34),"primer cluster short",""))))) | B51: 23 | C51: =$B$5*(1+B51*$B$8) -> 86386.855 | D51: =$B$5*(1+(B51-0.5)*$B$8) -> 86193.163 | E51: =$B$5*(1+(B51+0.5)*$B$8) -> 86580.548 | F51: =B51*$B$8 -> 0.115 | G51: =SUMIFS('14_Motor_Liq'!$N$5:$N$504,'14_Motor_Liq'!$M$5:$M$504,">="&D51,'14_Motor_Liq'!$M$5:$M$504,"<"&E51)+SUMIFS('14_Motor_Liq'!$R$5:$R$504,'14_Motor_Liq'!$Q$5:$Q$504,">="&D51,'14_Motor_Liq'!$Q$5:$Q$504,"<"&E51)+SUMIFS('14_Motor_Liq'!$V$5:$V$504,'14_Motor_Liq'!$U$5:$U$504,">="&D51,'14_Motor_Liq'!$U$5:$U$504,"<"&E51)+SUMIFS('14_Motor_Liq'!$Z$5:$Z$504,'14_Motor_Liq'!$Y$5:$Y$504,">="&D51,'14_Motor_Liq'!$Y$5:$Y$504,"<"&E51)+SUMIFS('14_Motor_Liq'!$AD$5:$AD$504,'14_Motor_Liq'!$AC$5:$AC$504,">="&D51,'14_Motor_Liq'!$AC$5:$AC$504,"<"&E51) -> 0 | H51: =SUMIFS('14_Motor_Liq'!$P$5:$P$504,'14_Motor_Liq'!$O$5:$O$504,">="&D51,'14_Motor_Liq'!$O$5:$O$504,"<"&E51)+SUMIFS('14_Motor_Liq'!$T$5:$T$504,'14_Motor_Liq'!$S$5:$S$504,">="&D51,'14_Motor_Liq'!$S$5:$S$504,"<"&E51)+SUMIFS('14_Motor_Liq'!$X$5:$X$504,'14_Motor_Liq'!$W$5:$W$504,">="&D51,'14_Motor_Liq'!$W$5:$W$504,"<"&E51)+SUMIFS('14_Motor_Liq'!$AB$5:$AB$504,'14_Motor_Liq'!$AA$5:$AA$504,">="&D51,'14_Motor_Liq'!$AA$5:$AA$504,"<"&E51)+SUMIFS('14_Motor_Liq'!$AF$5:$AF$504,'14_Motor_Liq'!$AE$5:$AE$504,">="&D51,'14_Motor_Liq'!$AE$5:$AE$504,"<"&E51) -> 0 | I51: =G51+H51 -> 0 | J51: =IF(MAX($I$44:$I$104)=0,"",REPT("|",ROUND(I51/MAX($I$44:$I$104)*45,0))) | K51: =IF(B51>0,SUMIFS($H$44:$H$104,$B$44:$B$104,">=0",$B$44:$B$104,"<="&B51),IF(B51<0,SUMIFS($G$44:$G$104,$B$44:$B$104,"<=0",$B$44:$B$104,">="&B51),G51+H51)) -> 0
A52: =IF(B52=0,"<< PRECIO ACTUAL",IF(AND(G52>0,G52=MAX($G$44:$G$104)),"CLUSTER LONG MAYOR",IF(AND(H52>0,H52=MAX($H$44:$H$104)),"CLUSTER SHORT MAYOR",IF(AND(ISNUMBER($B$31),B52=$B$31),"primer cluster long",IF(AND(ISNUMBER($B$34),B52=$B$34),"primer cluster short",""))))) | B52: 22 | C52: =$B$5*(1+B52*$B$8) -> 85999.47 | D52: =$B$5*(1+(B52-0.5)*$B$8) -> 85805.777 | E52: =$B$5*(1+(B52+0.5)*$B$8) -> 86193.163 | F52: =B52*$B$8 -> 0.11 | G52: =SUMIFS('14_Motor_Liq'!$N$5:$N$504,'14_Motor_Liq'!$M$5:$M$504,">="&D52,'14_Motor_Liq'!$M$5:$M$504,"<"&E52)+SUMIFS('14_Motor_Liq'!$R$5:$R$504,'14_Motor_Liq'!$Q$5:$Q$504,">="&D52,'14_Motor_Liq'!$Q$5:$Q$504,"<"&E52)+SUMIFS('14_Motor_Liq'!$V$5:$V$504,'14_Motor_Liq'!$U$5:$U$504,">="&D52,'14_Motor_Liq'!$U$5:$U$504,"<"&E52)+SUMIFS('14_Motor_Liq'!$Z$5:$Z$504,'14_Motor_Liq'!$Y$5:$Y$504,">="&D52,'14_Motor_Liq'!$Y$5:$Y$504,"<"&E52)+SUMIFS('14_Motor_Liq'!$AD$5:$AD$504,'14_Motor_Liq'!$AC$5:$AC$504,">="&D52,'14_Motor_Liq'!$AC$5:$AC$504,"<"&E52) -> 0 | H52: =SUMIFS('14_Motor_Liq'!$P$5:$P$504,'14_Motor_Liq'!$O$5:$O$504,">="&D52,'14_Motor_Liq'!$O$5:$O$504,"<"&E52)+SUMIFS('14_Motor_Liq'!$T$5:$T$504,'14_Motor_Liq'!$S$5:$S$504,">="&D52,'14_Motor_Liq'!$S$5:$S$504,"<"&E52)+SUMIFS('14_Motor_Liq'!$X$5:$X$504,'14_Motor_Liq'!$W$5:$W$504,">="&D52,'14_Motor_Liq'!$W$5:$W$504,"<"&E52)+SUMIFS('14_Motor_Liq'!$AB$5:$AB$504,'14_Motor_Liq'!$AA$5:$AA$504,">="&D52,'14_Motor_Liq'!$AA$5:$AA$504,"<"&E52)+SUMIFS('14_Motor_Liq'!$AF$5:$AF$504,'14_Motor_Liq'!$AE$5:$AE$504,">="&D52,'14_Motor_Liq'!$AE$5:$AE$504,"<"&E52) -> 0 | I52: =G52+H52 -> 0 | J52: =IF(MAX($I$44:$I$104)=0,"",REPT("|",ROUND(I52/MAX($I$44:$I$104)*45,0))) | K52: =IF(B52>0,SUMIFS($H$44:$H$104,$B$44:$B$104,">=0",$B$44:$B$104,"<="&B52),IF(B52<0,SUMIFS($G$44:$G$104,$B$44:$B$104,"<=0",$B$44:$B$104,">="&B52),G52+H52)) -> 0
A53: =IF(B53=0,"<< PRECIO ACTUAL",IF(AND(G53>0,G53=MAX($G$44:$G$104)),"CLUSTER LONG MAYOR",IF(AND(H53>0,H53=MAX($H$44:$H$104)),"CLUSTER SHORT MAYOR",IF(AND(ISNUMBER($B$31),B53=$B$31),"primer cluster long",IF(AND(ISNUMBER($B$34),B53=$B$34),"primer cluster short",""))))) | B53: 21 | C53: =$B$5*(1+B53*$B$8) -> 85612.085 | D53: =$B$5*(1+(B53-0.5)*$B$8) -> 85418.393 | E53: =$B$5*(1+(B53+0.5)*$B$8) -> 85805.777 | F53: =B53*$B$8 -> 0.105 | G53: =SUMIFS('14_Motor_Liq'!$N$5:$N$504,'14_Motor_Liq'!$M$5:$M$504,">="&D53,'14_Motor_Liq'!$M$5:$M$504,"<"&E53)+SUMIFS('14_Motor_Liq'!$R$5:$R$504,'14_Motor_Liq'!$Q$5:$Q$504,">="&D53,'14_Motor_Liq'!$Q$5:$Q$504,"<"&E53)+SUMIFS('14_Motor_Liq'!$V$5:$V$504,'14_Motor_Liq'!$U$5:$U$504,">="&D53,'14_Motor_Liq'!$U$5:$U$504,"<"&E53)+SUMIFS('14_Motor_Liq'!$Z$5:$Z$504,'14_Motor_Liq'!$Y$5:$Y$504,">="&D53,'14_Motor_Liq'!$Y$5:$Y$504,"<"&E53)+SUMIFS('14_Motor_Liq'!$AD$5:$AD$504,'14_Motor_Liq'!$AC$5:$AC$504,">="&D53,'14_Motor_Liq'!$AC$5:$AC$504,"<"&E53) -> 0 | H53: =SUMIFS('14_Motor_Liq'!$P$5:$P$504,'14_Motor_Liq'!$O$5:$O$504,">="&D53,'14_Motor_Liq'!$O$5:$O$504,"<"&E53)+SUMIFS('14_Motor_Liq'!$T$5:$T$504,'14_Motor_Liq'!$S$5:$S$504,">="&D53,'14_Motor_Liq'!$S$5:$S$504,"<"&E53)+SUMIFS('14_Motor_Liq'!$X$5:$X$504,'14_Motor_Liq'!$W$5:$W$504,">="&D53,'14_Motor_Liq'!$W$5:$W$504,"<"&E53)+SUMIFS('14_Motor_Liq'!$AB$5:$AB$504,'14_Motor_Liq'!$AA$5:$AA$504,">="&D53,'14_Motor_Liq'!$AA$5:$AA$504,"<"&E53)+SUMIFS('14_Motor_Liq'!$AF$5:$AF$504,'14_Motor_Liq'!$AE$5:$AE$504,">="&D53,'14_Motor_Liq'!$AE$5:$AE$504,"<"&E53) -> 0 | I53: =G53+H53 -> 0 | J53: =IF(MAX($I$44:$I$104)=0,"",REPT("|",ROUND(I53/MAX($I$44:$I$104)*45,0))) | K53: =IF(B53>0,SUMIFS($H$44:$H$104,$B$44:$B$104,">=0",$B$44:$B$104,"<="&B53),IF(B53<0,SUMIFS($G$44:$G$104,$B$44:$B$104,"<=0",$B$44:$B$104,">="&B53),G53+H53)) -> 0
A54: =IF(B54=0,"<< PRECIO ACTUAL",IF(AND(G54>0,G54=MAX($G$44:$G$104)),"CLUSTER LONG MAYOR",IF(AND(H54>0,H54=MAX($H$44:$H$104)),"CLUSTER SHORT MAYOR",IF(AND(ISNUMBER($B$31),B54=$B$31),"primer cluster long",IF(AND(ISNUMBER($B$34),B54=$B$34),"primer cluster short",""))))) | B54: 20 | C54: =$B$5*(1+B54*$B$8) -> 85224.7 | D54: =$B$5*(1+(B54-0.5)*$B$8) -> 85031.008 | E54: =$B$5*(1+(B54+0.5)*$B$8) -> 85418.393 | F54: =B54*$B$8 -> 0.1 | G54: =SUMIFS('14_Motor_Liq'!$N$5:$N$504,'14_Motor_Liq'!$M$5:$M$504,">="&D54,'14_Motor_Liq'!$M$5:$M$504,"<"&E54)+SUMIFS('14_Motor_Liq'!$R$5:$R$504,'14_Motor_Liq'!$Q$5:$Q$504,">="&D54,'14_Motor_Liq'!$Q$5:$Q$504,"<"&E54)+SUMIFS('14_Motor_Liq'!$V$5:$V$504,'14_Motor_Liq'!$U$5:$U$504,">="&D54,'14_Motor_Liq'!$U$5:$U$504,"<"&E54)+SUMIFS('14_Motor_Liq'!$Z$5:$Z$504,'14_Motor_Liq'!$Y$5:$Y$504,">="&D54,'14_Motor_Liq'!$Y$5:$Y$504,"<"&E54)+SUMIFS('14_Motor_Liq'!$AD$5:$AD$504,'14_Motor_Liq'!$AC$5:$AC$504,">="&D54,'14_Motor_Liq'!$AC$5:$AC$504,"<"&E54) -> 0 | H54: =SUMIFS('14_Motor_Liq'!$P$5:$P$504,'14_Motor_Liq'!$O$5:$O$504,">="&D54,'14_Motor_Liq'!$O$5:$O$504,"<"&E54)+SUMIFS('14_Motor_Liq'!$T$5:$T$504,'14_Motor_Liq'!$S$5:$S$504,">="&D54,'14_Motor_Liq'!$S$5:$S$504,"<"&E54)+SUMIFS('14_Motor_Liq'!$X$5:$X$504,'14_Motor_Liq'!$W$5:$W$504,">="&D54,'14_Motor_Liq'!$W$5:$W$504,"<"&E54)+SUMIFS('14_Motor_Liq'!$AB$5:$AB$504,'14_Motor_Liq'!$AA$5:$AA$504,">="&D54,'14_Motor_Liq'!$AA$5:$AA$504,"<"&E54)+SUMIFS('14_Motor_Liq'!$AF$5:$AF$504,'14_Motor_Liq'!$AE$5:$AE$504,">="&D54,'14_Motor_Liq'!$AE$5:$AE$504,"<"&E54) -> 0 | I54: =G54+H54 -> 0 | J54: =IF(MAX($I$44:$I$104)=0,"",REPT("|",ROUND(I54/MAX($I$44:$I$104)*45,0))) | K54: =IF(B54>0,SUMIFS($H$44:$H$104,$B$44:$B$104,">=0",$B$44:$B$104,"<="&B54),IF(B54<0,SUMIFS($G$44:$G$104,$B$44:$B$104,"<=0",$B$44:$B$104,">="&B54),G54+H54)) -> 0
A55: =IF(B55=0,"<< PRECIO ACTUAL",IF(AND(G55>0,G55=MAX($G$44:$G$104)),"CLUSTER LONG MAYOR",IF(AND(H55>0,H55=MAX($H$44:$H$104)),"CLUSTER SHORT MAYOR",IF(AND(ISNUMBER($B$31),B55=$B$31),"primer cluster long",IF(AND(ISNUMBER($B$34),B55=$B$34),"primer cluster short",""))))) | B55: 19 | C55: =$B$5*(1+B55*$B$8) -> 84837.315 | D55: =$B$5*(1+(B55-0.5)*$B$8) -> 84643.622 | E55: =$B$5*(1+(B55+0.5)*$B$8) -> 85031.008 | F55: =B55*$B$8 -> 0.095 | G55: =SUMIFS('14_Motor_Liq'!$N$5:$N$504,'14_Motor_Liq'!$M$5:$M$504,">="&D55,'14_Motor_Liq'!$M$5:$M$504,"<"&E55)+SUMIFS('14_Motor_Liq'!$R$5:$R$504,'14_Motor_Liq'!$Q$5:$Q$504,">="&D55,'14_Motor_Liq'!$Q$5:$Q$504,"<"&E55)+SUMIFS('14_Motor_Liq'!$V$5:$V$504,'14_Motor_Liq'!$U$5:$U$504,">="&D55,'14_Motor_Liq'!$U$5:$U$504,"<"&E55)+SUMIFS('14_Motor_Liq'!$Z$5:$Z$504,'14_Motor_Liq'!$Y$5:$Y$504,">="&D55,'14_Motor_Liq'!$Y$5:$Y$504,"<"&E55)+SUMIFS('14_Motor_Liq'!$AD$5:$AD$504,'14_Motor_Liq'!$AC$5:$AC$504,">="&D55,'14_Motor_Liq'!$AC$5:$AC$504,"<"&E55) -> 0 | H55: =SUMIFS('14_Motor_Liq'!$P$5:$P$504,'14_Motor_Liq'!$O$5:$O$504,">="&D55,'14_Motor_Liq'!$O$5:$O$504,"<"&E55)+SUMIFS('14_Motor_Liq'!$T$5:$T$504,'14_Motor_Liq'!$S$5:$S$504,">="&D55,'14_Motor_Liq'!$S$5:$S$504,"<"&E55)+SUMIFS('14_Motor_Liq'!$X$5:$X$504,'14_Motor_Liq'!$W$5:$W$504,">="&D55,'14_Motor_Liq'!$W$5:$W$504,"<"&E55)+SUMIFS('14_Motor_Liq'!$AB$5:$AB$504,'14_Motor_Liq'!$AA$5:$AA$504,">="&D55,'14_Motor_Liq'!$AA$5:$AA$504,"<"&E55)+SUMIFS('14_Motor_Liq'!$AF$5:$AF$504,'14_Motor_Liq'!$AE$5:$AE$504,">="&D55,'14_Motor_Liq'!$AE$5:$AE$504,"<"&E55) -> 0 | I55: =G55+H55 -> 0 | J55: =IF(MAX($I$44:$I$104)=0,"",REPT("|",ROUND(I55/MAX($I$44:$I$104)*45,0))) | K55: =IF(B55>0,SUMIFS($H$44:$H$104,$B$44:$B$104,">=0",$B$44:$B$104,"<="&B55),IF(B55<0,SUMIFS($G$44:$G$104,$B$44:$B$104,"<=0",$B$44:$B$104,">="&B55),G55+H55)) -> 0
... A104: =IF(B104=0,"<< PRECIO ACTUAL",IF(AND(G104>0,G104=MAX($G$44:$G$104)),"CLUSTER LONG MAYOR",IF(AND(H104>0,H104=MAX($H$44:$H$104)),"CLUSTER SHORT MAYOR",IF(AND(ISNUMBER($B$31),B104=$B$31),"primer cluster long",IF(AND(ISNUMBER($B$34),B104=$B$34),"primer cluster short",""))))) | B104: -30 | C104: =$B$5*(1+B104*$B$8) -> 65855.45 | D104: =$B$5*(1+(B104-0.5)*$B$8) -> 65661.758 | E104: =$B$5*(1+(B104+0.5)*$B$8) -> 66049.143 | F104: =B104*$B$8 -> -0.15 | G104: =SUMIFS('14_Motor_Liq'!$N$5:$N$504,'14_Motor_Liq'!$M$5:$M$504,">="&D104,'14_Motor_Liq'!$M$5:$M$504,"<"&E104)+SUMIFS('14_Motor_Liq'!$R$5:$R$504,'14_Motor_Liq'!$Q$5:$Q$504,">="&D104,'14_Motor_Liq'!$Q$5:$Q$504,"<"&E104)+SUMIFS('14_Motor_Liq'!$V$5:$V$504,'14_Motor_Liq'!$U$5:$U$504,">="&D104,'14_Motor_Liq'!$U$5:$U$504,"<"&E104)+SUMIFS('14_Motor_Liq'!$Z$5:$Z$504,'14_Motor_Liq'!$Y$5:$Y$504,">="&D104,'14_Motor_Liq'!$Y$5:$Y$504,"<"&E104)+SUMIFS('14_Motor_Liq'!$AD$5:$AD$504,'14_Motor_Liq'!$AC$5:$AC$504,">="&D104,'14_Motor_Liq'!$AC$5:$AC$504,"<"&E104) -> 0 | H104: =SUMIFS('14_Motor_Liq'!$P$5:$P$504,'14_Motor_Liq'!$O$5:$O$504,">="&D104,'14_Motor_Liq'!$O$5:$O$504,"<"&E104)+SUMIFS('14_Motor_Liq'!$T$5:$T$504,'14_Motor_Liq'!$S$5:$S$504,">="&D104,'14_Motor_Liq'!$S$5:$S$504,"<"&E104)+SUMIFS('14_Motor_Liq'!$X$5:$X$504,'14_Motor_Liq'!$W$5:$W$504,">="&D104,'14_Motor_Liq'!$W$5:$W$504,"<"&E104)+SUMIFS('14_Motor_Liq'!$AB$5:$AB$504,'14_Motor_Liq'!$AA$5:$AA$504,">="&D104,'14_Motor_Liq'!$AA$5:$AA$504,"<"&E104)+SUMIFS('14_Motor_Liq'!$AF$5:$AF$504,'14_Motor_Liq'!$AE$5:$AE$504,">="&D104,'14_Motor_Liq'!$AE$5:$AE$504,"<"&E104) -> 0 | I104: =G104+H104 -> 0 | J104: =IF(MAX($I$44:$I$104)=0,"",REPT("|",ROUND(I104/MAX($I$44:$I$104)*45,0))) | K104: =IF(B104>0,SUMIFS($H$44:$H$104,$B$44:$B$104,">=0",$B$44:$B$104,"<="&B104),IF(B104<0,SUMIFS($G$44:$G$104,$B$44:$B$104,"<=0",$B$44:$B$104,">="&B104),G104+H104)) -> 0

Sheet 15_Liq_Reales
A1: LIQUIDACIONES REALES — OKX (REST publico) + Binance (colector en tiempo real)
A2: Datos de ordenes de liquidacion ejecutadas, no estimaciones. Cobertura parcial del mercado: se extrapola con el factor de cobertura.
M3: OKX (qLiqOKX -> M4) | T3: BINANCE (qLiqBinanceCSV -> T4)
A4: A. PARAMETROS | M4: ts | N4: Hora | O4: Liquidado | P4: Precio | Q4: BTC | R4: USD | T4: ts | U4: Hora | V4: Liquidado | W4: Precio | X4: BTC | Y4: USD
A5: Factor de cobertura (Binance+OKX / mercado) | B5: 0.5 | E5: SUPUESTO. Ademas Binance solo emite 1 liquidacion/segundo/simbolo: subestima en cascadas.
A6: Ruta del CSV del colector | B6: C:\trading\liquidaciones_binance.csv | E6: Nombre definido RutaCSV. La lee la consulta qLiqBinanceCSV.
A7: Tu diferencia horaria con UTC (horas) | B7: -4 | E7: Bolivia = -4. Se usa para calcular 'ahora' en UTC.
A8: Ahora en UTC (ms) | B8: =ROUND((NOW()-DATE(1970,1,1)-B7/24)*86400000,0) -> 1790012128845 | E8: Ventanas de 1h/4h/24h medidas contra este instante.
A10: B. METRICAS DE LIQUIDACION REAL
A11: Metrica | B11: OKX | C11: Binance | D11: MERCADO (estimado) | E11: Lectura
A12: Longs liquidados 1h | B12: =SUMIFS($R$5:$R$5004,$O$5:$O$5004,"LONG",$M$5:$M$5004,">="&($B$8-1*3600000)) -> 0 | C12: =SUMIFS($Y$5:$Y$50004,$V$5:$V$50004,"LONG",$T$5:$T$50004,">="&($B$8-1*3600000)) -> 0 | D12: =(B12+C12)/$B$5 -> 0 | E12: FILTRO 1 (junto con shorts).
A13: Shorts liquidados 1h | B13: =SUMIFS($R$5:$R$5004,$O$5:$O$5004,"SHORT",$M$5:$M$5004,">="&($B$8-1*3600000)) -> 0 | C13: =SUMIFS($Y$5:$Y$50004,$V$5:$V$50004,"SHORT",$T$5:$T$50004,">="&($B$8-1*3600000)) -> 0 | D13: =(B13+C13)/$B$5 -> 0
A14: Longs liquidados 4h | B14: =SUMIFS($R$5:$R$5004,$O$5:$O$5004,"LONG",$M$5:$M$5004,">="&($B$8-4*3600000)) -> 0 | C14: =SUMIFS($Y$5:$Y$50004,$V$5:$V$50004,"LONG",$T$5:$T$50004,">="&($B$8-4*3600000)) -> 0 | D14: =(B14+C14)/$B$5 -> 0
A15: Shorts liquidados 4h | B15: =SUMIFS($R$5:$R$5004,$O$5:$O$5004,"SHORT",$M$5:$M$5004,">="&($B$8-4*3600000)) -> 0 | C15: =SUMIFS($Y$5:$Y$50004,$V$5:$V$50004,"SHORT",$T$5:$T$50004,">="&($B$8-4*3600000)) -> 0 | D15: =(B15+C15)/$B$5 -> 0
A16: Longs liquidados 24h | B16: =SUMIFS($R$5:$R$5004,$O$5:$O$5004,"LONG",$M$5:$M$5004,">="&($B$8-24*3600000)) -> 0 | C16: =SUMIFS($Y$5:$Y$50004,$V$5:$V$50004,"LONG",$T$5:$T$50004,">="&($B$8-24*3600000)) -> 0 | D16: =(B16+C16)/$B$5 -> 0 | E16: Comparable al dato de Coinglass.
A17: Shorts liquidados 24h | B17: =SUMIFS($R$5:$R$5004,$O$5:$O$5004,"SHORT",$M$5:$M$5004,">="&($B$8-24*3600000)) -> 0 | C17: =SUMIFS($Y$5:$Y$50004,$V$5:$V$50004,"SHORT",$T$5:$T$50004,">="&($B$8-24*3600000)) -> 0 | D17: =(B17+C17)/$B$5 -> 0
A18: Dominancia de longs 1h | B18: =IF(B12+B13=0,"n/d",B12/(B12+B13)) -> n/d | C18: =IF(C12+C13=0,"n/d",C12/(C12+C13)) -> n/d | D18: =IF(D12+D13=0,"n/d",D12/(D12+D13)) -> n/d | E18: FILTRO 3. >75% = purga unilateral.
A19: Eventos de liquidacion 1h | B19: =COUNTIFS($M$5:$M$5004,">="&($B$8-3600000)) -> 0 | C19: =COUNTIFS($T$5:$T$50004,">="&($B$8-3600000)) -> 0 | D19: =(B19+C19)/$B$5 -> 0 | E19: Muchos eventos pequenos = retail.
A20: Mayor liquidacion individual 24h | B20: =_xlfn.MAXIFS($R$5:$R$5004,$M$5:$M$5004,">="&($B$8-86400000)) -> 0 | C20: =_xlfn.MAXIFS($Y$5:$Y$50004,$T$5:$T$50004,">="&($B$8-86400000)) -> 0 | D20: =MAX(B20,C20) -> 0 | E20: Una sola > 5M = ballena liquidada.
A21: Precio medio de liquidacion LONG 1h | B21: =IF(B12=0,"n/d",SUMPRODUCT(($O$5:$O$5004="LONG")*($M$5:$M$5004>=$B$8-3600000)*$P$5:$P$5004*$R$5:$R$5004)/B12) -> n/d | C21: =IF(C12=0,"n/d",SUMPRODUCT(($V$5:$V$50004="LONG")*($T$5:$T$50004>=$B$8-3600000)*$W$5:$W$50004*$Y$5:$Y$50004)/C12) -> n/d | D21: =IFERROR((N(B21)*B12+N(C21)*C12)/(B12+C12),"n/d") -> n/d | E21: Donde se disparo la cascada: suele volverse soporte.
A22: Precio medio de liquidacion SHORT 1h | B22: =IF(B13=0,"n/d",SUMPRODUCT(($O$5:$O$5004="SHORT")*($M$5:$M$5004>=$B$8-3600000)*$P$5:$P$5004*$R$5:$R$5004)/B13) -> n/d | C22: =IF(C13=0,"n/d",SUMPRODUCT(($V$5:$V$50004="SHORT")*($T$5:$T$50004>=$B$8-3600000)*$W$5:$W$50004*$Y$5:$Y$50004)/C13) -> n/d | D22: =IFERROR((N(B22)*B13+N(C22)*C13)/(B13+C13),"n/d") -> n/d | E22: Donde se disparo el squeeze: suele volverse resistencia.
A24: C. DETECTOR DE CASCADA — ultimas 2 horas en bloques de 5 min (ambas fuentes)
A25: Bloque (minutos atras) | B25: Longs | C25: Shorts | D25: Total | E25: Senal
A26: -120 a -115 min | B26: =SUMIFS($R$5:$R$5004,$O$5:$O$5004,"LONG",$M$5:$M$5004,">="&($B$8-120*60000),$M$5:$M$5004,"<"&($B$8-115*60000))+SUMIFS($Y$5:$Y$50004,$V$5:$V$50004,"LONG",$T$5:$T$50004,">="&($B$8-120*60000),$T$5:$T$50004,"<"&($B$8-115*60000)) -> 0 | C26: =SUMIFS($R$5:$R$5004,$O$5:$O$5004,"SHORT",$M$5:$M$5004,">="&($B$8-120*60000),$M$5:$M$5004,"<"&($B$8-115*60000))+SUMIFS($Y$5:$Y$50004,$V$5:$V$50004,"SHORT",$T$5:$T$50004,">="&($B$8-120*60000),$T$5:$T$50004,"<"&($B$8-115*60000)) -> 0 | D26: =B26+C26 -> 0 | E26: =IF(AND(D26>0,D26>=3*MAX($B$51,1)),IF(B26>C26,"<< CASCADA LONG","<< SQUEEZE SHORT"),"")
A27: -115 a -110 min | B27: =SUMIFS($R$5:$R$5004,$O$5:$O$5004,"LONG",$M$5:$M$5004,">="&($B$8-115*60000),$M$5:$M$5004,"<"&($B$8-110*60000))+SUMIFS($Y$5:$Y$50004,$V$5:$V$50004,"LONG",$T$5:$T$50004,">="&($B$8-115*60000),$T$5:$T$50004,"<"&($B$8-110*60000)) -> 0 | C27: =SUMIFS($R$5:$R$5004,$O$5:$O$5004,"SHORT",$M$5:$M$5004,">="&($B$8-115*60000),$M$5:$M$5004,"<"&($B$8-110*60000))+SUMIFS($Y$5:$Y$50004,$V$5:$V$50004,"SHORT",$T$5:$T$50004,">="&($B$8-115*60000),$T$5:$T$50004,"<"&($B$8-110*60000)) -> 0 | D27: =B27+C27 -> 0 | E27: =IF(AND(D27>0,D27>=3*MAX($B$51,1)),IF(B27>C27,"<< CASCADA LONG","<< SQUEEZE SHORT"),"")
A28: -110 a -105 min | B28: =SUMIFS($R$5:$R$5004,$O$5:$O$5004,"LONG",$M$5:$M$5004,">="&($B$8-110*60000),$M$5:$M$5004,"<"&($B$8-105*60000))+SUMIFS($Y$5:$Y$50004,$V$5:$V$50004,"LONG",$T$5:$T$50004,">="&($B$8-110*60000),$T$5:$T$50004,"<"&($B$8-105*60000)) -> 0 | C28: =SUMIFS($R$5:$R$5004,$O$5:$O$5004,"SHORT",$M$5:$M$5004,">="&($B$8-110*60000),$M$5:$M$5004,"<"&($B$8-105*60000))+SUMIFS($Y$5:$Y$50004,$V$5:$V$50004,"SHORT",$T$5:$T$50004,">="&($B$8-110*60000),$T$5:$T$50004,"<"&($B$8-105*60000)) -> 0 | D28: =B28+C28 -> 0 | E28: =IF(AND(D28>0,D28>=3*MAX($B$51,1)),IF(B28>C28,"<< CASCADA LONG","<< SQUEEZE SHORT"),"")
A29: -105 a -100 min | B29: =SUMIFS($R$5:$R$5004,$O$5:$O$5004,"LONG",$M$5:$M$5004,">="&($B$8-105*60000),$M$5:$M$5004,"<"&($B$8-100*60000))+SUMIFS($Y$5:$Y$50004,$V$5:$V$50004,"LONG",$T$5:$T$50004,">="&($B$8-105*60000),$T$5:$T$50004,"<"&($B$8-100*60000)) -> 0 | C29: =SUMIFS($R$5:$R$5004,$O$5:$O$5004,"SHORT",$M$5:$M$5004,">="&($B$8-105*60000),$M$5:$M$5004,"<"&($B$8-100*60000))+SUMIFS($Y$5:$Y$50004,$V$5:$V$50004,"SHORT",$T$5:$T$50004,">="&($B$8-105*60000),$T$5:$T$50004,"<"&($B$8-100*60000)) -> 0 | D29: =B29+C29 -> 0 | E29: =IF(AND(D29>0,D29>=3*MAX($B$51,1)),IF(B29>C29,"<< CASCADA LONG","<< SQUEEZE SHORT"),"")
A30: -100 a -95 min | B30: =SUMIFS($R$5:$R$5004,$O$5:$O$5004,"LONG",$M$5:$M$5004,">="&($B$8-100*60000),$M$5:$M$5004,"<"&($B$8-95*60000))+SUMIFS($Y$5:$Y$50004,$V$5:$V$50004,"LONG",$T$5:$T$50004,">="&($B$8-100*60000),$T$5:$T$50004,"<"&($B$8-95*60000)) -> 0 | C30: =SUMIFS($R$5:$R$5004,$O$5:$O$5004,"SHORT",$M$5:$M$5004,">="&($B$8-100*60000),$M$5:$M$5004,"<"&($B$8-95*60000))+SUMIFS($Y$5:$Y$50004,$V$5:$V$50004,"SHORT",$T$5:$T$50004,">="&($B$8-100*60000),$T$5:$T$50004,"<"&($B$8-95*60000)) -> 0 | D30: =B30+C30 -> 0 | E30: =IF(AND(D30>0,D30>=3*MAX($B$51,1)),IF(B30>C30,"<< CASCADA LONG","<< SQUEEZE SHORT"),"")
A31: -95 a -90 min | B31: =SUMIFS($R$5:$R$5004,$O$5:$O$5004,"LONG",$M$5:$M$5004,">="&($B$8-95*60000),$M$5:$M$5004,"<"&($B$8-90*60000))+SUMIFS($Y$5:$Y$50004,$V$5:$V$50004,"LONG",$T$5:$T$50004,">="&($B$8-95*60000),$T$5:$T$50004,"<"&($B$8-90*60000)) -> 0 | C31: =SUMIFS($R$5:$R$5004,$O$5:$O$5004,"SHORT",$M$5:$M$5004,">="&($B$8-95*60000),$M$5:$M$5004,"<"&($B$8-90*60000))+SUMIFS($Y$5:$Y$50004,$V$5:$V$50004,"SHORT",$T$5:$T$50004,">="&($B$8-95*60000),$T$5:$T$50004,"<"&($B$8-90*60000)) -> 0 | D31: =B31+C31 -> 0 | E31: =IF(AND(D31>0,D31>=3*MAX($B$51,1)),IF(B31>C31,"<< CASCADA LONG","<< SQUEEZE SHORT"),"")
A32: -90 a -85 min | B32: =SUMIFS($R$5:$R$5004,$O$5:$O$5004,"LONG",$M$5:$M$5004,">="&($B$8-90*60000),$M$5:$M$5004,"<"&($B$8-85*60000))+SUMIFS($Y$5:$Y$50004,$V$5:$V$50004,"LONG",$T$5:$T$50004,">="&($B$8-90*60000),$T$5:$T$50004,"<"&($B$8-85*60000)) -> 0 | C32: =SUMIFS($R$5:$R$5004,$O$5:$O$5004,"SHORT",$M$5:$M$5004,">="&($B$8-90*60000),$M$5:$M$5004,"<"&($B$8-85*60000))+SUMIFS($Y$5:$Y$50004,$V$5:$V$50004,"SHORT",$T$5:$T$50004,">="&($B$8-90*60000),$T$5:$T$50004,"<"&($B$8-85*60000)) -> 0 | D32: =B32+C32 -> 0 | E32: =IF(AND(D32>0,D32>=3*MAX($B$51,1)),IF(B32>C32,"<< CASCADA LONG","<< SQUEEZE SHORT"),"")
A33: -85 a -80 min | B33: =SUMIFS($R$5:$R$5004,$O$5:$O$5004,"LONG",$M$5:$M$5004,">="&($B$8-85*60000),$M$5:$M$5004,"<"&($B$8-80*60000))+SUMIFS($Y$5:$Y$50004,$V$5:$V$50004,"LONG",$T$5:$T$50004,">="&($B$8-85*60000),$T$5:$T$50004,"<"&($B$8-80*60000)) -> 0 | C33: =SUMIFS($R$5:$R$5004,$O$5:$O$5004,"SHORT",$M$5:$M$5004,">="&($B$8-85*60000),$M$5:$M$5004,"<"&($B$8-80*60000))+SUMIFS($Y$5:$Y$50004,$V$5:$V$50004,"SHORT",$T$5:$T$50004,">="&($B$8-85*60000),$T$5:$T$50004,"<"&($B$8-80*60000)) -> 0 | D33: =B33+C33 -> 0 | E33: =IF(AND(D33>0,D33>=3*MAX($B$51,1)),IF(B33>C33,"<< CASCADA LONG","<< SQUEEZE SHORT"),"")
A34: -80 a -75 min | B34: =SUMIFS($R$5:$R$5004,$O$5:$O$5004,"LONG",$M$5:$M$5004,">="&($B$8-80*60000),$M$5:$M$5004,"<"&($B$8-75*60000))+SUMIFS($Y$5:$Y$50004,$V$5:$V$50004,"LONG",$T$5:$T$50004,">="&($B$8-80*60000),$T$5:$T$50004,"<"&($B$8-75*60000)) -> 0 | C34: =SUMIFS($R$5:$R$5004,$O$5:$O$5004,"SHORT",$M$5:$M$5004,">="&($B$8-80*60000),$M$5:$M$5004,"<"&($B$8-75*60000))+SUMIFS($Y$5:$Y$50004,$V$5:$V$50004,"SHORT",$T$5:$T$50004,">="&($B$8-80*60000),$T$5:$T$50004,"<"&($B$8-75*60000)) -> 0 | D34: =B34+C34 -> 0 | E34: =IF(AND(D34>0,D34>=3*MAX($B$51,1)),IF(B34>C34,"<< CASCADA LONG","<< SQUEEZE SHORT"),"")
A35: -75 a -70 min | B35: =SUMIFS($R$5:$R$5004,$O$5:$O$5004,"LONG",$M$5:$M$5004,">="&($B$8-75*60000),$M$5:$M$5004,"<"&($B$8-70*60000))+SUMIFS($Y$5:$Y$50004,$V$5:$V$50004,"LONG",$T$5:$T$50004,">="&($B$8-75*60000),$T$5:$T$50004,"<"&($B$8-70*60000)) -> 0 | C35: =SUMIFS($R$5:$R$5004,$O$5:$O$5004,"SHORT",$M$5:$M$5004,">="&($B$8-75*60000),$M$5:$M$5004,"<"&($B$8-70*60000))+SUMIFS($Y$5:$Y$50004,$V$5:$V$50004,"SHORT",$T$5:$T$50004,">="&($B$8-75*60000),$T$5:$T$50004,"<"&($B$8-70*60000)) -> 0 | D35: =B35+C35 -> 0 | E35: =IF(AND(D35>0,D35>=3*MAX($B$51,1)),IF(B35>C35,"<< CASCADA LONG","<< SQUEEZE SHORT"),"")
A36: -70 a -65 min | B36: =SUMIFS($R$5:$R$5004,$O$5:$O$5004,"LONG",$M$5:$M$5004,">="&($B$8-70*60000),$M$5:$M$5004,"<"&($B$8-65*60000))+SUMIFS($Y$5:$Y$50004,$V$5:$V$50004,"LONG",$T$5:$T$50004,">="&($B$8-70*60000),$T$5:$T$50004,"<"&($B$8-65*60000)) -> 0 | C36: =SUMIFS($R$5:$R$5004,$O$5:$O$5004,"SHORT",$M$5:$M$5004,">="&($B$8-70*60000),$M$5:$M$5004,"<"&($B$8-65*60000))+SUMIFS($Y$5:$Y$50004,$V$5:$V$50004,"SHORT",$T$5:$T$50004,">="&($B$8-70*60000),$T$5:$T$50004,"<"&($B$8-65*60000)) -> 0 | D36: =B36+C36 -> 0 | E36: =IF(AND(D36>0,D36>=3*MAX($B$51,1)),IF(B36>C36,"<< CASCADA LONG","<< SQUEEZE SHORT"),"")
A37: -65 a -60 min | B37: =SUMIFS($R$5:$R$5004,$O$5:$O$5004,"LONG",$M$5:$M$5004,">="&($B$8-65*60000),$M$5:$M$5004,"<"&($B$8-60*60000))+SUMIFS($Y$5:$Y$50004,$V$5:$V$50004,"LONG",$T$5:$T$50004,">="&($B$8-65*60000),$T$5:$T$50004,"<"&($B$8-60*60000)) -> 0 | C37: =SUMIFS($R$5:$R$5004,$O$5:$O$5004,"SHORT",$M$5:$M$5004,">="&($B$8-65*60000),$M$5:$M$5004,"<"&($B$8-60*60000))+SUMIFS($Y$5:$Y$50004,$V$5:$V$50004,"SHORT",$T$5:$T$50004,">="&($B$8-65*60000),$T$5:$T$50004,"<"&($B$8-60*60000)) -> 0 | D37: =B37+C37 -> 0 | E37: =IF(AND(D37>0,D37>=3*MAX($B$51,1)),IF(B37>C37,"<< CASCADA LONG","<< SQUEEZE SHORT"),"")
A38: -60 a -55 min | B38: =SUMIFS($R$5:$R$5004,$O$5:$O$5004,"LONG",$M$5:$M$5004,">="&($B$8-60*60000),$M$5:$M$5004,"<"&($B$8-55*60000))+SUMIFS($Y$5:$Y$50004,$V$5:$V$50004,"LONG",$T$5:$T$50004,">="&($B$8-60*60000),$T$5:$T$50004,"<"&($B$8-55*60000)) -> 0 | C38: =SUMIFS($R$5:$R$5004,$O$5:$O$5004,"SHORT",$M$5:$M$5004,">="&($B$8-60*60000),$M$5:$M$5004,"<"&($B$8-55*60000))+SUMIFS($Y$5:$Y$50004,$V$5:$V$50004,"SHORT",$T$5:$T$50004,">="&($B$8-60*60000),$T$5:$T$50004,"<"&($B$8-55*60000)) -> 0 | D38: =B38+C38 -> 0 | E38: =IF(AND(D38>0,D38>=3*MAX($B$51,1)),IF(B38>C38,"<< CASCADA LONG","<< SQUEEZE SHORT"),"")
A39: -55 a -50 min | B39: =SUMIFS($R$5:$R$5004,$O$5:$O$5004,"LONG",$M$5:$M$5004,">="&($B$8-55*60000),$M$5:$M$5004,"<"&($B$8-50*60000))+SUMIFS($Y$5:$Y$50004,$V$5:$V$50004,"LONG",$T$5:$T$50004,">="&($B$8-55*60000),$T$5:$T$50004,"<"&($B$8-50*60000)) -> 0 | C39: =SUMIFS($R$5:$R$5004,$O$5:$O$5004,"SHORT",$M$5:$M$5004,">="&($B$8-55*60000),$M$5:$M$5004,"<"&($B$8-50*60000))+SUMIFS($Y$5:$Y$50004,$V$5:$V$50004,"SHORT",$T$5:$T$50004,">="&($B$8-55*60000),$T$5:$T$50004,"<"&($B$8-50*60000)) -> 0 | D39: =B39+C39 -> 0 | E39: =IF(AND(D39>0,D39>=3*MAX($B$51,1)),IF(B39>C39,"<< CASCADA LONG","<< SQUEEZE SHORT"),"")
A40: -50 a -45 min | B40: =SUMIFS($R$5:$R$5004,$O$5:$O$5004,"LONG",$M$5:$M$5004,">="&($B$8-50*60000),$M$5:$M$5004,"<"&($B$8-45*60000))+SUMIFS($Y$5:$Y$50004,$V$5:$V$50004,"LONG",$T$5:$T$50004,">="&($B$8-50*60000),$T$5:$T$50004,"<"&($B$8-45*60000)) -> 0 | C40: =SUMIFS($R$5:$R$5004,$O$5:$O$5004,"SHORT",$M$5:$M$5004,">="&($B$8-50*60000),$M$5:$M$5004,"<"&($B$8-45*60000))+SUMIFS($Y$5:$Y$50004,$V$5:$V$50004,"SHORT",$T$5:$T$50004,">="&($B$8-50*60000),$T$5:$T$50004,"<"&($B$8-45*60000)) -> 0 | D40: =B40+C40 -> 0 | E40: =IF(AND(D40>0,D40>=3*MAX($B$51,1)),IF(B40>C40,"<< CASCADA LONG","<< SQUEEZE SHORT"),"")
A41: -45 a -40 min | B41: =SUMIFS($R$5:$R$5004,$O$5:$O$5004,"LONG",$M$5:$M$5004,">="&($B$8-45*60000),$M$5:$M$5004,"<"&($B$8-40*60000))+SUMIFS($Y$5:$Y$50004,$V$5:$V$50004,"LONG",$T$5:$T$50004,">="&($B$8-45*60000),$T$5:$T$50004,"<"&($B$8-40*60000)) -> 0 | C41: =SUMIFS($R$5:$R$5004,$O$5:$O$5004,"SHORT",$M$5:$M$5004,">="&($B$8-45*60000),$M$5:$M$5004,"<"&($B$8-40*60000))+SUMIFS($Y$5:$Y$50004,$V$5:$V$50004,"SHORT",$T$5:$T$50004,">="&($B$8-45*60000),$T$5:$T$50004,"<"&($B$8-40*60000)) -> 0 | D41: =B41+C41 -> 0 | E41: =IF(AND(D41>0,D41>=3*MAX($B$51,1)),IF(B41>C41,"<< CASCADA LONG","<< SQUEEZE SHORT"),"")
A42: -40 a -35 min | B42: =SUMIFS($R$5:$R$5004,$O$5:$O$5004,"LONG",$M$5:$M$5004,">="&($B$8-40*60000),$M$5:$M$5004,"<"&($B$8-35*60000))+SUMIFS($Y$5:$Y$50004,$V$5:$V$50004,"LONG",$T$5:$T$50004,">="&($B$8-40*60000),$T$5:$T$50004,"<"&($B$8-35*60000)) -> 0 | C42: =SUMIFS($R$5:$R$5004,$O$5:$O$5004,"SHORT",$M$5:$M$5004,">="&($B$8-40*60000),$M$5:$M$5004,"<"&($B$8-35*60000))+SUMIFS($Y$5:$Y$50004,$V$5:$V$50004,"SHORT",$T$5:$T$50004,">="&($B$8-40*60000),$T$5:$T$50004,"<"&($B$8-35*60000)) -> 0 | D42: =B42+C42 -> 0 | E42: =IF(AND(D42>0,D42>=3*MAX($B$51,1)),IF(B42>C42,"<< CASCADA LONG","<< SQUEEZE SHORT"),"")
A43: -35 a -30 min | B43: =SUMIFS($R$5:$R$5004,$O$5:$O$5004,"LONG",$M$5:$M$5004,">="&($B$8-35*60000),$M$5:$M$5004,"<"&($B$8-30*60000))+SUMIFS($Y$5:$Y$50004,$V$5:$V$50004,"LONG",$T$5:$T$50004,">="&($B$8-35*60000),$T$5:$T$50004,"<"&($B$8-30*60000)) -> 0 | C43: =SUMIFS($R$5:$R$5004,$O$5:$O$5004,"SHORT",$M$5:$M$5004,">="&($B$8-35*60000),$M$5:$M$5004,"<"&($B$8-30*60000))+SUMIFS($Y$5:$Y$50004,$V$5:$V$50004,"SHORT",$T$5:$T$50004,">="&($B$8-35*60000),$T$5:$T$50004,"<"&($B$8-30*60000)) -> 0 | D43: =B43+C43 -> 0 | E43: =IF(AND(D43>0,D43>=3*MAX($B$51,1)),IF(B43>C43,"<< CASCADA LONG","<< SQUEEZE SHORT"),"")
A44: -30 a -25 min | B44: =SUMIFS($R$5:$R$5004,$O$5:$O$5004,"LONG",$M$5:$M$5004,">="&($B$8-30*60000),$M$5:$M$5004,"<"&($B$8-25*60000))+SUMIFS($Y$5:$Y$50004,$V$5:$V$50004,"LONG",$T$5:$T$50004,">="&($B$8-30*60000),$T$5:$T$50004,"<"&($B$8-25*60000)) -> 0 | C44: =SUMIFS($R$5:$R$5004,$O$5:$O$5004,"SHORT",$M$5:$M$5004,">="&($B$8-30*60000),$M$5:$M$5004,"<"&($B$8-25*60000))+SUMIFS($Y$5:$Y$50004,$V$5:$V$50004,"SHORT",$T$5:$T$50004,">="&($B$8-30*60000),$T$5:$T$50004,"<"&($B$8-25*60000)) -> 0 | D44: =B44+C44 -> 0 | E44: =IF(AND(D44>0,D44>=3*MAX($B$51,1)),IF(B44>C44,"<< CASCADA LONG","<< SQUEEZE SHORT"),"")
A45: -25 a -20 min | B45: =SUMIFS($R$5:$R$5004,$O$5:$O$5004,"LONG",$M$5:$M$5004,">="&($B$8-25*60000),$M$5:$M$5004,"<"&($B$8-20*60000))+SUMIFS($Y$5:$Y$50004,$V$5:$V$50004,"LONG",$T$5:$T$50004,">="&($B$8-25*60000),$T$5:$T$50004,"<"&($B$8-20*60000)) -> 0 | C45: =SUMIFS($R$5:$R$5004,$O$5:$O$5004,"SHORT",$M$5:$M$5004,">="&($B$8-25*60000),$M$5:$M$5004,"<"&($B$8-20*60000))+SUMIFS($Y$5:$Y$50004,$V$5:$V$50004,"SHORT",$T$5:$T$50004,">="&($B$8-25*60000),$T$5:$T$50004,"<"&($B$8-20*60000)) -> 0 | D45: =B45+C45 -> 0 | E45: =IF(AND(D45>0,D45>=3*MAX($B$51,1)),IF(B45>C45,"<< CASCADA LONG","<< SQUEEZE SHORT"),"")
A46: -20 a -15 min | B46: =SUMIFS($R$5:$R$5004,$O$5:$O$5004,"LONG",$M$5:$M$5004,">="&($B$8-20*60000),$M$5:$M$5004,"<"&($B$8-15*60000))+SUMIFS($Y$5:$Y$50004,$V$5:$V$50004,"LONG",$T$5:$T$50004,">="&($B$8-20*60000),$T$5:$T$50004,"<"&($B$8-15*60000)) -> 0 | C46: =SUMIFS($R$5:$R$5004,$O$5:$O$5004,"SHORT",$M$5:$M$5004,">="&($B$8-20*60000),$M$5:$M$5004,"<"&($B$8-15*60000))+SUMIFS($Y$5:$Y$50004,$V$5:$V$50004,"SHORT",$T$5:$T$50004,">="&($B$8-20*60000),$T$5:$T$50004,"<"&($B$8-15*60000)) -> 0 | D46: =B46+C46 -> 0 | E46: =IF(AND(D46>0,D46>=3*MAX($B$51,1)),IF(B46>C46,"<< CASCADA LONG","<< SQUEEZE SHORT"),"")
A47: -15 a -10 min | B47: =SUMIFS($R$5:$R$5004,$O$5:$O$5004,"LONG",$M$5:$M$5004,">="&($B$8-15*60000),$M$5:$M$5004,"<"&($B$8-10*60000))+SUMIFS($Y$5:$Y$50004,$V$5:$V$50004,"LONG",$T$5:$T$50004,">="&($B$8-15*60000),$T$5:$T$50004,"<"&($B$8-10*60000)) -> 0 | C47: =SUMIFS($R$5:$R$5004,$O$5:$O$5004,"SHORT",$M$5:$M$5004,">="&($B$8-15*60000),$M$5:$M$5004,"<"&($B$8-10*60000))+SUMIFS($Y$5:$Y$50004,$V$5:$V$50004,"SHORT",$T$5:$T$50004,">="&($B$8-15*60000),$T$5:$T$50004,"<"&($B$8-10*60000)) -> 0 | D47: =B47+C47 -> 0 | E47: =IF(AND(D47>0,D47>=3*MAX($B$51,1)),IF(B47>C47,"<< CASCADA LONG","<< SQUEEZE SHORT"),"")
A48: -10 a -5 min | B48: =SUMIFS($R$5:$R$5004,$O$5:$O$5004,"LONG",$M$5:$M$5004,">="&($B$8-10*60000),$M$5:$M$5004,"<"&($B$8-5*60000))+SUMIFS($Y$5:$Y$50004,$V$5:$V$50004,"LONG",$T$5:$T$50004,">="&($B$8-10*60000),$T$5:$T$50004,"<"&($B$8-5*60000)) -> 0 | C48: =SUMIFS($R$5:$R$5004,$O$5:$O$5004,"SHORT",$M$5:$M$5004,">="&($B$8-10*60000),$M$5:$M$5004,"<"&($B$8-5*60000))+SUMIFS($Y$5:$Y$50004,$V$5:$V$50004,"SHORT",$T$5:$T$50004,">="&($B$8-10*60000),$T$5:$T$50004,"<"&($B$8-5*60000)) -> 0 | D48: =B48+C48 -> 0 | E48: =IF(AND(D48>0,D48>=3*MAX($B$51,1)),IF(B48>C48,"<< CASCADA LONG","<< SQUEEZE SHORT"),"")
A49: -5 a -0 min | B49: =SUMIFS($R$5:$R$5004,$O$5:$O$5004,"LONG",$M$5:$M$5004,">="&($B$8-5*60000),$M$5:$M$5004,"<"&($B$8-0*60000))+SUMIFS($Y$5:$Y$50004,$V$5:$V$50004,"LONG",$T$5:$T$50004,">="&($B$8-5*60000),$T$5:$T$50004,"<"&($B$8-0*60000)) -> 0 | C49: =SUMIFS($R$5:$R$5004,$O$5:$O$5004,"SHORT",$M$5:$M$5004,">="&($B$8-5*60000),$M$5:$M$5004,"<"&($B$8-0*60000))+SUMIFS($Y$5:$Y$50004,$V$5:$V$50004,"SHORT",$T$5:$T$50004,">="&($B$8-5*60000),$T$5:$T$50004,"<"&($B$8-0*60000)) -> 0 | D49: =B49+C49 -> 0 | E49: =IF(AND(D49>0,D49>=3*MAX($B$51,1)),IF(B49>C49,"<< CASCADA LONG","<< SQUEEZE SHORT"),"")
A51: Mediana por bloque | B51: =MEDIAN(D26:D49) -> 0
A52: Pico por bloque | B52: =MAX(D26:D49) -> 0
A53: Pico extrapolado al mercado | B53: =B52/$B$5 -> 0
A54: Multiplo pico / mediana | B54: =IF(B51=0,IF(B52>0,99,0),B52/B51) -> 0
A55: VEREDICTO DEL DETECTOR | B55: =IF(B52=0,"SIN LIQUIDACIONES REGISTRADAS",IF(AND(B54>=3,B53>=50000000),"CASCADA DETECTADA",IF(B54>=3,"MINI-CASCADA","FLUJO NORMAL"))) -> SIN LIQUIDACIONES REGISTRADAS

Sheet 16_Fase_Cascada
A1: DETECTOR DE FASE DE CASCADA — maquina de estados sobre precio, OI y flujo agresor
A2: Responde a la unica pregunta que importa para comprar la caida: en que punto del ciclo de liquidacion estamos.
A4: Barras disponibles (N) | B4: =COUNT('12_Datos_5m'!$F$5:$F$504) -> 0
A6: Metrica | B6: 15 min | C6: 1 hora | D6: 4 horas | E6: 24 horas | F6: Como leerlo
A7: Barras de la ventana | B7: 3 | C7: 12 | D7: 48 | E7: 288
A8: Retorno del precio | B8: =IF($B$4<2,"n/d",IFERROR(INDEX('12_Datos_5m'!$F$5:$F$504,$B$4)/INDEX('12_Datos_5m'!$F$5:$F$504,MAX(1,$B$4-B7))-1,"n/d")) -> n/d | C8: =IF($B$4<2,"n/d",IFERROR(INDEX('12_Datos_5m'!$F$5:$F$504,$B$4)/INDEX('12_Datos_5m'!$F$5:$F$504,MAX(1,$B$4-C7))-1,"n/d")) -> n/d | D8: =IF($B$4<2,"n/d",IFERROR(INDEX('12_Datos_5m'!$F$5:$F$504,$B$4)/INDEX('12_Datos_5m'!$F$5:$F$504,MAX(1,$B$4-D7))-1,"n/d")) -> n/d | E8: =IF($B$4<2,"n/d",IFERROR(INDEX('12_Datos_5m'!$F$5:$F$504,$B$4)/INDEX('12_Datos_5m'!$F$5:$F$504,MAX(1,$B$4-E7))-1,"n/d")) -> n/d | F8: Magnitud del movimiento.
A9: Cambio del Open Interest | B9: =IF($B$4<2,"n/d",IFERROR(INDEX('12_Datos_5m'!$I$5:$I$504,$B$4)/INDEX('12_Datos_5m'!$I$5:$I$504,MAX(1,$B$4-B7))-1,"n/d")) -> n/d | C9: =IF($B$4<2,"n/d",IFERROR(INDEX('12_Datos_5m'!$I$5:$I$504,$B$4)/INDEX('12_Datos_5m'!$I$5:$I$504,MAX(1,$B$4-C7))-1,"n/d")) -> n/d | D9: =IF($B$4<2,"n/d",IFERROR(INDEX('12_Datos_5m'!$I$5:$I$504,$B$4)/INDEX('12_Datos_5m'!$I$5:$I$504,MAX(1,$B$4-D7))-1,"n/d")) -> n/d | E9: =IF($B$4<2,"n/d",IFERROR(INDEX('12_Datos_5m'!$I$5:$I$504,$B$4)/INDEX('12_Datos_5m'!$I$5:$I$504,MAX(1,$B$4-E7))-1,"n/d")) -> n/d | F9: Negativo con precio cayendo = longs liquidados.
A10: Share comprador agresor | B10: =IF($B$4<2,"n/d",IFERROR(SUMPRODUCT((ROW('12_Datos_5m'!$H$5:$H$504)-4>$B$4-B7)*(ROW('12_Datos_5m'!$H$5:$H$504)-4<=$B$4)*'12_Datos_5m'!$H$5:$H$504)/SUMPRODUCT((ROW('12_Datos_5m'!$G$5:$G$504)-4>$B$4-B7)*(ROW('12_Datos_5m'!$G$5:$G$504)-4<=$B$4)*'12_Datos_5m'!$G$5:$G$504),"n/d")) -> n/d | C10: =IF($B$4<2,"n/d",IFERROR(SUMPRODUCT((ROW('12_Datos_5m'!$H$5:$H$504)-4>$B$4-C7)*(ROW('12_Datos_5m'!$H$5:$H$504)-4<=$B$4)*'12_Datos_5m'!$H$5:$H$504)/SUMPRODUCT((ROW('12_Datos_5m'!$G$5:$G$504)-4>$B$4-C7)*(ROW('12_Datos_5m'!$G$5:$G$504)-4<=$B$4)*'12_Datos_5m'!$G$5:$G$504),"n/d")) -> n/d | D10: =IF($B$4<2,"n/d",IFERROR(SUMPRODUCT((ROW('12_Datos_5m'!$H$5:$H$504)-4>$B$4-D7)*(ROW('12_Datos_5m'!$H$5:$H$504)-4<=$B$4)*'12_Datos_5m'!$H$5:$H$504)/SUMPRODUCT((ROW('12_Datos_5m'!$G$5:$G$504)-4>$B$4-D7)*(ROW('12_Datos_5m'!$G$5:$G$504)-4<=$B$4)*'12_Datos_5m'!$G$5:$G$504),"n/d")) -> n/d | E10: =IF($B$4<2,"n/d",IFERROR(SUMPRODUCT((ROW('12_Datos_5m'!$H$5:$H$504)-4>$B$4-E7)*(ROW('12_Datos_5m'!$H$5:$H$504)-4<=$B$4)*'12_Datos_5m'!$H$5:$H$504)/SUMPRODUCT((ROW('12_Datos_5m'!$G$5:$G$504)-4>$B$4-E7)*(ROW('12_Datos_5m'!$G$5:$G$504)-4<=$B$4)*'12_Datos_5m'!$G$5:$G$504),"n/d")) -> n/d | F10: >52% tras una cascada = alguien absorbe.
A11: Multiplo de volumen | B11: =IF($B$4<2,"n/d",IFERROR((SUMPRODUCT((ROW('12_Datos_5m'!$G$5:$G$504)-4>$B$4-B7)*(ROW('12_Datos_5m'!$G$5:$G$504)-4<=$B$4)*'12_Datos_5m'!$G$5:$G$504)/MIN(B7,$B$4))/(SUM('12_Datos_5m'!$G$5:$G$504)/$B$4),"n/d")) -> n/d | C11: =IF($B$4<2,"n/d",IFERROR((SUMPRODUCT((ROW('12_Datos_5m'!$G$5:$G$504)-4>$B$4-C7)*(ROW('12_Datos_5m'!$G$5:$G$504)-4<=$B$4)*'12_Datos_5m'!$G$5:$G$504)/MIN(C7,$B$4))/(SUM('12_Datos_5m'!$G$5:$G$504)/$B$4),"n/d")) -> n/d | D11: =IF($B$4<2,"n/d",IFERROR((SUMPRODUCT((ROW('12_Datos_5m'!$G$5:$G$504)-4>$B$4-D7)*(ROW('12_Datos_5m'!$G$5:$G$504)-4<=$B$4)*'12_Datos_5m'!$G$5:$G$504)/MIN(D7,$B$4))/(SUM('12_Datos_5m'!$G$5:$G$504)/$B$4),"n/d")) -> n/d | E11: =IF($B$4<2,"n/d",IFERROR((SUMPRODUCT((ROW('12_Datos_5m'!$G$5:$G$504)-4>$B$4-E7)*(ROW('12_Datos_5m'!$G$5:$G$504)-4<=$B$4)*'12_Datos_5m'!$G$5:$G$504)/MIN(E7,$B$4))/(SUM('12_Datos_5m'!$G$5:$G$504)/$B$4),"n/d")) -> n/d | F11: >2x = evento, no ruido.
A12: Cuadrante precio / OI | B12: =IF(OR(NOT(ISNUMBER(B8)),NOT(ISNUMBER(B9))),"n/d",IF(B8>=0,IF(B9>=0,"P+ OI+ largos nuevos","P+ OI- cierre de cortos"),IF(B9>=0,"P- OI+ cortos nuevos","P- OI- liquidacion de largos"))) -> n/d | C12: =IF(OR(NOT(ISNUMBER(C8)),NOT(ISNUMBER(C9))),"n/d",IF(C8>=0,IF(C9>=0,"P+ OI+ largos nuevos","P+ OI- cierre de cortos"),IF(C9>=0,"P- OI+ cortos nuevos","P- OI- liquidacion de largos"))) -> n/d | D12: =IF(OR(NOT(ISNUMBER(D8)),NOT(ISNUMBER(D9))),"n/d",IF(D8>=0,IF(D9>=0,"P+ OI+ largos nuevos","P+ OI- cierre de cortos"),IF(D9>=0,"P- OI+ cortos nuevos","P- OI- liquidacion de largos"))) -> n/d | E12: =IF(OR(NOT(ISNUMBER(E8)),NOT(ISNUMBER(E9))),"n/d",IF(E8>=0,IF(E9>=0,"P+ OI+ largos nuevos","P+ OI- cierre de cortos"),IF(E9>=0,"P- OI+ cortos nuevos","P- OI- liquidacion de largos"))) -> n/d | F12: P- OI- es el unico cuadrante que precede rebotes de arbitraje.
A13: Mecha inferior de la ultima barra | B13: =IF($B$4<1,"n/d",IFERROR((MIN(INDEX('12_Datos_5m'!$C$5:$C$504,$B$4),INDEX('12_Datos_5m'!$F$5:$F$504,$B$4))-INDEX('12_Datos_5m'!$E$5:$E$504,$B$4))/(INDEX('12_Datos_5m'!$D$5:$D$504,$B$4)-INDEX('12_Datos_5m'!$E$5:$E$504,$B$4)),0)) -> n/d | F13: >50% = rechazo de precios bajos. Firma de absorcion.
A14: Purga de OI desde el maximo de 24h | B14: =IF($B$4<2,"n/d",IFERROR(1-INDEX('12_Datos_5m'!$I$5:$I$504,$B$4)/_xlfn.MAXIFS('12_Datos_5m'!$I$5:$I$504,'12_Datos_5m'!$A$5:$A$504,">="&(INDEX('12_Datos_5m'!$A$5:$A$504,$B$4)-86400000)),"n/d")) -> n/d | F14: FILTRO 2 en vivo. El 28-ago fue 0.86%: purga incompleta. >=2.5% = limpieza real.
A16: UMBRALES (editables)
A17: Cascada: retorno 1h maximo | B17: -0.02
A18: Cascada: cambio de OI 1h maximo | B18: -0.015
A19: Cascada: multiplo de volumen minimo | B19: 2
A20: Agotamiento: retorno 4h maximo | B20: -0.03
A21: Agotamiento: cambio de OI 4h maximo | B21: -0.02
A22: Agotamiento: share comprador 15m minimo | B22: 0.52
A23: Ignicion: retorno 15m maximo | B23: -0.008
A24: Carga: aumento de OI 4h minimo | B24: 0.02
A25: Carga: movimiento de precio 4h maximo (abs) | B25: 0.01
A27: FASE ACTUAL
A28: FASE | B28: =IFERROR(IF($B$4<60,"SIN DATOS SUFICIENTES",IF(AND(C8<=B17,C9<=B18,C11>=B19),"CASCADA LONG EN CURSO",IF(AND(C8>=-B17,C9<=B18,C11>=B19),"SQUEEZE DE CORTOS EN CURSO",IF(AND(D8<=B20,D9<=B21,B8>=0,B10>=B22),"AGOTAMIENTO POST-CASCADA",IF(AND(B8<=B23,B9<0),"IGNICION",IF(AND(D9>=B24,ABS(D8)<=B25),"CARGANDO COMBUSTIBLE","NEUTRO")))))),"NEUTRO") -> SIN DATOS SUFICIENTES
A29: QUE HACER | B29: =IFERROR(INDEX($C$33:$C$39,MATCH(B28,$A$33:$A$39,0)),"") -> Instala y refresca qBase5m (hoja 9).
A32: Fase | B32: Firma | C32: Accion
A33: CARGANDO COMBUSTIBLE | B33: OI sube >2% en 4h con precio plano. | C33: Se esta armando el cluster que alguien cazara. Mira el mapa (hoja 13): ahi estara el objetivo.
A34: IGNICION | B34: Caida >0.8% en 15m con OI bajando. | C34: Reduce largos apalancados. No compres todavia: puede ser el inicio de la cascada.
A35: CASCADA LONG EN CURSO | B35: Caida >2% en 1h, OI -1.5%, volumen >2x. | C35: No atrapes el cuchillo. Coloca ordenes limite en el primer cluster long del mapa y espera.
A36: AGOTAMIENTO POST-CASCADA | B36: Caida 4h >3%, OI 4h -2%, 15m verde, compradores >52%. | C36: VENTANA DE ARBITRAJE. Revisa los 5 filtros del dashboard: con 4 o mas, entrada con 3x maximo.
A37: SQUEEZE DE CORTOS EN CURSO | B37: Subida >2% en 1h con OI cayendo. | C37: No te pongas corto contra el squeeze. El rally es de cobertura: fragil, pero no lo desafies en caliente.
A38: NEUTRO | B38: Ninguna firma activa. | C38: Sin evento de liquidacion. Escenario de rango: no hay trade de arbitraje.
A39: SIN DATOS SUFICIENTES | B39: Menos de 60 barras. | C39: Instala y refresca qBase5m (hoja 9).

Sheet 6_Wyckoff_Niveles
A1: MOTOR WYCKOFF — SPRING vs UPTHRUST/UTAD
A2: Cada evidencia se puntua 0-3. El motor convierte la suma ponderada en probabilidad. Edita solo el amarillo.
A4: A. EVIDENCIA UTAD (distribucion — barre maximos y baja)
A5: Evidencia | B5: Peso | C5: Puntaje 0-3 | D5: Aporte | E5: Verificable en vivo | F5: Celda fuente | G5: Estado 28-ago | H5: Comentario
A6: Maximo en 81,238 sin capacidad de sostenerlo | B6: 3 | C6: 3 | D6: =B6*C6 -> 9 | E6: No | F6: — | G6: Confirmado | H6: Rechazo en la MA 50 semanas (81,033).
A7: Grandes operadores vendiendo en 80–82K | B7: 3 | C7: 3 | D7: =B7*C7 -> 9 | E7: No | F7: — | G7: Confirmado | H7: Supply on demand clasico.
A8: Polaridad de liquidacion invertida a longs | B8: 3 | C8: 3 | D8: =B8*C8 -> 9 | E8: Si | F8: '5_Liquidaciones'!C16 | G8: 74% longs | H8: El dato mas pesado del bloque.
A9: Divergencia retail vs top traders | B9: 2 | C9: 3 | D9: =B9*C9 -> 6 | E9: Si | F9: '3_Live_Derivados'!G9-'3_Live_Derivados'!G10 | G9: 70.3% vs 57.4% | H9: 13 puntos de brecha.
A10: Sobrecompra (RSI/Stoch extremos) | B10: 2 | C10: 2 | D10: =B10*C10 -> 4 | E10: No | F10: — | G10: RSI 76, Stoch>90 | H10: ETH; BTC similar.
A11: Bid de dealers desaparecido (expiracion) | B11: 3 | C11: 3 | D11: =B11*C11 -> 9 | E11: No | F11: — | G11: Confirmado 08:00 UTC | H11: 6.32B expiraron, max pain 69K.
A12: OI en minimo de 5 meses durante el rally | B12: 3 | C12: 3 | D12: =B12*C12 -> 9 | E12: No | F12: — | G12: Confirmado | H12: Rally de cobertura, no de demanda.
A13: PUNTUACION UTAD | D13: =SUM(D6:D12) -> 55 | E13: =SUM(B6:B12)*3 -> 57 | F13: =D13/E13 -> 0.96491228 | G13: % del maximo
A15: B. EVIDENCIA SPRING (acumulacion — barre minimos y sube)
A16: Evidencia | B16: Peso | C16: Puntaje 0-3 | D16: Aporte | E16: Verificable en vivo | F16: Celda fuente | G16: Estado 28-ago | H16: Comentario
A17: Funding neutro o negativo | B17: 3 | C17: 3 | D17: =B17*C17 -> 9 | E17: Si | F17: '1_Dashboard'!E8 | G17: -0.0048% | H17: El argumento alcista mas fuerte.
A18: Funding muy por debajo del 0.03%/4h | B18: 2 | C18: 3 | D18: =B18*C18 -> 6 | E18: Si | F18: '3_Live_Derivados'!G5 | G18: Confirmado | H18: Sin apalancamiento largo excesivo.
A19: Bolsa 74–76.5K visible = iman | B19: 3 | C19: 3 | D19: =B19*C19 -> 9 | E19: No | F19: — | G19: Confirmado | H19: Lo visible se barre, no se respeta.
A20: OI subio solo 1.32% en el avance | B20: 3 | C20: 2 | D20: =B20*C20 -> 6 | E20: Si | F20: '3_Live_Derivados'!G7 | G20: Confirmado | H20: Avance no puramente apalancado.
A21: Flujos ETF positivos sostenidos | B21: 3 | C21: 3 | D21: =B21*C21 -> 9 | E21: Si | F21: '5_Liquidaciones'!C12 | G21: 8 sesiones | H21: Bid spot que no mira el grafico de 5m.
A22: Warsh no se comprometio a subir tasas | B22: 2 | C22: 2 | D22: =B22*C22 -> 4 | E22: No | F22: — | G22: Confirmado | H22: El-Erian: 60% es demasiado alto.
A23: Precio defendiendo la EMA 50 semanas | B23: 2 | C23: 2 | D23: =B23*C23 -> 4 | E23: Si | F23: '1_Dashboard'!E6 | G23: 77,477 vs 77,250 | H23: Margen de solo 227 USD.
A24: PUNTUACION SPRING | D24: =SUM(D17:D23) -> 47 | E24: =SUM(B17:B23)*3 -> 54 | F24: =D24/E24 -> 0.87037037 | G24: % del maximo
A26: C. RESULTADO DEL MOTOR
A27: Salida | B27: Valor | C27: Referencia analisis | D27: Confirmacion requerida | E27: Invalidacion
A28: Prob. UTAD confirmado | B28: =IFERROR(F13/(F13+F24),0) -> 0.52575677 | C28: 52% | D28: Cierre 4H bajo 76,900 + fallo en recuperar 79,000 | E28: Cierre diario > 80,500
A29: Prob. de que se dispare el Spring | B29: =IFERROR(F24/(F13+F24),0) -> 0.47424323 | C29: 44% | D29: Mecha bajo 74,500 rechazada en <4h con liq >800M | E29: Cierre 4H bajo 73,800
A30: Prob. de exito condicional del Spring | B30: 0.58 | C30: 58% | D30: Funding girando negativo en la mecha | E30: Funding positivo en el rebote
A31: Prob. combinada de Spring exitoso | B31: =B29*B30 -> 0.27506107 | C31: 26% | D31: Ambas anteriores | E31: Cualquiera de las dos falla
A32: Prob. sin resolucion (rango) | B32: =MAX(0,1-B28-B31) -> 0.19918216 | C32: 22% | D32: Cierre semanal entre 77,250 y 79,000 | E32: Ruptura de extremo con volumen
A33: ESTRUCTURA DOMINANTE | B33: =IF(B28>B31,"UTAD / DISTRIBUCION","SPRING / REACUMULACION") -> UTAD / DISTRIBUCION

Sheet 7_Arbitraje_Sizing
A1: ARBITRAJE POST-LIQUIDACION — CALCULADORA DE POSICION Y RUINA
A2: Comprar la caida solo cuando la venta es FORZADA. Si es informada (macro real), no hay rebote: hay tendencia.
A4: A. PARAMETROS DE LA OPERACION (amarillo = editar)
A5: Parametro | B5: Valor | H5: Nota
A6: Capital de la cuenta (USD) | B6: 10000 | H6: Tu capital total.
A7: Riesgo maximo por intento (%) | B7: 0.02 | H7: Regla estandar: 2%.
A8: Apalancamiento | B8: 3 | H8: El analisis recomienda 3x, NO 5x. Ver bloque D.
A9: Precio de entrada | B9: 75000 | H9: Zona de captura primaria BTC: 74,000–75,500.
A10: Stop (precio) | B10: 73800 | H10: Quiebre estructural. Debajo ya no es barrida.
A11: Objetivo 1 | B11: 77250 | H11: EMA 50 semanas.
A12: Objetivo 2 | B12: 79000 | H12: Gatillo de squeeze.
A13: Intentos maximos permitidos | B13: 3 | H13: Tras 3 fallos, se cierra el dia.
A15: B. RESULTADOS CALCULADOS
A16: Metrica | B16: Valor | C16: Formato | H16: Interpretacion
A17: Distancia al stop (%) | B17: =($B$9-$B$10)/$B$9 -> 0.016 | C17: 0.00% | H17: Movimiento adverso que te saca.
A18: Perdida con apalancamiento (% capital) | B18: =(($B$9-$B$10)/$B$9)*$B$8 -> 0.048 | C18: 0.00% | H18: AQUI esta el peligro real.
A19: Ganancia al objetivo 1 (% capital) | B19: =(($B$11-$B$9)/$B$9)*$B$8 -> 0.09 | C19: 0.00% | H19: Pago del escenario base.
A20: Ganancia al objetivo 2 (% capital) | B20: =(($B$12-$B$9)/$B$9)*$B$8 -> 0.16 | C20: 0.00% | H20: Pago extendido.
A21: Ratio riesgo/beneficio (obj.1) | B21: =IFERROR(($B$11-$B$9)/($B$9-$B$10),0) -> 1.875 | C21: 0.00x | H21: Minimo aceptable: 1.5x.
A22: Tamano nocional maximo (USD) | B22: =IFERROR($B$6*$B$7/(($B$9-$B$10)/$B$9),0) -> 12500 | C22: #,##0 | H22: Nocional que respeta el 2% de riesgo.
A23: Margen requerido (USD) | B23: =IFERROR(B22/$B$8,0) -> 4166.6667 | C23: #,##0 | H23: Colateral a inmovilizar.
A24: Perdida en USD si salta el stop | B24: =IFERROR($B$6*$B$7,0) -> 200 | C24: #,##0 | H24: Por diseno = el 2%.
A25: Win rate minimo para no perder | B25: =IFERROR((($B$9-$B$10)/$B$9)/((($B$9-$B$10)/$B$9)+(($B$11-$B$9)/$B$9)),0) -> 0.34782609 | C25: 0.0% | H25: Si tu acierto historico esta por debajo, la estrategia pierde dinero por diseno.
A26: Perdida tras 3 fallos consecutivos | B26: =1-(1-$B$7)^$B$13 -> 0.058808 | C26: 0.0% | H26: Peor caso del dia.
A27: Perdida con 5x en el mismo trade | B27: =(($B$9-$B$10)/$B$9)*5 -> 0.08 | C27: 0.00% | H27: Compara contra la fila 18. Por eso 3x.
A29: C. LOS 5 FILTROS — SEMAFORO ESPEJO DEL DASHBOARD
A30: Filtro | B30: Umbral | C30: Valor | D30: Cumple | E30: Peso | F30: Puntos | G30: Origen del dato | H30: Que hacer si falla
A31: 1. Liquidaciones 1h | B31: >= 800 M | C31: ='1_Dashboard'!C24 -> 0 | D31: =IF(NOT(ISNUMBER(C31)),0,IF(C31>=800000000,1,0)) -> 0 | E31: 1 | F31: =D31*E31 -> 0 | G31: Espejo del dashboard | H31: Esperar. Sin volumen no hay rebote.
A32: 2. % OI purgado | B32: >= 2.5% | C32: ='1_Dashboard'!C25 -> 0.0086345609 | D32: =IF(NOT(ISNUMBER(C32)),0,IF(C32>=0.025,1,0)) -> 0 | E32: 1.5 | F32: =D32*E32 -> 0 | G32: Espejo del dashboard | H32: Purga incompleta: viene otra cascada.
A33: 3. Dominancia longs | B33: >= 75% | C33: ='1_Dashboard'!C26 -> 0.73818898 | D33: =IF(NOT(ISNUMBER(C33)),0,IF(C33>=0.75,1,0)) -> 0 | E33: 1 | F33: =D33*E33 -> 0 | G33: Espejo del dashboard | H33: Purga mixta: sin direccion clara.
A34: 4. Funding pre-caida | B34: <= 0.010% | C34: ='1_Dashboard'!C27 -> 4.8e-05 | D34: =IF(NOT(ISNUMBER(C34)),0,IF(C34<=0.0001,1,0)) -> 1 | E34: 1 | F34: =D34*E34 -> 1 | G34: Espejo del dashboard | H34: Hay una segunda capa de longs por purgar.
A35: 5. Bid spot (ETF) | B35: positivo | C35: ='1_Dashboard'!C28 -> 1 | D35: =IF(NOT(ISNUMBER(C35)),0,IF(C35>=0.5,1,0)) -> 1 | E35: 0.5 | F35: =D35*E35 -> 0.5 | G35: Espejo del dashboard | H35: Sin bid estructural, no compres.
A36: DECISION | B36: =SUM(F31:F35) -> 1.5 | C36: =IF(B36>=4,"EJECUTAR",IF(B36>=3,"ORDEN LIMITE PREPARADA","NO OPERAR")) -> NO OPERAR | G36: de 5.0 | H36: Se requieren 4 de 5. La puntuacion del 28-ago fue 2.5.
A38: D. MATEMATICA DE RUINA — POR QUE 3x Y NO 5x
A39: Serie de resultados | B39: Con 2x | C39: Con 3x | D39: Con 5x | E39: Con 10x | G39: Veredicto | H39: Nota
A40: 3 aciertos de +1.3% (nominal) | B40: =(1+0.013*2)^3*(1-0.029*2)^0-1 -> 0.080045576 | C40: =(1+0.013*3)^3*(1-0.029*3)^0-1 -> 0.12162232 | D40: =(1+0.013*5)^3*(1-0.029*5)^0-1 -> 0.20794962 | E40: =(1+0.013*10)^3*(1-0.029*10)^0-1 -> 0.442897 | G40: =IF(D40<0,"5x DESTRUYE","5x sobrevive") -> 5x sobrevive | H40: Ganar 1% muchas veces y perder 15% una vez converge a cero.
A41: 3 fallos de -2.9% (nominal) | B41: =(1+0.013*2)^0*(1-0.029*2)^3-1 -> -0.16410311 | C41: =(1+0.013*3)^0*(1-0.029*3)^3-1 -> -0.2389515 | D41: =(1+0.013*5)^0*(1-0.029*5)^3-1 -> -0.37497362 | E41: =(1+0.013*10)^0*(1-0.029*10)^3-1 -> -0.642089 | G41: =IF(D41<0,"5x DESTRUYE","5x sobrevive") -> 5x DESTRUYE | H41: Ganar 1% muchas veces y perder 15% una vez converge a cero.
A42: 2 aciertos + 1 fallo | B42: =(1+0.013*2)^2*(1-0.029*2)^1-1 -> -0.008379208 | C42: =(1+0.013*3)^2*(1-0.029*3)^1-1 -> -0.014397327 | D42: =(1+0.013*5)^2*(1-0.029*5)^1-1 -> -0.030237625 | E42: =(1+0.013*10)^2*(1-0.029*10)^1-1 -> -0.093401 | G42: =IF(D42<0,"5x DESTRUYE","5x sobrevive") -> 5x DESTRUYE | H42: Ganar 1% muchas veces y perder 15% una vez converge a cero.
A43: 1 acierto + 2 fallos | B43: =(1+0.013*2)^1*(1-0.029*2)^2-1 -> -0.089564536 | C43: =(1+0.013*3)^1*(1-0.029*3)^2-1 -> -0.13392181 | D43: =(1+0.013*5)^1*(1-0.029*5)^2-1 -> -0.22145838 | E43: =(1+0.013*10)^1*(1-0.029*10)^2-1 -> -0.430367 | G43: =IF(D43<0,"5x DESTRUYE","5x sobrevive") -> 5x DESTRUYE | H43: Ganar 1% muchas veces y perder 15% una vez converge a cero.
A45: E. NIVELES OPERATIVOS PRECARGADOS
A46: Activo | B46: Captura primaria | C46: Captura secundaria | D46: Stop duro | E46: Objetivo 1 | F46: Objetivo 2 | G46: Apalanc. max | H46: Advertencia
A47: BTC | B47: 74,000 – 75,500 | C47: 76,300 – 76,900 | D47: cierre 5m < 73,800 | E47: 77,250 (EMA 50W) | F47: 79,000 | G47: 3x | H47: Tamano <=2% por intento, maximo 3 intentos.
A48: ETH | B48: 2,426 – 2,463 | C48: 2,471 – 2,503 | D48: cierre < 2,400 | E48: 2,503 (pivote) | F48: 2,528 | G48: 3x | H48: Bajo 2,400 no hay red hasta 2,250–2,350. Riesgo de hueco.

Sheet 8_API_Catalogo
A1: CATALOGO DE APIs PUBLICAS
A2: Todo lo marcado 'No' en la columna Clave funciona sin registro. Lo marcado 'Si' requiere cuenta gratuita o de pago.
A4: Proveedor | B4: Que aporta | C4: Endpoint base / ejemplo | D4: Clave | E4: Limite de uso | F4: Formato | G4: Uso en este modelo
A5: Binance Spot | B5: Precio, volumen, OHLC | C5: https://api.binance.com/api/v3/ticker/24hr?symbol=BTCUSDT | D5: No | E5: 1200 req/min | F5: JSON | G5: Precio principal, rango 24h
A6: Binance Futures | B6: Funding, OI, long/short, taker | C6: https://fapi.binance.com/fapi/v1/premiumIndex?symbol=BTCUSDT | D6: No | E6: 2400 req/min | F6: JSON | G6: FILTRO 4 y todo el bloque de posicionamiento
A7: Binance Futures Data | B7: Ratios historicos | C7: https://fapi.binance.com/futures/data/globalLongShortAccountRatio?symbol=BTCUSDT&period=1h&limit=30 | D7: No | E7: Alto | F7: JSON | G7: Divergencia retail vs pro
A8: Coinbase | B8: Precio spot institucional EEUU | C8: https://api.coinbase.com/v2/prices/BTC-USD/spot | D8: No | E8: 10 req/s | F8: JSON | G8: Prima EEUU vs offshore
A9: Kraken | B9: Precio, OHLC, libro | C9: https://api.kraken.com/0/public/Ticker?pair=XBTUSD | D9: No | E9: 1 req/s | F9: JSON | G9: Tercera referencia de precio
A10: Bitstamp | B10: Precio spot | C10: https://www.bitstamp.net/api/v2/ticker/btcusd/ | D10: No | E10: 8000 req/10min | F10: JSON | G10: Venue citada en el analisis del 28-ago
A11: Bybit v5 | B11: Funding, OI, tickers | C11: https://api.bybit.com/v5/market/tickers?category=linear&symbol=BTCUSDT | D11: No | E11: 120 req/s | F11: JSON | G11: Agregacion multi-venue de OI
A12: OKX v5 | B12: Funding, OI, opciones | C12: https://www.okx.com/api/v5/public/funding-rate?instId=BTC-USDT-SWAP | D12: No | E12: 20 req/2s | F12: JSON | G12: Divergencia de funding entre venues
A13: Deribit v2 | B13: Opciones, indice, DVOL | C13: https://www.deribit.com/api/v2/public/get_book_summary_by_currency?currency=BTC&kind=option | D13: No | E13: 20 req/s | F13: JSON | G13: Max pain, volatilidad implicita, expiraciones
A14: CoinGecko | B14: Precio agregado, capitalizacion, dominancia | C14: https://api.coingecko.com/api/v3/global | D14: No | E14: 10-30 req/min | F14: JSON | G14: Contexto de mercado total
A15: alternative.me | B15: Fear & Greed | C15: https://api.alternative.me/fng/?limit=30 | D15: No | E15: Sin limite publicado | F15: JSON | G15: Sentimiento; clave para leer squeezes
... A29: Binance klines futuros | B29: OHLC + flujo agresor 5 min | C29: https://fapi.binance.com/fapi/v1/klines?symbol=BTCUSDT&interval=5m&limit=499 | D29: No | E29: Alto | F29: JSON | G29: Hojas 13, 14 y 16 via qBase5m

Sheet 9_PowerQuery_M
A1: CODIGO POWER QUERY (M) — REFRESH REAL Y MULTIPLATAFORMA
A2: WEBSERVICE solo existe en Excel para Windows. Power Query funciona en Windows y Mac y se refresca con Datos > Actualizar todo.
A4: ARRANQUE MINIMO (v3): instala primero las 3 consultas marcadas NUEVA v3. Son las que alimentan el motor de liquidaciones.
A5: 1. Datos > Obtener datos > De otras fuentes > Consulta en blanco
A6: 2. Inicio > Editor avanzado > borra todo y pega el bloque
A7: 3. Ponle el nombre indicado > Cerrar y cargar en > Tabla > Hoja existente > la celda que indica el comentario de cabecera
A8: 4. Datos > Consultas y conexiones > Propiedades > 'Actualizar cada 5 minutos' y 'Actualizar al abrir'
A9: Privacidad: cuando Excel lo pida, marca todos los origenes como 'Publico'.
A10: v3: todas las consultas convierten numeros con configuracion 'en-US' para no fallar en Excel en espanol.
A12: CONSULTA: | B12: qBase5m [NUEVA v3 - IMPRESCINDIBLE]
B13: // Barras de 5 min de BTCUSDT perpetuo + Open Interest. Alimenta el mapa de liquidaciones
B14: // (hojas 13 y 14) y el detector de fase de cascada (hoja 16).
B15: // CARGAR EN: hoja 12_Datos_5m, celda A4 (Cerrar y cargar en > Tabla > Hoja existente)
B16: let
B17: Simbolo = "BTCUSDT",
B18: Klines = Json.Document(Web.Contents(
B19: "https://fapi.binance.com/fapi/v1/klines?symbol=" & Simbolo & "&interval=5m&limit=499")),
B20: Filas = List.Transform(Klines, each {_{0}, _{1}, _{2}, _{3}, _{4}, _{7}, _{10}}),
B21: TK = Table.FromRows(Filas, {"OpenTime","Open","High","Low","Close","QuoteVol","TakerBuyQuote"}),
B22: TK2 = Table.TransformColumnTypes(TK, {{"OpenTime", Int64.Type},{"Open", type number},
B23: {"High", type number},{"Low", type number},{"Close", type number},
B24: {"QuoteVol", type number},{"TakerBuyQuote", type number}}, "en-US"),
... B39: Final
A41: CONSULTA: | B41: qLiqOKX [NUEVA v3 - liquidaciones REALES]
B42: // Liquidaciones reales ejecutadas en OKX (endpoint publico, sin clave). Pagina hasta 10 x 100.
B43: // CARGAR EN: hoja 15_Liq_Reales, celda M4
B44: let
B45: ValorContrato = 0.01, // BTC por contrato BTC-USDT-SWAP. Verificar en /api/v5/public/instruments
B46: Base = "https://www.okx.com/api/v5/public/liquidation-orders?instType=SWAP&instFamily=BTC-USDT&state=filled&limit=100",
B47: Traer = (despues as nullable text) as list =>
B48: let
B49: Url = if despues = null then Base else Base & "&after=" & despues,
B50: J = Json.Document(Web.Contents(Url)),
B51: D = if List.Count(J[data]) = 0 then {} else J[data]{0}[details]
B52: in
B53: D,
... B72: Orden
A74: CONSULTA: | B74: qLiqBinanceCSV [NUEVA v3 - requiere el colector Python]
B75: // Lee el CSV que escribe colector_liquidaciones.py (Binance forceOrder en tiempo real).
B76: // La ruta se toma de la celda con nombre RutaCSV (hoja 15, celda B6).
B77: // CARGAR EN: hoja 15_Liq_Reales, celda T4
B78: let
B79: Ruta = Excel.CurrentWorkbook(){[Name="RutaCSV"]}[Content]{0}[Column1],
B80: Origen = Csv.Document(File.Contents(Ruta), [Delimiter=",", Encoding=65001, QuoteStyle=QuoteStyle.Csv]),
B81: Enc = Table.PromoteHeaders(Origen, [PromoteAllScalars=true]),
B82: Ty = Table.TransformColumnTypes(Enc, {{"ts_ms", Int64.Type},{"precio", type number},
B83: {"cantidad", type number},{"usd", type number}}, "en-US"),
B84: Sim = Table.SelectRows(Ty, each [simbolo] = "BTCUSDT"),
B85: Maximo = List.Max(Sim[ts_ms]),
B86: Corte = if Maximo = null then 0 else Maximo - 86400000,
... B93: Final
A95: CONSULTA: | B95: qPrecios
B96: let
B97: Fuentes = {
B98: [Activo="BTC", Url="https://api.binance.com/api/v3/ticker/24hr?symbol=BTCUSDT"],
B99: [Activo="ETH", Url="https://api.binance.com/api/v3/ticker/24hr?symbol=ETHUSDT"]
B100: },
B101: Tabla = Table.FromRecords(Fuentes),
B102: Llamada = Table.AddColumn(Tabla, "Datos", each Json.Document(Web.Contents([Url]))),
B103: Expandir = Table.ExpandRecordColumn(Llamada, "Datos",
B104: {"lastPrice","priceChangePercent","highPrice","lowPrice","quoteVolume","weightedAvgPrice"},
B105: {"Precio","Var24h_pct","Max24h","Min24h","Volumen24h","VWAP24h"}),
B106: Tipos = Table.TransformColumnTypes(Expandir,{
B107: {"Precio", type number},{"Var24h_pct", type number},{"Max24h", type number},
... B114: Final
A116: CONSULTA: | B116: qDerivados
B117: let
B118: Simbolos = {"BTCUSDT","ETHUSDT"},
B119: Base = Table.FromList(Simbolos, Splitter.SplitByNothing(), {"Simbolo"}),
B121: Funding = Table.AddColumn(Base, "fnd", each
B122: Json.Document(Web.Contents("https://fapi.binance.com/fapi/v1/premiumIndex?symbol=" & [Simbolo]))),
B123: F1 = Table.AddColumn(Funding, "FundingRate", each Number.From([fnd][lastFundingRate], "en-US"), type number),
B124: F2 = Table.AddColumn(F1, "MarkPrice", each Number.From([fnd][markPrice], "en-US"), type number),
B126: OI = Table.AddColumn(F2, "oi", each
B127: Json.Document(Web.Contents("https://fapi.binance.com/fapi/v1/openInterest?symbol=" & [Simbolo]))),
B128: O1 = Table.AddColumn(OI, "OpenInterest_contratos", each Number.From([oi][openInterest], "en-US"), type number),
B129: O2 = Table.AddColumn(O1, "OpenInterest_USD", each [OpenInterest_contratos]*[MarkPrice], type number),
B131: LSretail = Table.AddColumn(O2, "lsr", each
... B156: Limpio
A158: CONSULTA: | B158: qOI_Historico_Purga
B159: // Mide el % de Open Interest destruido en las ultimas horas.
B160: // Es el sustituto gratuito del dato de liquidaciones de Coinglass.
B161: let
B162: Origen = Json.Document(Web.Contents(
B163: "https://fapi.binance.com/futures/data/openInterestHist?symbol=BTCUSDT&period=5m&limit=288")),
B164: Tabla = Table.FromList(Origen, Splitter.SplitByNothing(), {"c"}),
B165: Exp = Table.ExpandRecordColumn(Tabla, "c",
B166: {"timestamp","sumOpenInterest","sumOpenInterestValue"},
B167: {"ts","OI_contratos","OI_USD"}),
B168: Tipos = Table.TransformColumnTypes(Exp,{{"OI_contratos", type number},{"OI_USD", type number}}, "en-US"),
B169: Fecha = Table.AddColumn(Tipos, "Hora",
B170: each DateTimeZone.FromUnixTime([ts]/1000), type datetimezone),
... B190: Resumen
A192: CONSULTA: | B192: qSentimiento_Macro
B193: let
B194: FnG = Json.Document(Web.Contents("https://api.alternative.me/fng/?limit=30")),
B195: Datos = Table.FromList(FnG[data], Splitter.SplitByNothing(), {"c"}),
B196: Exp = Table.ExpandRecordColumn(Datos, "c",
B197: {"value","value_classification","timestamp"},
B198: {"FearGreed","Clasificacion","ts"}),
...

Sheet 10_Bitacora
A1: BITACORA DE OPERACIONES
A2: Registra cada intento. La fila 5 es un EJEMPLO con el formato esperado: borrala antes de usar.
A4: Fecha | B4: Activo | C4: Entrada | D4: Stop | E4: Salida | F4: Apalanc. | G4: Filtros (0-5) | H4: P&L % | I4: Que aprendi
A5: 2026-08-28 | B5: BTC | C5: 76909 | D5: 73800 | E5: 77712 | F5: 3 | G5: 2.5 | H5: =IFERROR((E5-C5)/C5*F5,0) -> 0.031322732 | I5: EJEMPLO: filtros en 2.5, por debajo del minimo de 4. No se debio operar.
H6: =IF(AND(ISNUMBER(C6),ISNUMBER(E6)),(E6-C6)/C6*F6,"")
H7: =IF(AND(ISNUMBER(C7),ISNUMBER(E7)),(E7-C7)/C7*F7,"")
H8: =IF(AND(ISNUMBER(C8),ISNUMBER(E8)),(E8-C8)/C8*F8,"")
H9: =IF(AND(ISNUMBER(C9),ISNUMBER(E9)),(E9-C9)/C9*F9,"")
H10: =IF(AND(ISNUMBER(C10),ISNUMBER(E10)),(E10-C10)/C10*F10,"")
H11: =IF(AND(ISNUMBER(C11),ISNUMBER(E11)),(E11-C11)/C11*F11,"")
H12: =IF(AND(ISNUMBER(C12),ISNUMBER(E12)),(E12-C12)/C12*F12,"")
H13: =IF(AND(ISNUMBER(C13),ISNUMBER(E13)),(E13-C13)/C13*F13,"")
H14: =IF(AND(ISNUMBER(C14),ISNUMBER(E14)),(E14-C14)/C14*F14,"")
H15: =IF(AND(ISNUMBER(C15),ISNUMBER(E15)),(E15-C15)/C15*F15,"")
H16: =IF(AND(ISNUMBER(C16),ISNUMBER(E16)),(E16-C16)/C16*F16,"")
H17: =IF(AND(ISNUMBER(C17),ISNUMBER(E17)),(E17-C17)/C17*F17,"")
... H40: =IF(AND(ISNUMBER(C40),ISNUMBER(E40)),(E40-C40)/C40*F40,"")
A42: RESUMEN | G42: Win rate | H42: =IFERROR(COUNTIF(H5:H40,">0")/COUNT(H5:H40),0) -> 1 | I42: Comparar contra el 'win rate minimo' de la hoja 7. Si es menor, la estrategia pierde por diseno.
G43: P&L acumulado | H43: =IFERROR(SUM(H5:H40),0) -> 0.031322732 | I43: Suma simple de retornos porcentuales.

Sheet 11_Fuentes_Supuestos
A1: FUENTES, SUPUESTOS Y ADVERTENCIAS
A3: Dato hardcodeado | B3: Valor | C3: Fuente / justificacion
A4: Precio BTC de respaldo | B4: 77,477 | C4: Ultimo dato citado el 28-ago-2026 tras el discurso de Warsh (minimo 76,909, recuperacion 77,712). Fuente: CryptoSlate / CoinDesk live blog.
A5: Precio ETH de respaldo | B5: 2,501 | C5: Blockonomi 28-ago-2026, pre-discurso. No hay dato aislado de ETH post-discurso confirmado.
A6: EMA 50 semanas BTC | B6: 77,250 | C6: Citado como nivel a defender para mantener la tendencia mayor intacta. Fuente: analisis tecnico recogido el 28-ago.
A7: MA 50 semanas BTC | B7: 81,033 | C7: CoinDesk, 24-ago-2026: siguiente resistencia mayor.
A8: Liquidaciones 24h | B8: 487.68 M | C8: CoinGlass via CryptoSlate, 28-ago-2026. 97,691 traders; >360 M en longs.
A9: Open Interest agregado | B9: 56.48 B | C9: CoinStats, dos dias hasta el 28-ago. +736.38 M (+1.32%).
A10: Funding BTC | B10: -0.0048% / 0.0057% | C10: MacroMicro, 28-ago-2026.
A11: Expiracion Deribit | B11: 6.32–6.44 B | C11: Deribit Metrics / DWF Labs. 78,595 contratos, max pain ~69,000, liquidacion 08:00 UTC.
A12: Flujos ETF | B12: 1.92 B semanales | C12: Trading Economics: mejores entradas en 10 meses. 8 sesiones positivas consecutivas (CoinStats).
A13: Prob. subida septiembre | B13: ~60% (desde ~35%) | C13: CoinDesk, tras el discurso de Warsh. El-Erian la considera demasiado alta.
A14: Rend. 2A / 30A | B14: 4.35% / 5.15% | C14: CoinDesk live blog 28-ago. El 2A subio 12pb; el 30A bajo.
... A19: Pesos del motor Wyckoff | B19: 0-3 por evidencia | C19: ASIGNACION SUBJETIVA. Editable en la hoja 6. Cambiala si tu lectura difiere.
A21: ADVERTENCIAS
A22: Esto NO es asesoria de inversion. Es un tablero de analisis. No soy asesor financiero y no conozco tu situacion, tolerancia al riesgo ni horizonte.
A23: Las APIs cambian sin aviso. Si una celda devuelve n/d, abre la URL en el navegador y revisa si la clave JSON sigue existiendo. Ajusta la columna D de las hojas 2-4.
A24: WEBSERVICE solo funciona en Excel para Windows y requiere permitir contenido externo. En Mac, iPad o Excel web usa las consultas Power Query de la hoja 9.
A25: El apalancamiento sobre cascadas de liquidacion puede eliminar una cuenta completa en segundos. La hoja 7 bloque D existe precisamente para que veas esa matematica antes de operar.
A26: Los clusters de liquidacion de BTC son derivacion estructural, no lectura de heatmap verificado. Los de ETH si estan citados de fuente. La diferencia importa.
A27: Coinglass no ofrece endpoint gratuito de liquidaciones. La consulta qOI_Historico_Purga de la hoja 9 es el mejor sustituto gratuito: mide destruccion de Open Interest, que es la causa mecanica de las liquidaciones.
A28: Los datos de referencia congelados corresponden al 28 de agosto de 2026. Todo lo que no se refresque por API envejece rapido.
A30: SUPUESTOS NUEVOS DE LA v3 (liquidaciones)
A31: Pesos de apalancamiento | B31: 15/30/30/15/10% | C31: SUPUESTO del modelo (hoja 13). No existe dato publico de la distribucion real. Ajustalo si tienes mejor informacion.
A32: Share agresor = lado que abre | B32: TakerBuy/QuoteVol | C32: SUPUESTO: el OI nuevo se reparte segun el flujo agresor. Aproximacion estandar, no exacta.
A33: Vida media de posiciones | B33: 24 h | C33: SUPUESTO. Sustituye al cierre voluntario, que no es observable.
A34: MMR | B34: 0.40% | C34: Tramo base de BTCUSDT en Binance. Tramos altos usan MMR mayor: el modelo es conservador ahi.
A35: Factor de cobertura | B35: 50% | C35: SUPUESTO: Binance+OKX como fraccion de liquidaciones del mercado. Calibralo contra Coinglass cuando puedas.
A36: Limite del stream forceOrder | B36: 1 evento/s/simbolo | C36: Documentado por Binance: en cascadas fuertes el colector SUBESTIMA.
A37: Valor de contrato OKX | B37: 0.01 BTC | C37: BTC-USDT-SWAP. Verificar en /api/v5/public/instruments si cambia.

Sheet 12_Datos_5m
A1: DATOS 5 MIN — BTCUSDT PERPETUO (zona de aterrizaje de qBase5m)
A2: Pega la consulta qBase5m (hoja 9) y cargala aqui: Cerrar y cargar en > Tabla > Hoja existente > =12_Datos_5m!$A$4. No escribas a mano en A4:I504.
A3: =IF(COUNT(F5:F504)=0,"SIN DATOS: instala qBase5m (hoja 9)","Barras cargadas: "&COUNT(F5:F504)&" de 5 min") -> SIN DATOS: instala qBase5m (hoja 9)
A4: OpenTime | B4: Hora | C4: Open | D4: High | E4: Low | F4: Close | G4: QuoteVol | H4: TakerBuyQuote | I4: OI_USD
K5: QUE HAY AQUI
K6: 499 barras de 5 minutos (~41 horas) del perpetuo BTCUSDT de Binance, con el Open Interest
K7: en USD de cada barra. Es la materia prima del mapa de liquidaciones estimado.
K9: POR QUE ESTOS CAMPOS
K10: OI_USD: cuando sube, se abrieron posiciones nuevas. Cada una tiene un precio de liquidacion.
K11: TakerBuyQuote / QuoteVol: la fraccion agresora compradora. Se usa para repartir el OI nuevo
K12: entre largos y cortos (supuesto: quien abre posicion es mayoritariamente el agresor).
K13: High / Low: permiten saber si el precio YA toco un nivel de liquidacion. Si lo toco,
K14: esas posiciones ya no existen y se borran del mapa. Esto es lo que separa un mapa util
K15: de uno que muestra clusters fantasma.

Sheet 14_Motor_Liq
A1: MOTOR DEL MAPA — una fila por barra de 5 min (no editar)
A2: Tiempo mas reciente (ms) | C2: =MAX('12_Datos_5m'!$A$5:$A$504) -> 0
A4: n | B4: Close | C4: OpenTime | D4: Delta OI | E4: OI nuevo | F4: Share compra | G4: Edad (h) | H4: Peso vida | I4: Nocional LONG | J4: Nocional SHORT | K4: Min futuro | L4: Max futuro | M4: Liq L T1 | N4: Vivo L T1 | O4: Liq S T1 | P4: Vivo S T1 | Q4: Liq L T2 | R4: Vivo L T2 | S4: Liq S T2 | T4: Vivo S T2 | U4: Liq L T3 | V4: Vivo L T3 | W4: Liq S T3 | X4: Vivo S T3 | Y4: Liq L T4 | Z4: Vivo L T4 | AA4: Liq S T4 | AB4: Vivo S T4 | AC4: Liq L T5 | AD4: Vivo L T5 | AE4: Liq S T5 | AF4: Vivo S T5 | AH4: Ejec. LONG | AI4: Ejec. SHORT
A5: =IF(ISNUMBER('12_Datos_5m'!F5),ROW()-4,"") | B5: =IF(ISNUMBER('12_Datos_5m'!F5),'12_Datos_5m'!F5,"") | C5: =IF(ISNUMBER('12_Datos_5m'!A5),'12_Datos_5m'!A5,"") | D5: =0 -> 0 | E5: =MAX(0,D5) -> 0 | F5: =IF(AND(ISNUMBER('12_Datos_5m'!G5),N('12_Datos_5m'!G5)>0),'12_Datos_5m'!H5/'12_Datos_5m'!G5,0.5) -> 0.5 | G5: =IF(ISNUMBER(C5),($C$2-C5)/3600000,0) -> 0 | H5: =EXP(-G5/'13_Mapa_Liq'!$B$7) -> 1 | I5: =E5*F5*H5 -> 0 | J5: =E5*(1-F5)*H5 -> 0 | K5: =IF(COUNT('12_Datos_5m'!E6:E$504)=0,1000000000000,MIN('12_Datos_5m'!E6:E$504)) -> 1000000000000 | L5: =IF(COUNT('12_Datos_5m'!D6:D$504)=0,0,MAX('12_Datos_5m'!D6:D$504)) -> 0 | M5: =IF(ISNUMBER(B5),B5*(1-1/'13_Mapa_Liq'!$B$15+'13_Mapa_Liq'!$B$6),"") | N5: =IF(ISNUMBER(B5),IF(K5>M5,I5*'13_Mapa_Liq'!$C$15,0),0) -> 0 | O5: =IF(ISNUMBER(B5),B5*(1+1/'13_Mapa_Liq'!$B$15-'13_Mapa_Liq'!$B$6),"") | P5: =IF(ISNUMBER(B5),IF(L5<O5,J5*'13_Mapa_Liq'!$C$15,0),0) -> 0 | Q5: =IF(ISNUMBER(B5),B5*(1-1/'13_Mapa_Liq'!$B$16+'13_Mapa_Liq'!$B$6),"") | R5: =IF(ISNUMBER(B5),IF(K5>Q5,I5*'13_Mapa_Liq'!$C$16,0),0) -> 0 | S5: =IF(ISNUMBER(B5),B5*(1+1/'13_Mapa_Liq'!$B$16-'13_Mapa_Liq'!$B$6),"") | T5: =IF(ISNUMBER(B5),IF(L5<S5,J5*'13_Mapa_Liq'!$C$16,0),0) -> 0 | U5: =IF(ISNUMBER(B5),B5*(1-1/'13_Mapa_Liq'!$B$17+'13_Mapa_Liq'!$B$6),"") | V5: =IF(ISNUMBER(B5),IF(K5>U5,I5*'13_Mapa_Liq'!$C$17,0),0) -> 0 | W5: =IF(ISNUMBER(B5),B5*(1+1/'13_Mapa_Liq'!$B$17-'13_Mapa_Liq'!$B$6),"") | X5: =IF(ISNUMBER(B5),IF(L5<W5,J5*'13_Mapa_Liq'!$C$17,0),0) -> 0 | Y5: =IF(ISNUMBER(B5),B5*(1-1/'13_Mapa_Liq'!$B$18+'13_Mapa_Liq'!$B$6),"") | Z5: =IF(ISNUMBER(B5),IF(K5>Y5,I5*'13_Mapa_Liq'!$C$18,0),0) -> 0 | AA5: =IF(ISNUMBER(B5),B5*(1+1/'13_Mapa_Liq'!$B$18-'13_Mapa_Liq'!$B$6),"") | AB5: =IF(ISNUMBER(B5),IF(L5<AA5,J5*'13_Mapa_Liq'!$C$18,0),0) -> 0 | AC5: =IF(ISNUMBER(B5),B5*(1-1/'13_Mapa_Liq'!$B$19+'13_Mapa_Liq'!$B$6),"") | AD5: =IF(ISNUMBER(B5),IF(K5>AC5,I5*'13_Mapa_Liq'!$C$19,0),0) -> 0 | AE5: =IF(ISNUMBER(B5),B5*(1+1/'13_Mapa_Liq'!$B$19-'13_Mapa_Liq'!$B$6),"") | AF5: =IF(ISNUMBER(B5),IF(L5<AE5,J5*'13_Mapa_Liq'!$C$19,0),0) -> 0 | AH5: =IF(ISNUMBER(B5),E5*F5*((K5<=M5)*'13_Mapa_Liq'!$C$15+(K5<=Q5)*'13_Mapa_Liq'!$C$16+(K5<=U5)*'13_Mapa_Liq'!$C$17+(K5<=Y5)*'13_Mapa_Liq'!$C$18+(K5<=AC5)*'13_Mapa_Liq'!$C$19),0) -> 0 | AI5: =IF(ISNUMBER(B5),E5*(1-F5)*((L5>=O5)*'13_Mapa_Liq'!$C$15+(L5>=S5)*'13_Mapa_Liq'!$C$16+(L5>=W5)*'13_Mapa_Liq'!$C$17+(L5>=AA5)*'13_Mapa_Liq'!$C$18+(L5>=AE5)*'13_Mapa_Liq'!$C$19),0) -> 0
A6: =IF(ISNUMBER('12_Datos_5m'!F6),ROW()-4,"") | B6: =IF(ISNUMBER('12_Datos_5m'!F6),'12_Datos_5m'!F6,"") | C6: =IF(ISNUMBER('12_Datos_5m'!A6),'12_Datos_5m'!A6,"") | D6: =IF(AND(ISNUMBER('12_Datos_5m'!I6),ISNUMBER('12_Datos_5m'!I5)),'12_Datos_5m'!I6-'12_Datos_5m'!I5,0) -> 0 | E6: =MAX(0,D6) -> 0 | F6: =IF(AND(ISNUMBER('12_Datos_5m'!G6),N('12_Datos_5m'!G6)>0),'12_Datos_5m'!H6/'12_Datos_5m'!G6,0.5) -> 0.5 | G6: =IF(ISNUMBER(C6),($C$2-C6)/3600000,0) -> 0 | H6: =EXP(-G6/'13_Mapa_Liq'!$B$7) -> 1 | I6: =E6*F6*H6 -> 0 | J6: =E6*(1-F6)*H6 -> 0 | K6: =IF(COUNT('12_Datos_5m'!E7:E$504)=0,1000000000000,MIN('12_Datos_5m'!E7:E$504)) -> 1000000000000 | L6: =IF(COUNT('12_Datos_5m'!D7:D$504)=0,0,MAX('12_Datos_5m'!D7:D$504)) -> 0 | M6: =IF(ISNUMBER(B6),B6*(1-1/'13_Mapa_Liq'!$B$15+'13_Mapa_Liq'!$B$6),"") | N6: =IF(ISNUMBER(B6),IF(K6>M6,I6*'13_Mapa_Liq'!$C$15,0),0) -> 0 | O6: =IF(ISNUMBER(B6),B6*(1+1/'13_Mapa_Liq'!$B$15-'13_Mapa_Liq'!$B$6),"") | P6: =IF(ISNUMBER(B6),IF(L6<O6,J6*'13_Mapa_Liq'!$C$15,0),0) -> 0 | Q6: =IF(ISNUMBER(B6),B6*(1-1/'13_Mapa_Liq'!$B$16+'13_Mapa_Liq'!$B$6),"") | R6: =IF(ISNUMBER(B6),IF(K6>Q6,I6*'13_Mapa_Liq'!$C$16,0),0) -> 0 | S6: =IF(ISNUMBER(B6),B6*(1+1/'13_Mapa_Liq'!$B$16-'13_Mapa_Liq'!$B$6),"") | T6: =IF(ISNUMBER(B6),IF(L6<S6,J6*'13_Mapa_Liq'!$C$16,0),0) -> 0 | U6: =IF(ISNUMBER(B6),B6*(1-1/'13_Mapa_Liq'!$B$17+'13_Mapa_Liq'!$B$6),"") | V6: =IF(ISNUMBER(B6),IF(K6>U6,I6*'13_Mapa_Liq'!$C$17,0),0) -> 0 | W6: =IF(ISNUMBER(B6),B6*(1+1/'13_Mapa_Liq'!$B$17-'13_Mapa_Liq'!$B$6),"") | X6: =IF(ISNUMBER(B6),IF(L6<W6,J6*'13_Mapa_Liq'!$C$17,0),0) -> 0 | Y6: =IF(ISNUMBER(B6),B6*(1-1/'13_Mapa_Liq'!$B$18+'13_Mapa_Liq'!$B$6),"") | Z6: =IF(ISNUMBER(B6),IF(K6>Y6,I6*'13_Mapa_Liq'!$C$18,0),0) -> 0 | AA6: =IF(ISNUMBER(B6),B6*(1+1/'13_Mapa_Liq'!$B$18-'13_Mapa_Liq'!$B$6),"") | AB6: =IF(ISNUMBER(B6),IF(L6<AA6,J6*'13_Mapa_Liq'!$C$18,0),0) -> 0 | AC6: =IF(ISNUMBER(B6),B6*(1-1/'13_Mapa_Liq'!$B$19+'13_Mapa_Liq'!$B$6),"") | AD6: =IF(ISNUMBER(B6),IF(K6>AC6,I6*'13_Mapa_Liq'!$C$19,0),0) -> 0 | AE6: =IF(ISNUMBER(B6),B6*(1+1/'13_Mapa_Liq'!$B$19-'13_Mapa_Liq'!$B$6),"") | AF6: =IF(ISNUMBER(B6),IF(L6<AE6,J6*'13_Mapa_Liq'!$C$19,0),0) -> 0 | AH6: =IF(ISNUMBER(B6),E6*F6*((K6<=M6)*'13_Mapa_Liq'!$C$15+(K6<=Q6)*'13_Mapa_Liq'!$C$16+(K6<=U6)*'13_Mapa_Liq'!$C$17+(K6<=Y6)*'13_Mapa_Liq'!$C$18+(K6<=AC6)*'13_Mapa_Liq'!$C$19),0) -> 0 | AI6: =IF(ISNUMBER(B6),E6*(1-F6)*((L6>=O6)*'13_Mapa_Liq'!$C$15+(L6>=S6)*'13_Mapa_Liq'!$C$16+(L6>=W6)*'13_Mapa_Liq'!$C$17+(L6>=AA6)*'13_Mapa_Liq'!$C$18+(L6>=AE6)*'13_Mapa_Liq'!$C$19),0) -> 0
A7: =IF(ISNUMBER('12_Datos_5m'!F7),ROW()-4,"") | B7: =IF(ISNUMBER('12_Datos_5m'!F7),'12_Datos_5m'!F7,"") | C7: =IF(ISNUMBER('12_Datos_5m'!A7),'12_Datos_5m'!A7,"") | D7: =IF(AND(ISNUMBER('12_Datos_5m'!I7),ISNUMBER('12_Datos_5m'!I6)),'12_Datos_5m'!I7-'12_Datos_5m'!I6,0) -> 0 | E7: =MAX(0,D7) -> 0 | F7: =IF(AND(ISNUMBER('12_Datos_5m'!G7),N('12_Datos_5m'!G7)>0),'12_Datos_5m'!H7/'12_Datos_5m'!G7,0.5) -> 0.5 | G7: =IF(ISNUMBER(C7),($C$2-C7)/3600000,0) -> 0 | H7: =EXP(-G7/'13_Mapa_Liq'!$B$7) -> 1 | I7: =E7*F7*H7 -> 0 | J7: =E7*(1-F7)*H7 -> 0 | K7: =IF(COUNT('12_Datos_5m'!E8:E$504)=0,1000000000000,MIN('12_Datos_5m'!E8:E$504)) -> 1000000000000 | L7: =IF(COUNT('12_Datos_5m'!D8:D$504)=0,0,MAX('12_Datos_5m'!D8:D$504)) -> 0 | M7: =IF(ISNUMBER(B7),B7*(1-1/'13_Mapa_Liq'!$B$15+'13_Mapa_Liq'!$B$6),"") | N7: =IF(ISNUMBER(B7),IF(K7>M7,I7*'13_Mapa_Liq'!$C$15,0),0) -> 0 | O7: =IF(ISNUMBER(B7),B7*(1+1/'13_Mapa_Liq'!$B$15-'13_Mapa_Liq'!$B$6),"") | P7: =IF(ISNUMBER(B7),IF(L7<O7,J7*'13_Mapa_Liq'!$C$15,0),0) -> 0 | Q7: =IF(ISNUMBER(B7),B7*(1-1/'13_Mapa_Liq'!$B$16+'13_Mapa_Liq'!$B$6),"") | R7: =IF(ISNUMBER(B7),IF(K7>Q7,I7*'13_Mapa_Liq'!$C$16,0),0) -> 0 | S7: =IF(ISNUMBER(B7),B7*(1+1/'13_Mapa_Liq'!$B$16-'13_Mapa_Liq'!$B$6),"") | T7: =IF(ISNUMBER(B7),IF(L7<S7,J7*'13_Mapa_Liq'!$C$16,0),0) -> 0 | U7: =IF(ISNUMBER(B7),B7*(1-1/'13_Mapa_Liq'!$B$17+'13_Mapa_Liq'!$B$6),"") | V7: =IF(ISNUMBER(B7),IF(K7>U7,I7*'13_Mapa_Liq'!$C$17,0),0) -> 0 | W7: =IF(ISNUMBER(B7),B7*(1+1/'13_Mapa_Liq'!$B$17-'13_Mapa_Liq'!$B$6),"") | X7: =IF(ISNUMBER(B7),IF(L7<W7,J7*'13_Mapa_Liq'!$C$17,0),0) -> 0 | Y7: =IF(ISNUMBER(B7),B7*(1-1/'13_Mapa_Liq'!$B$18+'13_Mapa_Liq'!$B$6),"") | Z7: =IF(ISNUMBER(B7),IF(K7>Y7,I7*'13_Mapa_Liq'!$C$18,0),0) -> 0 | AA7: =IF(ISNUMBER(B7),B7*(1+1/'13_Mapa_Liq'!$B$18-'13_Mapa_Liq'!$B$6),"") | AB7: =IF(ISNUMBER(B7),IF(L7<AA7,J7*'13_Mapa_Liq'!$C$18,0),0) -> 0 | AC7: =IF(ISNUMBER(B7),B7*(1-1/'13_Mapa_Liq'!$B$19+'13_Mapa_Liq'!$B$6),"") | AD7: =IF(ISNUMBER(B7),IF(K7>AC7,I7*'13_Mapa_Liq'!$C$19,0),0) -> 0 | AE7: =IF(ISNUMBER(B7),B7*(1+1/'13_Mapa_Liq'!$B$19-'13_Mapa_Liq'!$B$6),"") | AF7: =IF(ISNUMBER(B7),IF(L7<AE7,J7*'13_Mapa_Liq'!$C$19,0),0) -> 0 | AH7: =IF(ISNUMBER(B7),E7*F7*((K7<=M7)*'13_Mapa_Liq'!$C$15+(K7<=Q7)*'13_Mapa_Liq'!$C$16+(K7<=U7)*'13_Mapa_Liq'!$C$17+(K7<=Y7)*'13_Mapa_Liq'!$C$18+(K7<=AC7)*'13_Mapa_Liq'!$C$19),0) -> 0 | AI7: =IF(ISNUMBER(B7),E7*(1-F7)*((L7>=O7)*'13_Mapa_Liq'!$C$15+(L7>=S7)*'13_Mapa_Liq'!$C$16+(L7>=W7)*'13_Mapa_Liq'!$C$17+(L7>=AA7)*'13_Mapa_Liq'!$C$18+(L7>=AE7)*'13_Mapa_Liq'!$C$19),0) -> 0
A8: =IF(ISNUMBER('12_Datos_5m'!F8),ROW()-4,"") | B8: =IF(ISNUMBER('12_Datos_5m'!F8),'12_Datos_5m'!F8,"") | C8: =IF(ISNUMBER('12_Datos_5m'!A8),'12_Datos_5m'!A8,"") | D8: =IF(AND(ISNUMBER('12_Datos_5m'!I8),ISNUMBER('12_Datos_5m'!I7)),'12_Datos_5m'!I8-'12_Datos_5m'!I7,0) -> 0 | E8: =MAX(0,D8) -> 0 | F8: =IF(AND(ISNUMBER('12_Datos_5m'!G8),N('12_Datos_5m'!G8)>0),'12_Datos_5m'!H8/'12_Datos_5m'!G8,0.5) -> 0.5 | G8: =IF(ISNUMBER(C8),($C$2-C8)/3600000,0) -> 0 | H8: =EXP(-G8/'13_Mapa_Liq'!$B$7) -> 1 | I8: =E8*F8*H8 -> 0 | J8: =E8*(1-F8)*H8 -> 0 | K8: =IF(COUNT('12_Datos_5m'!E9:E$504)=0,1000000000000,MIN('12_Datos_5m'!E9:E$504)) -> 1000000000000 | L8: =IF(COUNT('12_Datos_5m'!D9:D$504)=0,0,MAX('12_Datos_5m'!D9:D$504)) -> 0 | M8: =IF(ISNUMBER(B8),B8*(1-1/'13_Mapa_Liq'!$B$15+'13_Mapa_Liq'!$B$6),"") | N8: =IF(ISNUMBER(B8),IF(K8>M8,I8*'13_Mapa_Liq'!$C$15,0),0) -> 0 | O8: =IF(ISNUMBER(B8),B8*(1+1/'13_Mapa_Liq'!$B$15-'13_Mapa_Liq'!$B$6),"") | P8: =IF(ISNUMBER(B8),IF(L8<O8,J8*'13_Mapa_Liq'!$C$15,0),0) -> 0 | Q8: =IF(ISNUMBER(B8),B8*(1-1/'13_Mapa_Liq'!$B$16+'13_Mapa_Liq'!$B$6),"") | R8: =IF(ISNUMBER(B8),IF(K8>Q8,I8*'13_Mapa_Liq'!$C$16,0),0) -> 0 | S8: =IF(ISNUMBER(B8),B8*(1+1/'13_Mapa_Liq'!$B$16-'13_Mapa_Liq'!$B$6),"") | T8: =IF(ISNUMBER(B8),IF(L8<S8,J8*'13_Mapa_Liq'!$C$16,0),0) -> 0 | U8: =IF(ISNUMBER(B8),B8*(1-1/'13_Mapa_Liq'!$B$17+'13_Mapa_Liq'!$B$6),"") | V8: =IF(ISNUMBER(B8),IF(K8>U8,I8*'13_Mapa_Liq'!$C$17,0),0) -> 0 | W8: =IF(ISNUMBER(B8),B8*(1+1/'13_Mapa_Liq'!$B$17-'13_Mapa_Liq'!$B$6),"") | X8: =IF(ISNUMBER(B8),IF(L8<W8,J8*'13_Mapa_Liq'!$C$17,0),0) -> 0 | Y8: =IF(ISNUMBER(B8),B8*(1-1/'13_Mapa_Liq'!$B$18+'13_Mapa_Liq'!$B$6),"") | Z8: =IF(ISNUMBER(B8),IF(K8>Y8,I8*'13_Mapa_Liq'!$C$18,0),0) -> 0 | AA8: =IF(ISNUMBER(B8),B8*(1+1/'13_Mapa_Liq'!$B$18-'13_Mapa_Liq'!$B$6),"") | AB8: =IF(ISNUMBER(B8),IF(L8<AA8,J8*'13_Mapa_Liq'!$C$18,0),0) -> 0 | AC8: =IF(ISNUMBER(B8),B8*(1-1/'13_Mapa_Liq'!$B$19+'13_Mapa_Liq'!$B$6),"") | AD8: =IF(ISNUMBER(B8),IF(K8>AC8,I8*'13_Mapa_Liq'!$C$19,0),0) -> 0 | AE8: =IF(ISNUMBER(B8),B8*(1+1/'13_Mapa_Liq'!$B$19-'13_Mapa_Liq'!$B$6),"") | AF8: =IF(ISNUMBER(B8),IF(L8<AE8,J8*'13_Mapa_Liq'!$C$19,0),0) -> 0 | AH8: =IF(ISNUMBER(B8),E8*F8*((K8<=M8)*'13_Mapa_Liq'!$C$15+(K8<=Q8)*'13_Mapa_Liq'!$C$16+(K8<=U8)*'13_Mapa_Liq'!$C$17+(K8<=Y8)*'13_Mapa_Liq'!$C$18+(K8<=AC8)*'13_Mapa_Liq'!$C$19),0) -> 0 | AI8: =IF(ISNUMBER(B8),E8*(1-F8)*((L8>=O8)*'13_Mapa_Liq'!$C$15+(L8>=S8)*'13_Mapa_Liq'!$C$16+(L8>=W8)*'13_Mapa_Liq'!$C$17+(L8>=AA8)*'13_Mapa_Liq'!$C$18+(L8>=AE8)*'13_Mapa_Liq'!$C$19),0) -> 0
A9: =IF(ISNUMBER('12_Datos_5m'!F9),ROW()-4,"") | B9: =IF(ISNUMBER('12_Datos_5m'!F9),'12_Datos_5m'!F9,"") | C9: =IF(ISNUMBER('12_Datos_5m'!A9),'12_Datos_5m'!A9,"") | D9: =IF(AND(ISNUMBER('12_Datos_5m'!I9),ISNUMBER('12_Datos_5m'!I8)),'12_Datos_5m'!I9-'12_Datos_5m'!I8,0) -> 0 | E9: =MAX(0,D9) -> 0 | F9: =IF(AND(ISNUMBER('12_Datos_5m'!G9),N('12_Datos_5m'!G9)>0),'12_Datos_5m'!H9/'12_Datos_5m'!G9,0.5) -> 0.5 | G9: =IF(ISNUMBER(C9),($C$2-C9)/3600000,0) -> 0 | H9: =EXP(-G9/'13_Mapa_Liq'!$B$7) -> 1 | I9: =E9*F9*H9 -> 0 | J9: =E9*(1-F9)*H9 -> 0 | K9: =IF(COUNT('12_Datos_5m'!E10:E$504)=0,1000000000000,MIN('12_Datos_5m'!E10:E$504)) -> 1000000000000 | L9: =IF(COUNT('12_Datos_5m'!D10:D$504)=0,0,MAX('12_Datos_5m'!D10:D$504)) -> 0 | M9: =IF(ISNUMBER(B9),B9*(1-1/'13_Mapa_Liq'!$B$15+'13_Mapa_Liq'!$B$6),"") | N9: =IF(ISNUMBER(B9),IF(K9>M9,I9*'13_Mapa_Liq'!$C$15,0),0) -> 0 | O9: =IF(ISNUMBER(B9),B9*(1+1/'13_Mapa_Liq'!$B$15-'13_Mapa_Liq'!$B$6),"") | P9: =IF(ISNUMBER(B9),IF(L9<O9,J9*'13_Mapa_Liq'!$C$15,0),0) -> 0 | Q9: =IF(ISNUMBER(B9),B9*(1-1/'13_Mapa_Liq'!$B$16+'13_Mapa_Liq'!$B$6),"") | R9: =IF(ISNUMBER(B9),IF(K9>Q9,I9*'13_Mapa_Liq'!$C$16,0),0) -> 0 | S9: =IF(ISNUMBER(B9),B9*(1+1/'13_Mapa_Liq'!$B$16-'13_Mapa_Liq'!$B$6),"") | T9: =IF(ISNUMBER(B9),IF(L9<S9,J9*'13_Mapa_Liq'!$C$16,0),0) -> 0 | U9: =IF(ISNUMBER(B9),B9*(1-1/'13_Mapa_Liq'!$B$17+'13_Mapa_Liq'!$B$6),"") | V9: =IF(ISNUMBER(B9),IF(K9>U9,I9*'13_Mapa_Liq'!$C$17,0),0) -> 0 | W9: =IF(ISNUMBER(B9),B9*(1+1/'13_Mapa_Liq'!$B$17-'13_Mapa_Liq'!$B$6),"") | X9: =IF(ISNUMBER(B9),IF(L9<W9,J9*'13_Mapa_Liq'!$C$17,0),0) -> 0 | Y9: =IF(ISNUMBER(B9),B9*(1-1/'13_Mapa_Liq'!$B$18+'13_Mapa_Liq'!$B$6),"") | Z9: =IF(ISNUMBER(B9),IF(K9>Y9,I9*'13_Mapa_Liq'!$C$18,0),0) -> 0 | AA9: =IF(ISNUMBER(B9),B9*(1+1/'13_Mapa_Liq'!$B$18-'13_Mapa_Liq'!$B$6),"") | AB9: =IF(ISNUMBER(B9),IF(L9<AA9,J9*'13_Mapa_Liq'!$C$18,0),0) -> 0 | AC9: =IF(ISNUMBER(B9),B9*(1-1/'13_Mapa_Liq'!$B$19+'13_Mapa_Liq'!$B$6),"") | AD9: =IF(ISNUMBER(B9),IF(K9>AC9,I9*'13_Mapa_Liq'!$C$19,0),0) -> 0 | AE9: =IF(ISNUMBER(B9),B9*(1+1/'13_Mapa_Liq'!$B$19-'13_Mapa_Liq'!$B$6),"") | AF9: =IF(ISNUMBER(B9),IF(L9<AE9,J9*'13_Mapa_Liq'!$C$19,0),0) -> 0 | AH9: =IF(ISNUMBER(B9),E9*F9*((K9<=M9)*'13_Mapa_Liq'!$C$15+(K9<=Q9)*'13_Mapa_Liq'!$C$16+(K9<=U9)*'13_Mapa_Liq'!$C$17+(K9<=Y9)*'13_Mapa_Liq'!$C$18+(K9<=AC9)*'13_Mapa_Liq'!$C$19),0) -> 0 | AI9: =IF(ISNUMBER(B9),E9*(1-F9)*((L9>=O9)*'13_Mapa_Liq'!$C$15+(L9>=S9)*'13_Mapa_Liq'!$C$16+(L9>=W9)*'13_Mapa_Liq'!$C$17+(L9>=AA9)*'13_Mapa_Liq'!$C$18+(L9>=AE9)*'13_Mapa_Liq'!$C$19),0) -> 0
A10: =IF(ISNUMBER('12_Datos_5m'!F10),ROW()-4,"") | B10: =IF(ISNUMBER('12_Datos_5m'!F10),'12_Datos_5m'!F10,"") | C10: =IF(ISNUMBER('12_Datos_5m'!A10),'12_Datos_5m'!A10,"") | D10: =IF(AND(ISNUMBER('12_Datos_5m'!I10),ISNUMBER('12_Datos_5m'!I9)),'12_Datos_5m'!I10-'12_Datos_5m'!I9,0) -> 0 | E10: =MAX(0,D10) -> 0 | F10: =IF(AND(ISNUMBER('12_Datos_5m'!G10),N('12_Datos_5m'!G10)>0),'12_Datos_5m'!H10/'12_Datos_5m'!G10,0.5) -> 0.5 | G10: =IF(ISNUMBER(C10),($C$2-C10)/3600000,0) -> 0 | H10: =EXP(-G10/'13_Mapa_Liq'!$B$7) -> 1 | I10: =E10*F10*H10 -> 0 | J10: =E10*(1-F10)*H10 -> 0 | K10: =IF(COUNT('12_Datos_5m'!E11:E$504)=0,1000000000000,MIN('12_Datos_5m'!E11:E$504)) -> 1000000000000 | L10: =IF(COUNT('12_Datos_5m'!D11:D$504)=0,0,MAX('12_Datos_5m'!D11:D$504)) -> 0 | M10: =IF(ISNUMBER(B10),B10*(1-1/'13_Mapa_Liq'!$B$15+'13_Mapa_Liq'!$B$6),"") | N10: =IF(ISNUMBER(B10),IF(K10>M10,I10*'13_Mapa_Liq'!$C$15,0),0) -> 0 | O10: =IF(ISNUMBER(B10),B10*(1+1/'13_Mapa_Liq'!$B$15-'13_Mapa_Liq'!$B$6),"") | P10: =IF(ISNUMBER(B10),IF(L10<O10,J10*'13_Mapa_Liq'!$C$15,0),0) -> 0 | Q10: =IF(ISNUMBER(B10),B10*(1-1/'13_Mapa_Liq'!$B$16+'13_Mapa_Liq'!$B$6),"") | R10: =IF(ISNUMBER(B10),IF(K10>Q10,I10*'13_Mapa_Liq'!$C$16,0),0) -> 0 | S10: =IF(ISNUMBER(B10),B10*(1+1/'13_Mapa_Liq'!$B$16-'13_Mapa_Liq'!$B$6),"") | T10: =IF(ISNUMBER(B10),IF(L10<S10,J10*'13_Mapa_Liq'!$C$16,0),0) -> 0 | U10: =IF(ISNUMBER(B10),B10*(1-1/'13_Mapa_Liq'!$B$17+'13_Mapa_Liq'!$B$6),"") | V10: =IF(ISNUMBER(B10),IF(K10>U10,I10*'13_Mapa_Liq'!$C$17,0),0) -> 0 | W10: =IF(ISNUMBER(B10),B10*(1+1/'13_Mapa_Liq'!$B$17-'13_Mapa_Liq'!$B$6),"") | X10: =IF(ISNUMBER(B10),IF(L10<W10,J10*'13_Mapa_Liq'!$C$17,0),0) -> 0 | Y10: =IF(ISNUMBER(B10),B10*(1-1/'13_Mapa_Liq'!$B$18+'13_Mapa_Liq'!$B$6),"") | Z10: =IF(ISNUMBER(B10),IF(K10>Y10,I10*'13_Mapa_Liq'!$C$18,0),0) -> 0 | AA10: =IF(ISNUMBER(B10),B10*(1+1/'13_Mapa_Liq'!$B$18-'13_Mapa_Liq'!$B$6),"") | AB10: =IF(ISNUMBER(B10),IF(L10<AA10,J10*'13_Mapa_Liq'!$C$18,0),0) -> 0 | AC10: =IF(ISNUMBER(B10),B10*(1-1/'13_Mapa_Liq'!$B$19+'13_Mapa_Liq'!$B$6),"") | AD10: =IF(ISNUMBER(B10),IF(K10>AC10,I10*'13_Mapa_Liq'!$C$19,0),0) -> 0 | AE10: =IF(ISNUMBER(B10),B10*(1+1/'13_Mapa_Liq'!$B$19-'13_Mapa_Liq'!$B$6),"") | AF10: =IF(ISNUMBER(B10),IF(L10<AE10,J10*'13_Mapa_Liq'!$C$19,0),0) -> 0 | AH10: =IF(ISNUMBER(B10),E10*F10*((K10<=M10)*'13_Mapa_Liq'!$C$15+(K10<=Q10)*'13_Mapa_Liq'!$C$16+(K10<=U10)*'13_Mapa_Liq'!$C$17+(K10<=Y10)*'13_Mapa_Liq'!$C$18+(K10<=AC10)*'13_Mapa_Liq'!$C$19),0) -> 0 | AI10: =IF(ISNUMBER(B10),E10*(1-F10)*((L10>=O10)*'13_Mapa_Liq'!$C$15+(L10>=S10)*'13_Mapa_Liq'!$C$16+(L10>=W10)*'13_Mapa_Liq'!$C$17+(L10>=AA10)*'13_Mapa_Liq'!$C$18+(L10>=AE10)*'13_Mapa_Liq'!$C$19),0) -> 0
A11: =IF(ISNUMBER('12_Datos_5m'!F11),ROW()-4,"") | B11: =IF(ISNUMBER('12_Datos_5m'!F11),'12_Datos_5m'!F11,"") | C11: =IF(ISNUMBER('12_Datos_5m'!A11),'12_Datos_5m'!A11,"") | D11: =IF(AND(ISNUMBER('12_Datos_5m'!I11),ISNUMBER('12_Datos_5m'!I10)),'12_Datos_5m'!I11-'12_Datos_5m'!I10,0) -> 0 | E11: =MAX(0,D11) -> 0 | F11: =IF(AND(ISNUMBER('12_Datos_5m'!G11),N('12_Datos_5m'!G11)>0),'12_Datos_5m'!H11/'12_Datos_5m'!G11,0.5) -> 0.5 | G11: =IF(ISNUMBER(C11),($C$2-C11)/3600000,0) -> 0 | H11: =EXP(-G11/'13_Mapa_Liq'!$B$7) -> 1 | I11: =E11*F11*H11 -> 0 | J11: =E11*(1-F11)*H11 -> 0 | K11: =IF(COUNT('12_Datos_5m'!E12:E$504)=0,1000000000000,MIN('12_Datos_5m'!E12:E$504)) -> 1000000000000 | L11: =IF(COUNT('12_Datos_5m'!D12:D$504)=0,0,MAX('12_Datos_5m'!D12:D$504)) -> 0 | M11: =IF(ISNUMBER(B11),B11*(1-1/'13_Mapa_Liq'!$B$15+'13_Mapa_Liq'!$B$6),"") | N11: =IF(ISNUMBER(B11),IF(K11>M11,I11*'13_Mapa_Liq'!$C$15,0),0) -> 0 | O11: =IF(ISNUMBER(B11),B11*(1+1/'13_Mapa_Liq'!$B$15-'13_Mapa_Liq'!$B$6),"") | P11: =IF(ISNUMBER(B11),IF(L11<O11,J11*'13_Mapa_Liq'!$C$15,0),0) -> 0 | Q11: =IF(ISNUMBER(B11),B11*(1-1/'13_Mapa_Liq'!$B$16+'13_Mapa_Liq'!$B$6),"") | R11: =IF(ISNUMBER(B11),IF(K11>Q11,I11*'13_Mapa_Liq'!$C$16,0),0) -> 0 | S11: =IF(ISNUMBER(B11),B11*(1+1/'13_Mapa_Liq'!$B$16-'13_Mapa_Liq'!$B$6),"") | T11: =IF(ISNUMBER(B11),IF(L11<S11,J11*'13_Mapa_Liq'!$C$16,0),0) -> 0 | U11: =IF(ISNUMBER(B11),B11*(1-1/'13_Mapa_Liq'!$B$17+'13_Mapa_Liq'!$B$6),"") | V11: =IF(ISNUMBER(B11),IF(K11>U11,I11*'13_Mapa_Liq'!$C$17,0),0) -> 0 | W11: =IF(ISNUMBER(B11),B11*(1+1/'13_Mapa_Liq'!$B$17-'13_Mapa_Liq'!$B$6),"") | X11: =IF(ISNUMBER(B11),IF(L11<W11,J11*'13_Mapa_Liq'!$C$17,0),0) -> 0 | Y11: =IF(ISNUMBER(B11),B11*(1-1/'13_Mapa_Liq'!$B$18+'13_Mapa_Liq'!$B$6),"") | Z11: =IF(ISNUMBER(B11),IF(K11>Y11,I11*'13_Mapa_Liq'!$C$18,0),0) -> 0 | AA11: =IF(ISNUMBER(B11),B11*(1+1/'13_Mapa_Liq'!$B$18-'13_Mapa_Liq'!$B$6),"") | AB11: =IF(ISNUMBER(B11),IF(L11<AA11,J11*'13_Mapa_Liq'!$C$18,0),0) -> 0 | AC11: =IF(ISNUMBER(B11),B11*(1-1/'13_Mapa_Liq'!$B$19+'13_Mapa_Liq'!$B$6),"") | AD11: =IF(ISNUMBER(B11),IF(K11>AC11,I11*'13_Mapa_Liq'!$C$19,0),0) -> 0 | AE11: =IF(ISNUMBER(B11),B11*(1+1/'13_Mapa_Liq'!$B$19-'13_Mapa_Liq'!$B$6),"") | AF11: =IF(ISNUMBER(B11),IF(L11<AE11,J11*'13_Mapa_Liq'!$C$19,0),0) -> 0 | AH11: =IF(ISNUMBER(B11),E11*F11*((K11<=M11)*'13_Mapa_Liq'!$C$15+(K11<=Q11)*'13_Mapa_Liq'!$C$16+(K11<=U11)*'13_Mapa_Liq'!$C$17+(K11<=Y11)*'13_Mapa_Liq'!$C$18+(K11<=AC11)*'13_Mapa_Liq'!$C$19),0) -> 0 | AI11: =IF(ISNUMBER(B11),E11*(1-F11)*((L11>=O11)*'13_Mapa_Liq'!$C$15+(L11>=S11)*'13_Mapa_Liq'!$C$16+(L11>=W11)*'13_Mapa_Liq'!$C$17+(L11>=AA11)*'13_Mapa_Liq'!$C$18+(L11>=AE11)*'13_Mapa_Liq'!$C$19),0) -> 0
A12: =IF(ISNUMBER('12_Datos_5m'!F12),ROW()-4,"") | B12: =IF(ISNUMBER('12_Datos_5m'!F12),'12_Datos_5m'!F12,"") | C12: =IF(ISNUMBER('12_Datos_5m'!A12),'12_Datos_5m'!A12,"") | D12: =IF(AND(ISNUMBER('12_Datos_5m'!I12),ISNUMBER('12_Datos_5m'!I11)),'12_Datos_5m'!I12-'12_Datos_5m'!I11,0) -> 0 | E12: =MAX(0,D12) -> 0 | F12: =IF(AND(ISNUMBER('12_Datos_5m'!G12),N('12_Datos_5m'!G12)>0),'12_Datos_5m'!H12/'12_Datos_5m'!G12,0.5) -> 0.5 | G12: =IF(ISNUMBER(C12),($C$2-C12)/3600000,0) -> 0 | H12: =EXP(-G12/'13_Mapa_Liq'!$B$7) -> 1 | I12: =E12*F12*H12 -> 0 | J12: =E12*(1-F12)*H12 -> 0 | K12: =IF(COUNT('12_Datos_5m'!E13:E$504)=0,1000000000000,MIN('12_Datos_5m'!E13:E$504)) -> 1000000000000 | L12: =IF(COUNT('12_Datos_5m'!D13:D$504)=0,0,MAX('12_Datos_5m'!D13:D$504)) -> 0 | M12: =IF(ISNUMBER(B12),B12*(1-1/'13_Mapa_Liq'!$B$15+'13_Mapa_Liq'!$B$6),"") | N12: =IF(ISNUMBER(B12),IF(K12>M12,I12*'13_Mapa_Liq'!$C$15,0),0) -> 0 | O12: =IF(ISNUMBER(B12),B12*(1+1/'13_Mapa_Liq'!$B$15-'13_Mapa_Liq'!$B$6),"") | P12: =IF(ISNUMBER(B12),IF(L12<O12,J12*'13_Mapa_Liq'!$C$15,0),0) -> 0 | Q12: =IF(ISNUMBER(B12),B12*(1-1/'13_Mapa_Liq'!$B$16+'13_Mapa_Liq'!$B$6),"") | R12: =IF(ISNUMBER(B12),IF(K12>Q12,I12*'13_Mapa_Liq'!$C$16,0),0) -> 0 | S12: =IF(ISNUMBER(B12),B12*(1+1/'13_Mapa_Liq'!$B$16-'13_Mapa_Liq'!$B$6),"") | T12: =IF(ISNUMBER(B12),IF(L12<S12,J12*'13_Mapa_Liq'!$C$16,0),0) -> 0 | U12: =IF(ISNUMBER(B12),B12*(1-1/'13_Mapa_Liq'!$B$17+'13_Mapa_Liq'!$B$6),"") | V12: =IF(ISNUMBER(B12),IF(K12>U12,I12*'13_Mapa_Liq'!$C$17,0),0) -> 0 | W12: =IF(ISNUMBER(B12),B12*(1+1/'13_Mapa_Liq'!$B$17-'13_Mapa_Liq'!$B$6),"") | X12: =IF(ISNUMBER(B12),IF(L12<W12,J12*'13_Mapa_Liq'!$C$17,0),0) -> 0 | Y12: =IF(ISNUMBER(B12),B12*(1-1/'13_Mapa_Liq'!$B$18+'13_Mapa_Liq'!$B$6),"") | Z12: =IF(ISNUMBER(B12),IF(K12>Y12,I12*'13_Mapa_Liq'!$C$18,0),0) -> 0 | AA12: =IF(ISNUMBER(B12),B12*(1+1/'13_Mapa_Liq'!$B$18-'13_Mapa_Liq'!$B$6),"") | AB12: =IF(ISNUMBER(B12),IF(L12<AA12,J12*'13_Mapa_Liq'!$C$18,0),0) -> 0 | AC12: =IF(ISNUMBER(B12),B12*(1-1/'13_Mapa_Liq'!$B$19+'13_Mapa_Liq'!$B$6),"") | AD12: =IF(ISNUMBER(B12),IF(K12>AC12,I12*'13_Mapa_Liq'!$C$19,0),0) -> 0 | AE12: =IF(ISNUMBER(B12),B12*(1+1/'13_Mapa_Liq'!$B$19-'13_Mapa_Liq'!$B$6),"") | AF12: =IF(ISNUMBER(B12),IF(L12<AE12,J12*'13_Mapa_Liq'!$C$19,0),0) -> 0 | AH12: =IF(ISNUMBER(B12),E12*F12*((K12<=M12)*'13_Mapa_Liq'!$C$15+(K12<=Q12)*'13_Mapa_Liq'!$C$16+(K12<=U12)*'13_Mapa_Liq'!$C$17+(K12<=Y12)*'13_Mapa_Liq'!$C$18+(K12<=AC12)*'13_Mapa_Liq'!$C$19),0) -> 0 | AI12: =IF(ISNUMBER(B12),E12*(1-F12)*((L12>=O12)*'13_Mapa_Liq'!$C$15+(L12>=S12)*'13_Mapa_Liq'!$C$16+(L12>=W12)*'13_Mapa_Liq'!$C$17+(L12>=AA12)*'13_Mapa_Liq'!$C$18+(L12>=AE12)*'13_Mapa_Liq'!$C$19),0) -> 0
A13: =IF(ISNUMBER('12_Datos_5m'!F13),ROW()-4,"") | B13: =IF(ISNUMBER('12_Datos_5m'!F13),'12_Datos_5m'!F13,"") | C13: =IF(ISNUMBER('12_Datos_5m'!A13),'12_Datos_5m'!A13,"") | D13: =IF(AND(ISNUMBER('12_Datos_5m'!I13),ISNUMBER('12_Datos_5m'!I12)),'12_Datos_5m'!I13-'12_Datos_5m'!I12,0) -> 0 | E13: =MAX(0,D13) -> 0 | F13: =IF(AND(ISNUMBER('12_Datos_5m'!G13),N('12_Datos_5m'!G13)>0),'12_Datos_5m'!H13/'12_Datos_5m'!G13,0.5) -> 0.5 | G13: =IF(ISNUMBER(C13),($C$2-C13)/3600000,0) -> 0 | H13: =EXP(-G13/'13_Mapa_Liq'!$B$7) -> 1 | I13: =E13*F13*H13 -> 0 | J13: =E13*(1-F13)*H13 -> 0 | K13: =IF(COUNT('12_Datos_5m'!E14:E$504)=0,1000000000000,MIN('12_Datos_5m'!E14:E$504)) -> 1000000000000 | L13: =IF(COUNT('12_Datos_5m'!D14:D$504)=0,0,MAX('12_Datos_5m'!D14:D$504)) -> 0 | M13: =IF(ISNUMBER(B13),B13*(1-1/'13_Mapa_Liq'!$B$15+'13_Mapa_Liq'!$B$6),"") | N13: =IF(ISNUMBER(B13),IF(K13>M13,I13*'13_Mapa_Liq'!$C$15,0),0) -> 0 | O13: =IF(ISNUMBER(B13),B13*(1+1/'13_Mapa_Liq'!$B$15-'13_Mapa_Liq'!$B$6),"") | P13: =IF(ISNUMBER(B13),IF(L13<O13,J13*'13_Mapa_Liq'!$C$15,0),0) -> 0 | Q13: =IF(ISNUMBER(B13),B13*(1-1/'13_Mapa_Liq'!$B$16+'13_Mapa_Liq'!$B$6),"") | R13: =IF(ISNUMBER(B13),IF(K13>Q13,I13*'13_Mapa_Liq'!$C$16,0),0) -> 0 | S13: =IF(ISNUMBER(B13),B13*(1+1/'13_Mapa_Liq'!$B$16-'13_Mapa_Liq'!$B$6),"") | T13: =IF(ISNUMBER(B13),IF(L13<S13,J13*'13_Mapa_Liq'!$C$16,0),0) -> 0 | U13: =IF(ISNUMBER(B13),B13*(1-1/'13_Mapa_Liq'!$B$17+'13_Mapa_Liq'!$B$6),"") | V13: =IF(ISNUMBER(B13),IF(K13>U13,I13*'13_Mapa_Liq'!$C$17,0),0) -> 0 | W13: =IF(ISNUMBER(B13),B13*(1+1/'13_Mapa_Liq'!$B$17-'13_Mapa_Liq'!$B$6),"") | X13: =IF(ISNUMBER(B13),IF(L13<W13,J13*'13_Mapa_Liq'!$C$17,0),0) -> 0 | Y13: =IF(ISNUMBER(B13),B13*(1-1/'13_Mapa_Liq'!$B$18+'13_Mapa_Liq'!$B$6),"") | Z13: =IF(ISNUMBER(B13),IF(K13>Y13,I13*'13_Mapa_Liq'!$C$18,0),0) -> 0 | AA13: =IF(ISNUMBER(B13),B13*(1+1/'13_Mapa_Liq'!$B$18-'13_Mapa_Liq'!$B$6),"") | AB13: =IF(ISNUMBER(B13),IF(L13<AA13,J13*'13_Mapa_Liq'!$C$18,0),0) -> 0 | AC13: =IF(ISNUMBER(B13),B13*(1-1/'13_Mapa_Liq'!$B$19+'13_Mapa_Liq'!$B$6),"") | AD13: =IF(ISNUMBER(B13),IF(K13>AC13,I13*'13_Mapa_Liq'!$C$19,0),0) -> 0 | AE13: =IF(ISNUMBER(B13),B13*(1+1/'13_Mapa_Liq'!$B$19-'13_Mapa_Liq'!$B$6),"") | AF13: =IF(ISNUMBER(B13),IF(L13<AE13,J13*'13_Mapa_Liq'!$C$19,0),0) -> 0 | AH13: =IF(ISNUMBER(B13),E13*F13*((K13<=M13)*'13_Mapa_Liq'!$C$15+(K13<=Q13)*'13_Mapa_Liq'!$C$16+(K13<=U13)*'13_Mapa_Liq'!$C$17+(K13<=Y13)*'13_Mapa_Liq'!$C$18+(K13<=AC13)*'13_Mapa_Liq'!$C$19),0) -> 0 | AI13: =IF(ISNUMBER(B13),E13*(1-F13)*((L13>=O13)*'13_Mapa_Liq'!$C$15+(L13>=S13)*'13_Mapa_Liq'!$C$16+(L13>=W13)*'13_Mapa_Liq'!$C$17+(L13>=AA13)*'13_Mapa_Liq'!$C$18+(L13>=AE13)*'13_Mapa_Liq'!$C$19),0) -> 0
A14: =IF(ISNUMBER('12_Datos_5m'!F14),ROW()-4,"") | B14: =IF(ISNUMBER('12_Datos_5m'!F14),'12_Datos_5m'!F14,"") | C14: =IF(ISNUMBER('12_Datos_5m'!A14),'12_Datos_5m'!A14,"") | D14: =IF(AND(ISNUMBER('12_Datos_5m'!I14),ISNUMBER('12_Datos_5m'!I13)),'12_Datos_5m'!I14-'12_Datos_5m'!I13,0) -> 0 | E14: =MAX(0,D14) -> 0 | F14: =IF(AND(ISNUMBER('12_Datos_5m'!G14),N('12_Datos_5m'!G14)>0),'12_Datos_5m'!H14/'12_Datos_5m'!G14,0.5) -> 0.5 | G14: =IF(ISNUMBER(C14),($C$2-C14)/3600000,0) -> 0 | H14: =EXP(-G14/'13_Mapa_Liq'!$B$7) -> 1 | I14: =E14*F14*H14 -> 0 | J14: =E14*(1-F14)*H14 -> 0 | K14: =IF(COUNT('12_Datos_5m'!E15:E$504)=0,1000000000000,MIN('12_Datos_5m'!E15:E$504)) -> 1000000000000 | L14: =IF(COUNT('12_Datos_5m'!D15:D$504)=0,0,MAX('12_Datos_5m'!D15:D$504)) -> 0 | M14: =IF(ISNUMBER(B14),B14*(1-1/'13_Mapa_Liq'!$B$15+'13_Mapa_Liq'!$B$6),"") | N14: =IF(ISNUMBER(B14),IF(K14>M14,I14*'13_Mapa_Liq'!$C$15,0),0) -> 0 | O14: =IF(ISNUMBER(B14),B14*(1+1/'13_Mapa_Liq'!$B$15-'13_Mapa_Liq'!$B$6),"") | P14: =IF(ISNUMBER(B14),IF(L14<O14,J14*'13_Mapa_Liq'!$C$15,0),0) -> 0 | Q14: =IF(ISNUMBER(B14),B14*(1-1/'13_Mapa_Liq'!$B$16+'13_Mapa_Liq'!$B$6),"") | R14: =IF(ISNUMBER(B14),IF(K14>Q14,I14*'13_Mapa_Liq'!$C$16,0),0) -> 0 | S14: =IF(ISNUMBER(B14),B14*(1+1/'13_Mapa_Liq'!$B$16-'13_Mapa_Liq'!$B$6),"") | T14: =IF(ISNUMBER(B14),IF(L14<S14,J14*'13_Mapa_Liq'!$C$16,0),0) -> 0 | U14: =IF(ISNUMBER(B14),B14*(1-1/'13_Mapa_Liq'!$B$17+'13_Mapa_Liq'!$B$6),"") | V14: =IF(ISNUMBER(B14),IF(K14>U14,I14*'13_Mapa_Liq'!$C$17,0),0) -> 0 | W14: =IF(ISNUMBER(B14),B14*(1+1/'13_Mapa_Liq'!$B$17-'13_Mapa_Liq'!$B$6),"") | X14: =IF(ISNUMBER(B14),IF(L14<W14,J14*'13_Mapa_Liq'!$C$17,0),0) -> 0 | Y14: =IF(ISNUMBER(B14),B14*(1-1/'13_Mapa_Liq'!$B$18+'13_Mapa_Liq'!$B$6),"") | Z14: =IF(ISNUMBER(B14),IF(K14>Y14,I14*'13_Mapa_Liq'!$C$18,0),0) -> 0 | AA14: =IF(ISNUMBER(B14),B14*(1+1/'13_Mapa_Liq'!$B$18-'13_Mapa_Liq'!$B$6),"") | AB14: =IF(ISNUMBER(B14),IF(L14<AA14,J14*'13_Mapa_Liq'!$C$18,0),0) -> 0 | AC14: =IF(ISNUMBER(B14),B14*(1-1/'13_Mapa_Liq'!$B$19+'13_Mapa_Liq'!$B$6),"") | AD14: =IF(ISNUMBER(B14),IF(K14>AC14,I14*'13_Mapa_Liq'!$C$19,0),0) -> 0 | AE14: =IF(ISNUMBER(B14),B14*(1+1/'13_Mapa_Liq'!$B$19-'13_Mapa_Liq'!$B$6),"") | AF14: =IF(ISNUMBER(B14),IF(L14<AE14,J14*'13_Mapa_Liq'!$C$19,0),0) -> 0 | AH14: =IF(ISNUMBER(B14),E14*F14*((K14<=M14)*'13_Mapa_Liq'!$C$15+(K14<=Q14)*'13_Mapa_Liq'!$C$16+(K14<=U14)*'13_Mapa_Liq'!$C$17+(K14<=Y14)*'13_Mapa_Liq'!$C$18+(K14<=AC14)*'13_Mapa_Liq'!$C$19),0) -> 0 | AI14: =IF(ISNUMBER(B14),E14*(1-F14)*((L14>=O14)*'13_Mapa_Liq'!$C$15+(L14>=S14)*'13_Mapa_Liq'!$C$16+(L14>=W14)*'13_Mapa_Liq'!$C$17+(L14>=AA14)*'13_Mapa_Liq'!$C$18+(L14>=AE14)*'13_Mapa_Liq'!$C$19),0) -> 0
A15: =IF(ISNUMBER('12_Datos_5m'!F15),ROW()-4,"") | B15: =IF(ISNUMBER('12_Datos_5m'!F15),'12_Datos_5m'!F15,"") | C15: =IF(ISNUMBER('12_Datos_5m'!A15),'12_Datos_5m'!A15,"") | D15: =IF(AND(ISNUMBER('12_Datos_5m'!I15),ISNUMBER('12_Datos_5m'!I14)),'12_Datos_5m'!I15-'12_Datos_5m'!I14,0) -> 0 | E15: =MAX(0,D15) -> 0 | F15: =IF(AND(ISNUMBER('12_Datos_5m'!G15),N('12_Datos_5m'!G15)>0),'12_Datos_5m'!H15/'12_Datos_5m'!G15,0.5) -> 0.5 | G15: =IF(ISNUMBER(C15),($C$2-C15)/3600000,0) -> 0 | H15: =EXP(-G15/'13_Mapa_Liq'!$B$7) -> 1 | I15: =E15*F15*H15 -> 0 | J15: =E15*(1-F15)*H15 -> 0 | K15: =IF(COUNT('12_Datos_5m'!E16:E$504)=0,1000000000000,MIN('12_Datos_5m'!E16:E$504)) -> 1000000000000 | L15: =IF(COUNT('12_Datos_5m'!D16:D$504)=0,0,MAX('12_Datos_5m'!D16:D$504)) -> 0 | M15: =IF(ISNUMBER(B15),B15*(1-1/'13_Mapa_Liq'!$B$15+'13_Mapa_Liq'!$B$6),"") | N15: =IF(ISNUMBER(B15),IF(K15>M15,I15*'13_Mapa_Liq'!$C$15,0),0) -> 0 | O15: =IF(ISNUMBER(B15),B15*(1+1/'13_Mapa_Liq'!$B$15-'13_Mapa_Liq'!$B$6),"") | P15: =IF(ISNUMBER(B15),IF(L15<O15,J15*'13_Mapa_Liq'!$C$15,0),0) -> 0 | Q15: =IF(ISNUMBER(B15),B15*(1-1/'13_Mapa_Liq'!$B$16+'13_Mapa_Liq'!$B$6),"") | R15: =IF(ISNUMBER(B15),IF(K15>Q15,I15*'13_Mapa_Liq'!$C$16,0),0) -> 0 | S15: =IF(ISNUMBER(B15),B15*(1+1/'13_Mapa_Liq'!$B$16-'13_Mapa_Liq'!$B$6),"") | T15: =IF(ISNUMBER(B15),IF(L15<S15,J15*'13_Mapa_Liq'!$C$16,0),0) -> 0 | U15: =IF(ISNUMBER(B15),B15*(1-1/'13_Mapa_Liq'!$B$17+'13_Mapa_Liq'!$B$6),"") | V15: =IF(ISNUMBER(B15),IF(K15>U15,I15*'13_Mapa_Liq'!$C$17,0),0) -> 0 | W15: =IF(ISNUMBER(B15),B15*(1+1/'13_Mapa_Liq'!$B$17-'13_Mapa_Liq'!$B$6),"") | X15: =IF(ISNUMBER(B15),IF(L15<W15,J15*'13_Mapa_Liq'!$C$17,0),0) -> 0 | Y15: =IF(ISNUMBER(B15),B15*(1-1/'13_Mapa_Liq'!$B$18+'13_Mapa_Liq'!$B$6),"") | Z15: =IF(ISNUMBER(B15),IF(K15>Y15,I15*'13_Mapa_Liq'!$C$18,0),0) -> 0 | AA15: =IF(ISNUMBER(B15),B15*(1+1/'13_Mapa_Liq'!$B$18-'13_Mapa_Liq'!$B$6),"") | AB15: =IF(ISNUMBER(B15),IF(L15<AA15,J15*'13_Mapa_Liq'!$C$18,0),0) -> 0 | AC15: =IF(ISNUMBER(B15),B15*(1-1/'13_Mapa_Liq'!$B$19+'13_Mapa_Liq'!$B$6),"") | AD15: =IF(ISNUMBER(B15),IF(K15>AC15,I15*'13_Mapa_Liq'!$C$19,0),0) -> 0 | AE15: =IF(ISNUMBER(B15),B15*(1+1/'13_Mapa_Liq'!$B$19-'13_Mapa_Liq'!$B$6),"") | AF15: =IF(ISNUMBER(B15),IF(L15<AE15,J15*'13_Mapa_Liq'!$C$19,0),0) -> 0 | AH15: =IF(ISNUMBER(B15),E15*F15*((K15<=M15)*'13_Mapa_Liq'!$C$15+(K15<=Q15)*'13_Mapa_Liq'!$C$16+(K15<=U15)*'13_Mapa_Liq'!$C$17+(K15<=Y15)*'13_Mapa_Liq'!$C$18+(K15<=AC15)*'13_Mapa_Liq'!$C$19),0) -> 0 | AI15: =IF(ISNUMBER(B15),E15*(1-F15)*((L15>=O15)*'13_Mapa_Liq'!$C$15+(L15>=S15)*'13_Mapa_Liq'!$C$16+(L15>=W15)*'13_Mapa_Liq'!$C$17+(L15>=AA15)*'13_Mapa_Liq'!$C$18+(L15>=AE15)*'13_Mapa_Liq'!$C$19),0) -> 0
A16: =IF(ISNUMBER('12_Datos_5m'!F16),ROW()-4,"") | B16: =IF(ISNUMBER('12_Datos_5m'!F16),'12_Datos_5m'!F16,"") | C16: =IF(ISNUMBER('12_Datos_5m'!A16),'12_Datos_5m'!A16,"") | D16: =IF(AND(ISNUMBER('12_Datos_5m'!I16),ISNUMBER('12_Datos_5m'!I15)),'12_Datos_5m'!I16-'12_Datos_5m'!I15,0) -> 0 | E16: =MAX(0,D16) -> 0 | F16: =IF(AND(ISNUMBER('12_Datos_5m'!G16),N('12_Datos_5m'!G16)>0),'12_Datos_5m'!H16/'12_Datos_5m'!G16,0.5) -> 0.5 | G16: =IF(ISNUMBER(C16),($C$2-C16)/3600000,0) -> 0 | H16: =EXP(-G16/'13_Mapa_Liq'!$B$7) -> 1 | I16: =E16*F16*H16 -> 0 | J16: =E16*(1-F16)*H16 -> 0 | K16: =IF(COUNT('12_Datos_5m'!E17:E$504)=0,1000000000000,MIN('12_Datos_5m'!E17:E$504)) -> 1000000000000 | L16: =IF(COUNT('12_Datos_5m'!D17:D$504)=0,0,MAX('12_Datos_5m'!D17:D$504)) -> 0 | M16: =IF(ISNUMBER(B16),B16*(1-1/'13_Mapa_Liq'!$B$15+'13_Mapa_Liq'!$B$6),"") | N16: =IF(ISNUMBER(B16),IF(K16>M16,I16*'13_Mapa_Liq'!$C$15,0),0) -> 0 | O16: =IF(ISNUMBER(B16),B16*(1+1/'13_Mapa_Liq'!$B$15-'13_Mapa_Liq'!$B$6),"") | P16: =IF(ISNUMBER(B16),IF(L16<O16,J16*'13_Mapa_Liq'!$C$15,0),0) -> 0 | Q16: =IF(ISNUMBER(B16),B16*(1-1/'13_Mapa_Liq'!$B$16+'13_Mapa_Liq'!$B$6),"") | R16: =IF(ISNUMBER(B16),IF(K16>Q16,I16*'13_Mapa_Liq'!$C$16,0),0) -> 0 | S16: =IF(ISNUMBER(B16),B16*(1+1/'13_Mapa_Liq'!$B$16-'13_Mapa_Liq'!$B$6),"") | T16: =IF(ISNUMBER(B16),IF(L16<S16,J16*'13_Mapa_Liq'!$C$16,0),0) -> 0 | U16: =IF(ISNUMBER(B16),B16*(1-1/'13_Mapa_Liq'!$B$17+'13_Mapa_Liq'!$B$6),"") | V16: =IF(ISNUMBER(B16),IF(K16>U16,I16*'13_Mapa_Liq'!$C$17,0),0) -> 0 | W16: =IF(ISNUMBER(B16),B16*(1+1/'13_Mapa_Liq'!$B$17-'13_Mapa_Liq'!$B$6),"") | X16: =IF(ISNUMBER(B16),IF(L16<W16,J16*'13_Mapa_Liq'!$C$17,0),0) -> 0 | Y16: =IF(ISNUMBER(B16),B16*(1-1/'13_Mapa_Liq'!$B$18+'13_Mapa_Liq'!$B$6),"") | Z16: =IF(ISNUMBER(B16),IF(K16>Y16,I16*'13_Mapa_Liq'!$C$18,0),0) -> 0 | AA16: =IF(ISNUMBER(B16),B16*(1+1/'13_Mapa_Liq'!$B$18-'13_Mapa_Liq'!$B$6),"") | AB16: =IF(ISNUMBER(B16),IF(L16<AA16,J16*'13_Mapa_Liq'!$C$18,0),0) -> 0 | AC16: =IF(ISNUMBER(B16),B16*(1-1/'13_Mapa_Liq'!$B$19+'13_Mapa_Liq'!$B$6),"") | AD16: =IF(ISNUMBER(B16),IF(K16>AC16,I16*'13_Mapa_Liq'!$C$19,0),0) -> 0 | AE16: =IF(ISNUMBER(B16),B16*(1+1/'13_Mapa_Liq'!$B$19-'13_Mapa_Liq'!$B$6),"") | AF16: =IF(ISNUMBER(B16),IF(L16<AE16,J16*'13_Mapa_Liq'!$C$19,0),0) -> 0 | AH16: =IF(ISNUMBER(B16),E16*F16*((K16<=M16)*'13_Mapa_Liq'!$C$15+(K16<=Q16)*'13_Mapa_Liq'!$C$16+(K16<=U16)*'13_Mapa_Liq'!$C$17+(K16<=Y16)*'13_Mapa_Liq'!$C$18+(K16<=AC16)*'13_Mapa_Liq'!$C$19),0) -> 0 | AI16: =IF(ISNUMBER(B16),E16*(1-F16)*((L16>=O16)*'13_Mapa_Liq'!$C$15+(L16>=S16)*'13_Mapa_Liq'!$C$16+(L16>=W16)*'13_Mapa_Liq'!$C$17+(L16>=AA16)*'13_Mapa_Liq'!$C$18+(L16>=AE16)*'13_Mapa_Liq'!$C$19),0) -> 0
A17: =IF(ISNUMBER('12_Datos_5m'!F17),ROW()-4,"") | B17: =IF(ISNUMBER('12_Datos_5m'!F17),'12_Datos_5m'!F17,"") | C17: =IF(ISNUMBER('12_Datos_5m'!A17),'12_Datos_5m'!A17,"") | D17: =IF(AND(ISNUMBER('12_Datos_5m'!I17),ISNUMBER('12_Datos_5m'!I16)),'12_Datos_5m'!I17-'12_Datos_5m'!I16,0) -> 0 | E17: =MAX(0,D17) -> 0 | F17: =IF(AND(ISNUMBER('12_Datos_5m'!G17),N('12_Datos_5m'!G17)>0),'12_Datos_5m'!H17/'12_Datos_5m'!G17,0.5) -> 0.5 | G17: =IF(ISNUMBER(C17),($C$2-C17)/3600000,0) -> 0 | H17: =EXP(-G17/'13_Mapa_Liq'!$B$7) -> 1 | I17: =E17*F17*H17 -> 0 | J17: =E17*(1-F17)*H17 -> 0 | K17: =IF(COUNT('12_Datos_5m'!E18:E$504)=0,1000000000000,MIN('12_Datos_5m'!E18:E$504)) -> 1000000000000 | L17: =IF(COUNT('12_Datos_5m'!D18:D$504)=0,0,MAX('12_Datos_5m'!D18:D$504)) -> 0 | M17: =IF(ISNUMBER(B17),B17*(1-1/'13_Mapa_Liq'!$B$15+'13_Mapa_Liq'!$B$6),"") | N17: =IF(ISNUMBER(B17),IF(K17>M17,I17*'13_Mapa_Liq'!$C$15,0),0) -> 0 | O17: =IF(ISNUMBER(B17),B17*(1+1/'13_Mapa_Liq'!$B$15-'13_Mapa_Liq'!$B$6),"") | P17: =IF(ISNUMBER(B17),IF(L17<O17,J17*'13_Mapa_Liq'!$C$15,0),0) -> 0 | Q17: =IF(ISNUMBER(B17),B17*(1-1/'13_Mapa_Liq'!$B$16+'13_Mapa_Liq'!$B$6),"") | R17: =IF(ISNUMBER(B17),IF(K17>Q17,I17*'13_Mapa_Liq'!$C$16,0),0) -> 0 | S17: =IF(ISNUMBER(B17),B17*(1+1/'13_Mapa_Liq'!$B$16-'13_Mapa_Liq'!$B$6),"") | T17: =IF(ISNUMBER(B17),IF(L17<S17,J17*'13_Mapa_Liq'!$C$16,0),0) -> 0 | U17: =IF(ISNUMBER(B17),B17*(1-1/'13_Mapa_Liq'!$B$17+'13_Mapa_Liq'!$B$6),"") | V17: =IF(ISNUMBER(B17),IF(K17>U17,I17*'13_Mapa_Liq'!$C$17,0),0) -> 0 | W17: =IF(ISNUMBER(B17),B17*(1+1/'13_Mapa_Liq'!$B$17-'13_Mapa_Liq'!$B$6),"") | X17: =IF(ISNUMBER(B17),IF(L17<W17,J17*'13_Mapa_Liq'!$C$17,0),0) -> 0 | Y17: =IF(ISNUMBER(B17),B17*(1-1/'13_Mapa_Liq'!$B$18+'13_Mapa_Liq'!$B$6),"") | Z17: =IF(ISNUMBER(B17),IF(K17>Y17,I17*'13_Mapa_Liq'!$C$18,0),0) -> 0 | AA17: =IF(ISNUMBER(B17),B17*(1+1/'13_Mapa_Liq'!$B$18-'13_Mapa_Liq'!$B$6),"") | AB17: =IF(ISNUMBER(B17),IF(L17<AA17,J17*'13_Mapa_Liq'!$C$18,0),0) -> 0 | AC17: =IF(ISNUMBER(B17),B17*(1-1/'13_Mapa_Liq'!$B$19+'13_Mapa_Liq'!$B$6),"") | AD17: =IF(ISNUMBER(B17),IF(K17>AC17,I17*'13_Mapa_Liq'!$C$19,0),0) -> 0 | AE17: =IF(ISNUMBER(B17),B17*(1+1/'13_Mapa_Liq'!$B$19-'13_Mapa_Liq'!$B$6),"") | AF17: =IF(ISNUMBER(B17),IF(L17<AE17,J17*'13_Mapa_Liq'!$C$19,0),0) -> 0 | AH17: =IF(ISNUMBER(B17),E17*F17*((K17<=M17)*'13_Mapa_Liq'!$C$15+(K17<=Q17)*'13_Mapa_Liq'!$C$16+(K17<=U17)*'13_Mapa_Liq'!$C$17+(K17<=Y17)*'13_Mapa_Liq'!$C$18+(K17<=AC17)*'13_Mapa_Liq'!$C$19),0) -> 0 | AI17: =IF(ISNUMBER(B17),E17*(1-F17)*((L17>=O17)*'13_Mapa_Liq'!$C$15+(L17>=S17)*'13_Mapa_Liq'!$C$16+(L17>=W17)*'13_Mapa_Liq'!$C$17+(L17>=AA17)*'13_Mapa_Liq'!$C$18+(L17>=AE17)*'13_Mapa_Liq'!$C$19),0) -> 0
... A503: =IF(ISNUMBER('12_Datos_5m'!F503),ROW()-4,"") | B503: =IF(ISNUMBER('12_Datos_5m'!F503),'12_Datos_5m'!F503,"") | C503: =IF(ISNUMBER('12_Datos_5m'!A503),'12_Datos_5m'!A503,"") | D503: =IF(AND(ISNUMBER('12_Datos_5m'!I503),ISNUMBER('12_Datos_5m'!I502)),'12_Datos_5m'!I503-'12_Datos_5m'!I502,0) -> 0 | E503: =MAX(0,D503) -> 0 | F503: =IF(AND(ISNUMBER('12_Datos_5m'!G503),N('12_Datos_5m'!G503)>0),'12_Datos_5m'!H503/'12_Datos_5m'!G503,0.5) -> 0.5 | G503: =IF(ISNUMBER(C503),($C$2-C503)/3600000,0) -> 0 | H503: =EXP(-G503/'13_Mapa_Liq'!$B$7) -> 1 | I503: =E503*F503*H503 -> 0 | J503: =E503*(1-F503)*H503 -> 0 | K503: =IF(COUNT('12_Datos_5m'!E504:E$504)=0,1000000000000,MIN('12_Datos_5m'!E504:E$504)) -> 1000000000000 | L503: =IF(COUNT('12_Datos_5m'!D504:D$504)=0,0,MAX('12_Datos_5m'!D504:D$504)) -> 0 | M503: =IF(ISNUMBER(B503),B503*(1-1/'13_Mapa_Liq'!$B$15+'13_Mapa_Liq'!$B$6),"") | N503: =IF(ISNUMBER(B503),IF(K503>M503,I503*'13_Mapa_Liq'!$C$15,0),0) -> 0 | O503: =IF(ISNUMBER(B503),B503*(1+1/'13_Mapa_Liq'!$B$15-'13_Mapa_Liq'!$B$6),"") | P503: =IF(ISNUMBER(B503),IF(L503<O503,J503*'13_Mapa_Liq'!$C$15,0),0) -> 0 | Q503: =IF(ISNUMBER(B503),B503*(1-1/'13_Mapa_Liq'!$B$16+'13_Mapa_Liq'!$B$6),"") | R503: =IF(ISNUMBER(B503),IF(K503>Q503,I503*'13_Mapa_Liq'!$C$16,0),0) -> 0 | S503: =IF(ISNUMBER(B503),B503*(1+1/'13_Mapa_Liq'!$B$16-'13_Mapa_Liq'!$B$6),"") | T503: =IF(ISNUMBER(B503),IF(L503<S503,J503*'13_Mapa_Liq'!$C$16,0),0) -> 0 | U503: =IF(ISNUMBER(B503),B503*(1-1/'13_Mapa_Liq'!$B$17+'13_Mapa_Liq'!$B$6),"") | V503: =IF(ISNUMBER(B503),IF(K503>U503,I503*'13_Mapa_Liq'!$C$17,0),0) -> 0 | W503: =IF(ISNUMBER(B503),B503*(1+1/'13_Mapa_Liq'!$B$17-'13_Mapa_Liq'!$B$6),"") | X503: =IF(ISNUMBER(B503),IF(L503<W503,J503*'13_Mapa_Liq'!$C$17,0),0) -> 0 | Y503: =IF(ISNUMBER(B503),B503*(1-1/'13_Mapa_Liq'!$B$18+'13_Mapa_Liq'!$B$6),"") | Z503: =IF(ISNUMBER(B503),IF(K503>Y503,I503*'13_Mapa_Liq'!$C$18,0),0) -> 0 | AA503: =IF(ISNUMBER(B503),B503*(1+1/'13_Mapa_Liq'!$B$18-'13_Mapa_Liq'!$B$6),"") | AB503: =IF(ISNUMBER(B503),IF(L503<AA503,J503*'13_Mapa_Liq'!$C$18,0),0) -> 0 | AC503: =IF(ISNUMBER(B503),B503*(1-1/'13_Mapa_Liq'!$B$19+'13_Mapa_Liq'!$B$6),"") | AD503: =IF(ISNUMBER(B503),IF(K503>AC503,I503*'13_Mapa_Liq'!$C$19,0),0) -> 0 | AE503: =IF(ISNUMBER(B503),B503*(1+1/'13_Mapa_Liq'!$B$19-'13_Mapa_Liq'!$B$6),"") | AF503: =IF(ISNUMBER(B503),IF(L503<AE503,J503*'13_Mapa_Liq'!$C$19,0),0) -> 0 | AH503: =IF(ISNUMBER(B503),E503*F503*((K503<=M503)*'13_Mapa_Liq'!$C$15+(K503<=Q503)*'13_Mapa_Liq'!$C$16+(K503<=U503)*'13_Mapa_Liq'!$C$17+(K503<=Y503)*'13_Mapa_Liq'!$C$18+(K503<=AC503)*'13_Mapa_Liq'!$C$19),0) -> 0 | AI503: =IF(ISNUMBER(B503),E503*(1-F503)*((L503>=O503)*'13_Mapa_Liq'!$C$15+(L503>=S503)*'13_Mapa_Liq'!$C$16+(L503>=W503)*'13_Mapa_Liq'!$C$17+(L503>=AA503)*'13_Mapa_Liq'!$C$18+(L503>=AE503)*'13_Mapa_Liq'!$C$19),0) -> 0
A504: =IF(ISNUMBER('12_Datos_5m'!F504),ROW()-4,"") | B504: =IF(ISNUMBER('12_Datos_5m'!F504),'12_Datos_5m'!F504,"") | C504: =IF(ISNUMBER('12_Datos_5m'!A504),'12_Datos_5m'!A504,"") | D504: =IF(AND(ISNUMBER('12_Datos_5m'!I504),ISNUMBER('12_Datos_5m'!I503)),'12_Datos_5m'!I504-'12_Datos_5m'!I503,0) -> 0 | E504: =MAX(0,D504) -> 0 | F504: =IF(AND(ISNUMBER('12_Datos_5m'!G504),N('12_Datos_5m'!G504)>0),'12_Datos_5m'!H504/'12_Datos_5m'!G504,0.5) -> 0.5 | G504: =IF(ISNUMBER(C504),($C$2-C504)/3600000,0) -> 0 | H504: =EXP(-G504/'13_Mapa_Liq'!$B$7) -> 1 | I504: =E504*F504*H504 -> 0 | J504: =E504*(1-F504)*H504 -> 0 | K504: =1000000000000 -> 1000000000000 | L504: =0 -> 0 | M504: =IF(ISNUMBER(B504),B504*(1-1/'13_Mapa_Liq'!$B$15+'13_Mapa_Liq'!$B$6),"") | N504: =IF(ISNUMBER(B504),IF(K504>M504,I504*'13_Mapa_Liq'!$C$15,0),0) -> 0 | O504: =IF(ISNUMBER(B504),B504*(1+1/'13_Mapa_Liq'!$B$15-'13_Mapa_Liq'!$B$6),"") | P504: =IF(ISNUMBER(B504),IF(L504<O504,J504*'13_Mapa_Liq'!$C$15,0),0) -> 0 | Q504: =IF(ISNUMBER(B504),B504*(1-1/'13_Mapa_Liq'!$B$16+'13_Mapa_Liq'!$B$6),"") | R504: =IF(ISNUMBER(B504),IF(K504>Q504,I504*'13_Mapa_Liq'!$C$16,0),0) -> 0 | S504: =IF(ISNUMBER(B504),B504*(1+1/'13_Mapa_Liq'!$B$16-'13_Mapa_Liq'!$B$6),"") | T504: =IF(ISNUMBER(B504),IF(L504<S504,J504*'13_Mapa_Liq'!$C$16,0),0) -> 0 | U504: =IF(ISNUMBER(B504),B504*(1-1/'13_Mapa_Liq'!$B$17+'13_Mapa_Liq'!$B$6),"") | V504: =IF(ISNUMBER(B504),IF(K504>U504,I504*'13_Mapa_Liq'!$C$17,0),0) -> 0 | W504: =IF(ISNUMBER(B504),B504*(1+1/'13_Mapa_Liq'!$B$17-'13_Mapa_Liq'!$B$6),"") | X504: =IF(ISNUMBER(B504),IF(L504<W504,J504*'13_Mapa_Liq'!$C$17,0),0) -> 0 | Y504: =IF(ISNUMBER(B504),B504*(1-1/'13_Mapa_Liq'!$B$18+'13_Mapa_Liq'!$B$6),"") | Z504: =IF(ISNUMBER(B504),IF(K504>Y504,I504*'13_Mapa_Liq'!$C$18,0),0) -> 0 | AA504: =IF(ISNUMBER(B504),B504*(1+1/'13_Mapa_Liq'!$B$18-'13_Mapa_Liq'!$B$6),"") | AB504: =IF(ISNUMBER(B504),IF(L504<AA504,J504*'13_Mapa_Liq'!$C$18,0),0) -> 0 | AC504: =IF(ISNUMBER(B504),B504*(1-1/'13_Mapa_Liq'!$B$19+'13_Mapa_Liq'!$B$6),"") | AD504: =IF(ISNUMBER(B504),IF(K504>AC504,I504*'13_Mapa_Liq'!$C$19,0),0) -> 0 | AE504: =IF(ISNUMBER(B504),B504*(1+1/'13_Mapa_Liq'!$B$19-'13_Mapa_Liq'!$B$6),"") | AF504: =IF(ISNUMBER(B504),IF(L504<AE504,J504*'13_Mapa_Liq'!$C$19,0),0) -> 0 | AH504: =IF(ISNUMBER(B504),E504*F504*((K504<=M504)*'13_Mapa_Liq'!$C$15+(K504<=Q504)*'13_Mapa_Liq'!$C$16+(K504<=U504)*'13_Mapa_Liq'!$C$17+(K504<=Y504)*'13_Mapa_Liq'!$C$18+(K504<=AC504)*'13_Mapa_Liq'!$C$19),0) -> 0 | AI504: =IF(ISNUMBER(B504),E504*(1-F504)*((L504>=O504)*'13_Mapa_Liq'!$C$15+(L504>=S504)*'13_Mapa_Liq'!$C$16+(L504>=W504)*'13_Mapa_Liq'!$C$17+(L504>=AA504)*'13_Mapa_Liq'!$C$18+(L504>=AE504)*'13_Mapa_Liq'!$C$19),0) -> 0
